Workbook
Name AÑO: #REF!
Name AÑOVENTA: #REF!
Name BANCO: #REF!
Name CONTRATO: #REF!
Name MES: #REF!
Name MINUTAS: #REF!
Name PAZYSALVO: #REF!
Name PROTOCOLO: #REF!
Name RESIDENCIA: #REF!
Name RESIDENCIA2: #REF!
Name SINOPF: #REF!
Name STATUS: #REF!
Name STATUSBANCO: #REF!
Name VENDEDOR: #REF!

Sheet LISTA PRECIOS
A1: List de precios The Palms Ocean Front
A2: Ud. | B2: Nivel | C2: Modelo | D2: Apartamento | E2: Precio
A3: 1 | B3: 100 | C3: A | D3: 101 | E3: ='BASE DATOS'!AA48 -> 220862.25
A4: 2 | B4: 100 | C4: B | D4: 102 | E4: ='BASE DATOS'!AA49 -> 182000
A5: 3 | B5: 100 | C5: C | D5: 103 | E5: ='BASE DATOS'!AA50 -> 236000
A6: 4 | B6: 100 | C6: C | D6: 104 | E6: ='BASE DATOS'!AA51 -> 212650
A7: 5 | B7: 100 | C7: C | D7: 105 | E7: ='BASE DATOS'!AA52 -> 250000
A8: 6 | B8: 100 | C8: C | D8: 106 | E8: ='BASE DATOS'!AA53 -> 250000
A9: 7 | B9: 100 | C9: C | D9: 107 | E9: ='BASE DATOS'!AA54 -> 220000 | H9: Modelo | I9: Precio
A10: 8 | B10: 100 | C10: C | D10: 108 | E10: ='BASE DATOS'!AA55 -> 217000 | H10: A | I10: =E3+E13+E14+E25+E26+E37+E38+E48+E49+E59 -> 1834364.4
A11: 9 | B11: 100 | C11: C | D11: 109 | E11: ='BASE DATOS'!AA56 -> 221338.98 | H11: B | I11: =E4+E12+E15+E24+E27+E36+E39+E47+E50+E58 -> 1581604.4
A12: 10 | B12: 100 | C12: B | D12: 110 | E12: ='BASE DATOS'!AA57 -> 204000 | H12: C | I12: =E5+E6+E7+E8+E9+E10+E11+E16+E17+E18+E19+E20+E21+E22+E23 -> 3080889
A13: 11 | B13: 100 | C13: A | D13: 111 | E13: ='BASE DATOS'!AA58 -> 194230.69 | F13: =SUM(E3:E13) -> 2408081.9 | H13: C1 | I13: =E28+E29+E30+E31+E32+E33+E34+E35+E40+E41+E42+E43+E46+E51+E52+E53+E54+E57 -> 3452877.8
A14: 12 | B14: 200 | C14: A | D14: 201 | E14: ='BASE DATOS'!AA36 -> 202000 | H14: D | I14: =E44+E45+E55+E56 -> 1097683.5
A15: 13 | B15: 200 | C15: B | D15: 202 | E15: ='BASE DATOS'!AA37 -> 137862 | H15: Total | I15: =SUM(I10:I14) -> 11047419
A16: 14 | B16: 200 | C16: C | D16: 203 | E16: ='BASE DATOS'!AA38 -> 179900
A17: 15 | B17: 200 | C17: C | D17: 204 | E17: ='BASE DATOS'!AA39 -> 184000
A18: 16 | B18: 200 | C18: C | D18: 205 | E18: ='BASE DATOS'!AA40 -> 194000
A19: 17 | B19: 200 | C19: C | D19: 206 | E19: ='BASE DATOS'!AA41 -> 204000
A20: 18 | B20: 200 | C20: C | D20: 207 | E20: ='BASE DATOS'!AA42 -> 201000
A21: 19 | B21: 200 | C21: C | D21: 208 | E21: ='BASE DATOS'!AA43 -> 201000
A22: 20 | B22: 200 | C22: C | D22: 209 | E22: ='BASE DATOS'!AA44 -> 130000
A23: 21 | B23: 200 | C23: C | D23: 210 | E23: ='BASE DATOS'!AA45 -> 180000
A24: 22 | B24: 200 | C24: B | D24: 211 | E24: ='BASE DATOS'!AA46 -> 143389.44
A25: 23 | B25: 200 | C25: A | D25: 212 | E25: ='BASE DATOS'!AA47 -> 185000 | F25: =SUM(E14:E25) -> 2142151.4
A26: 24 | B26: 300 | C26: A | D26: 301 | E26: ='BASE DATOS'!AA24 -> 202000
A27: 25 | B27: 300 | C27: B | D27: 302 | E27: ='BASE DATOS'!AA25 -> 145000
A28: 26 | B28: 300 | C28: C1 | D28: 303 | E28: ='BASE DATOS'!AA26 -> 187000
A29: 27 | B29: 300 | C29: C1 | D29: 304 | E29: ='BASE DATOS'!AA27 -> 183000
A30: 28 | B30: 300 | C30: C1 | D30: 305 | E30: ='BASE DATOS'!AA28 -> 187976.82
A31: 29 | B31: 300 | C31: C1 | D31: 306 | E31: ='BASE DATOS'!AA29 -> 198850
A32: 30 | B32: 300 | C32: C1 | D32: 307 | E32: ='BASE DATOS'!AA30 -> 187000
A33: 31 | B33: 300 | C33: C1 | D33: 308 | E33: ='BASE DATOS'!AA31 -> 185000
A34: 32 | B34: 300 | C34: C1 | D34: 309 | E34: ='BASE DATOS'!AA32 -> 180000
A35: 33 | B35: 300 | C35: C1 | D35: 310 | E35: ='BASE DATOS'!AA33 -> 185000
A36: 34 | B36: 300 | C36: B | D36: 311 | E36: ='BASE DATOS'!AA34 -> 150000
A37: 35 | B37: 300 | C37: A | D37: 312 | E37: ='BASE DATOS'!AA35 -> 172500 | F37: =SUM(E26:E37) -> 2163326.8
A38: 36 | B38: 400 | C38: A | D38: 401 | E38: ='BASE DATOS'!AA13 -> 160000
A39: 37 | B39: 400 | C39: B | D39: 402 | E39: ='BASE DATOS'!AA14 -> 152500
A40: 38 | B40: 400 | C40: C1 | D40: 403 | E40: ='BASE DATOS'!AA15 -> 185270
A41: 39 | B41: 400 | C41: C1 | D41: 404 | E41: ='BASE DATOS'!AA16 -> 191892.6
A42: 40 | B42: 400 | C42: C1 | D42: 405 | E42: ='BASE DATOS'!AA17 -> 180000
A43: 41 | B43: 400 | C43: C1 | D43: 406 | E43: ='BASE DATOS'!AA18 -> 205422.3
A44: 42 | B44: 400 | C44: D | D44: 407 | E44: ='BASE DATOS'!AA19 -> 299000
A45: 43 | B45: 400 | C45: D | D45: 408 | E45: ='BASE DATOS'!AA20 -> 250000
A46: 44 | B46: 400 | C46: C1 | D46: 409 | E46: ='BASE DATOS'!AA21 -> 205000
A47: 45 | B47: 400 | C47: B | D47: 410 | E47: ='BASE DATOS'!AA22 -> 146853
A48: 46 | B48: 400 | C48: A | D48: 411 | E48: ='BASE DATOS'!AA23 -> 161528.5 | F48: =SUM(E38:E48) -> 2137466.4
A49: 47 | B49: 500 | C49: A | D49: 501 | E49: ='BASE DATOS'!AA2 -> 168121.5
A50: 48 | B50: 500 | C50: B | D50: 502 | E50: ='BASE DATOS'!AA3 -> 170000
A51: 49 | B51: 500 | C51: C1 | D51: 503 | E51: ='BASE DATOS'!AA4 -> 205107.09
A52: 50 | B52: 500 | C52: C1 | D52: 504 | E52: ='BASE DATOS'!AA5 -> 204500
A53: 51 | B53: 500 | C53: C1 | D53: 505 | E53: ='BASE DATOS'!AA6 -> 186379.5
A54: 52 | B54: 500 | C54: C1 | D54: 506 | E54: ='BASE DATOS'!AA7 -> 209100
A55: 53 | B55: 500 | C55: D | D55: 507 | E55: ='BASE DATOS'!AA8 -> 270000
A56: 54 | B56: 500 | C56: D | D56: 508 | E56: ='BASE DATOS'!AA9 -> 278683.5
A57: 55 | B57: 500 | C57: C1 | D57: 509 | E57: ='BASE DATOS'!AA10 -> 186379.5
A58: 56 | B58: 500 | C58: B | D58: 510 | E58: ='BASE DATOS'!AA11 -> 150000
A59: 57 | B59: 500 | C59: A | D59: 511 | E59: ='BASE DATOS'!AA12 -> 168121.5 | F59: =SUM(E49:E59) -> 2196392.6
A60: Total | E60: =SUM(E3:E59) -> 11047419
E61: 10867180 | G61: =E15+E24+E26+E27+E37+E38+E39+E43+E44+E45+E46+E47+E48+E49+E51+E53+E54+E55+E56+E57+E58+E59 -> 4202947.8
E62: =E61-E60 -> -180239.17
E64: =151135-145000 -> 6135

Sheet BASE DATOS
A1: UNIDAD APTO | B1: NIVEL | C1: CLIENTE | D1: RESERVADAS, VENDIDAS | E1: ESTATUS | F1: FECHA DE RESERVA | G1: NÚMERO DE IDENTIDAD | H1: NACIONALIDAD | I1: CLASIFCACIÓN | J1: BROKER | K1: FECHA NACIMIENTO | L1: PERFIL DE INGRESOS | M1: PROFESION | N1: FORMA DE PAGO | O1: PAQUETE DE MUEBLES | P1: EXTRAS | Q1: INCLUIDO EN PRECIO DE VENTA | R1: VALOR DEL PAQUETE | S1: MODELO | T1: AREA CERRADA | U1: AREA BALCON | V1: AREA TOTAL CUANTIFICABLE | W1: VALOR DE BALCON | X1: VALOR DE VENTA DE AREA CERRADA | Y1: CARGO ADICIONAL | Z1: AJUSTE | AA1: VALOR TOTAL | AB1: PRECIO X M2 | AC1: PORCENTAJE ABONADO | AD1: ABONOS RECIBIDOS | AE1: MONTO A GISA | AF1: MONTO A MULTIBANK | AG1: SALDO PENDIENTE | AH1: ESTATUS DE PAGO | AI1: BANCO | AJ1: OFICIAL DE TRÁMITE | AK1: CONTACTO OFICIAL | AL1: ESTATUS2 | AM1: FECHA DE EMISION DE CPP | AN1: FECHA DE VENCIMIENTO CPP | AO1: COMENTARIOS | AP1: MONTO CPP | AQ1: RESERVAS, VENDIDAS | AR1: FECHA DE CONTRATO | AS1: PRECIO DE CONTRATO DE COMPRA Y VENTA | AT1: NUMERO FINCA | AU1: GASTOS LEGALES | AV1: MONTO5 | AW1: SALDO PENDIENTE3 | AX1: ESTATUS6 | AY1: COMENTARIOS ESTATUS LEGAL | AZ1: SOLICITUD DE MINUTA LIBERACIÓN | BA1: MINUTA LIBERACIÓN | BB1: FECHA RECIBIDO MINUTA LIBERACION | BC1: DIAS TRANSCURRIDOS MINUTA LIBERACIÓN | BD1: MINUTA DE VENTA | BE1: FECHA EMISION MINUTA VENTA | BF1: MINUTA DE PRESTAMO | BG1: ACTIVACIÓN DE TRAMITE | BH1: SOLICITUD DE AVALUO | BI1: FECHA DE INSPECCIÓN DE AVALUO | BJ1: ENCARGADO DE AVALUO | BK1: CONFECCION DE PROTOCOLO | BL1: FIRMA CLIENTE | BM1: FIRMA PROMOTOR | BN1: ENVIO A INTERINO | BO1: RECEPCIÓN INTERINO | BP1: DIAS TRANSCURRIDOS INTERINO | BQ1: PAGO IMPUESTO | BR1: IDAAN | BS1: INMUEBLE | BT1: PH | BU1: BANCO CLIENTE | BV1: NOTARIA | BW1: RECEPCIÓN DE NOTARIA | BX1: CIERRE DE NOTARIA | BY1: INGRESO REGISTRO | BZ1: INSCRIPCIÓN REGISTRO | CA1: SOLICITUD DE DESEMBOLSO | CB1: DESEMBOLSO | CC1: FECHA DE ENTREGA
A2: L-501 | B2: 000 | C2: KEVIN FORSYTH | D2: TRASPASADO | E2: INSCRITO Y DESEMBOLSADO | F2: 44986 | G2: HD802468 | H2: CANADIENSE | I2: EXTRANJERO NO RESIDENTE | J2: PANAMA PACIFICA REALTY | K2: 25351 | L2: INDEPENDIENTE | M2: ADMINISTRADOR DE EMPRESAS | N2: CONTADO | O2: SI | P2: SI | Q2: NO | S2: A | T2: 65.93 | U2: 0 | V2: =U2+T2 -> 65.93 | X2: =AB2*T2 -> 168121.5 | AA2: =X2+W2+Y2+Z2 -> 168121.5 | AB2: 2550 | AC2: =((AD2*1)/AA2) -> 1 | AD2: =SUMIFS(Tabla35[Abonos],Tabla35[Lote],Tabla4[[#This Row],[UNIDAD APTO]],Tabla35[Cliente],Tabla4[[#This Row],[CLIENTE]],Tabla35[Concepto],"ABONO")+SUMIFS(Tabla35[Abonos],Tabla35[Lote],Tabla4[[#This Row],[UNIDAD APTO]],Tabla35[Cliente],Tabla4[[#This Row],[CLIENTE]],Tabla35[Concepto],"MULTIBANK") -> 168121.5 | AE2: =Tabla4[[#This Row],[VALOR TOTAL]]-Tabla4[[#This Row],[MONTO A MULTIBANK]] -> 50461.45 | AF2: 117660.05 | AG2: =ABONOS!E3 -> 0 | AH2: {=_xlfn.IFS(Tabla4[[#This Row],[RESERVADAS, VENDIDAS]]="DISPONIBLE","",Tabla4[[#This Row],[SALDO PENDIENTE]]=0,"PAZ Y SALVO",Tabla4[[#This Row],[SALDO PENDIENTE]]=Tabla4[[#This Row],[MONTO CPP]],"COBRO CPP",Tabla4[[#This Row],[SALDO PENDIENTE]]>0,"PENDIENTE")} -> PAZ Y SALVO | AI2: N/A | AJ2: N/A | AK2: N/A | AL2: N/A | AM2: N/A | AN2: N/A | AO2: N/A | AP2: N/A | AQ2: Reservada - Con Contrato | AR2: 45073 | AS2: =AA2 -> 168121.5 | AT2: 30474571 | AU2: GISA | AV2: 1600 | AW2: =ABONOS!O3 -> 0 | AX2: {=_xlfn.IFS(Tabla4[[#This Row],[MONTO5]]=0,"",Tabla4[[#This Row],[SALDO PENDIENTE3]]=0,"PAZ Y SALVO",Tabla4[[#This Row],[SALDO PENDIENTE3]]>0,"PENDIENTE")} -> PAZ Y SALVO | AY2: INSCRITA Y DESEMBOLSADA | AZ2: 45428 | BA2: SI | BB2: 45449 | BC2: =Tabla4[[#This Row],[FECHA RECIBIDO MINUTA LIBERACION]]-Tabla4[[#This Row],[SOLICITUD DE MINUTA LIBERACIÓN]] -> 21 | BD2: SI | BE2: 45440 | BF2: N/A | BG2: N/A | BH2: N/A | BI2: N/A | BJ2: N/A | BK2: 45469 | BL2: 45480 | BM2: 45469 | BN2: 45481 | BO2: 45485 | BP2: =Tabla4[[#This Row],[RECEPCIÓN INTERINO]]-Tabla4[[#This Row],[ENVIO A INTERINO]] -> 4 | BQ2: 45874 | BR2: 45859 | BS2: 45874 | BT2: 45876 | BU2: N/A | BV2: SI | BW2: 45883 | BX2: 45883 | BY2: 45883 | BZ2: 45909 | CA2: N/A | CB2: N/A | CC2: 45377
A3: L-502 | B3: 000 | C3: LANCE Y RADANA MORGAN | D3: TRASPASADO | E3: INSCRITO Y DESEMBOLSADO | F3: 45505 | G3: 571322934 | H3: CANADIENSE | I3: EXTRANJERO NO RESIDENTE | J3: KOYNE | K3: 24967 | L3: INDEPENDIENTE | M3: TECNICO ELECTRODOMESTICOS / ENFERMERA | N3: CONTADO | O3: SI | P3: SI | Q3: SI | S3: B | T3: 59.94 | U3: 0 | V3: =U3+T3 -> 59.94 | X3: =AB3*T3 -> 152847 | AA3: 170000 | AB3: 2550 | AC3: =((AD3*1)/AA3) -> 1 | AD3: =SUMIFS(Tabla35[Abonos],Tabla35[Lote],Tabla4[[#This Row],[UNIDAD APTO]],Tabla35[Cliente],Tabla4[[#This Row],[CLIENTE]],Tabla35[Concepto],"ABONO")+SUMIFS(Tabla35[Abonos],Tabla35[Lote],Tabla4[[#This Row],[UNIDAD APTO]],Tabla35[Cliente],Tabla4[[#This Row],[CLIENTE]],Tabla35[Concepto],"MULTIBANK") -> 170000 | AE3: =Tabla4[[#This Row],[VALOR TOTAL]]-Tabla4[[#This Row],[MONTO A MULTIBANK]] -> 51000 | AF3: =AA3*70% -> 119000 | AG3: =ABONOS!E4 -> 0 | AH3: {=_xlfn.IFS(Tabla4[[#This Row],[RESERVADAS, VENDIDAS]]="DISPONIBLE","",Tabla4[[#This Row],[SALDO PENDIENTE]]=0,"PAZ Y SALVO",Tabla4[[#This Row],[SALDO PENDIENTE]]=Tabla4[[#This Row],[MONTO CPP]],"COBRO CPP",Tabla4[[#This Row],[SALDO PENDIENTE]]>0,"PENDIENTE")} -> PAZ Y SALVO | AI3: N/A | AJ3: N/A | AK3: N/A | AL3: N/A | AM3: N/A | AN3: N/A | AO3: N/A | AP3: N/A | AQ3: Reservada - Con Contrato | AR3: 45519 | AS3: =AA3 -> 170000 | AT3: 30474570 | AU3: GISA | AV3: 1900 | AW3: =ABONOS!O4 -> 0 | AX3: {=_xlfn.IFS(Tabla4[[#This Row],[MONTO5]]=0,"",Tabla4[[#This Row],[SALDO PENDIENTE3]]=0,"PAZ Y SALVO",Tabla4[[#This Row],[SALDO PENDIENTE3]]>0,"PENDIENTE")} -> PAZ Y SALVO | AY3: INSCRITA Y DESEMBOLSADA | AZ3: 45528 | BA3: SI | BB3: 45552 | BC3: =Tabla4[[#This Row],[FECHA RECIBIDO MINUTA LIBERACION]]-Tabla4[[#This Row],[SOLICITUD DE MINUTA LIBERACIÓN]] -> 24 | BD3: SI | BE3: 45549 | BF3: N/A | BG3: N/A | BH3: N/A | BI3: N/A | BJ3: N/A | BK3: 45560 | BL3: 45596 | BM3: 45561 | BN3: 45604 | BO3: 45611 | BP3: =Tabla4[[#This Row],[RECEPCIÓN INTERINO]]-Tabla4[[#This Row],[ENVIO A INTERINO]] -> 7 | BQ3: 45622 | BR3: 45614 | BS3: 45611 | BT3: 45611 | BU3: N/A | BV3: SI | BW3: 45561 | BX3: 45622 | BY3: 45623 | BZ3: 45631 | CA3: N/A | CB3: N/A | CC3: 45600
A4: L-503 | B4: 000 | C4: AARON Y MARSHA EDWARDS | D4: TRASPASADO | E4: INSCRITO Y DESEMBOLSADO | F4: 45200 | G4: 8-1137-1326 | H4: PANAMEÑA | I4: NACIONAL | J4: PANAMA PACIFICA REALTY | K4: 28787 | L4: ASALARIADO | M4: EDUCADOR / DOCTORA | N4: FINANCIAMIENTO | O4: SI | P4: NO | Q4: SI | R4: 15000 | S4: C1 | T4: 73.09 | U4: 0 | V4: =U4+T4 -> 73.09 | X4: =AB4*T4 -> 186379.5 | AA4: 205107.09 | AB4: 2550 | AC4: =((AD4*1)/AA4) -> 1 | AD4: =SUMIFS(Tabla35[Abonos],Tabla35[Lote],Tabla4[[#This Row],[UNIDAD APTO]],Tabla35[Cliente],Tabla4[[#This Row],[CLIENTE]],Tabla35[Concepto],"ABONO")+SUMIFS(Tabla35[Abonos],Tabla35[Lote],Tabla4[[#This Row],[UNIDAD APTO]],Tabla35[Cliente],Tabla4[[#This Row],[CLIENTE]],Tabla35[Concepto],"MULTIBANK") -> 205107.09 | AE4: =Tabla4[[#This Row],[VALOR TOTAL]]-Tabla4[[#This Row],[MONTO A MULTIBANK]] -> 61532.13 | AF4: =Tabla4[[#This Row],[MONTO CPP]] -> 143574.96 | AG4: =ABONOS!E5 -> 0 | AH4: {=_xlfn.IFS(Tabla4[[#This Row],[RESERVADAS, VENDIDAS]]="DISPONIBLE","",Tabla4[[#This Row],[SALDO PENDIENTE]]=0,"PAZ Y SALVO",Tabla4[[#This Row],[SALDO PENDIENTE]]=Tabla4[[#This Row],[MONTO CPP]],"COBRO CPP",Tabla4[[#This Row],[SALDO PENDIENTE]]>0,"PENDIENTE")} -> PAZ Y SALVO | AI4: UNIBANK | AJ4: MONICA OSES | AK4: monica.oses@unibank.com.pa / 6997-8248 | AL4: CON CPP | AM4: 45275 | AN4: N/A | AO4: N/A | AP4: 143574.96 | AQ4: Reservada - Con Contrato | AR4: 45215 | AS4: =AA4 -> 205107.09 | AT4: 30474569 | AU4: UNIBANK | AV4: 5858.13 | AW4: =ABONOS!O5 -> 0 | AX4: {=_xlfn.IFS(Tabla4[[#This Row],[MONTO5]]=0,"",Tabla4[[#This Row],[SALDO PENDIENTE3]]=0,"PAZ Y SALVO",Tabla4[[#This Row],[SALDO PENDIENTE3]]>0,"PENDIENTE")} -> PAZ Y SALVO | AY4: INSCRITA Y DESEMBOLSADA | AZ4: 45492 | BA4: SI | BB4: 45506 | BC4: =Tabla4[[#This Row],[FECHA RECIBIDO MINUTA LIBERACION]]-Tabla4[[#This Row],[SOLICITUD DE MINUTA LIBERACIÓN]] -> 14 | BD4: SI | BE4: 45440 | BF4: SI | BG4: 45499 | BH4: 45499 | BI4: N/A | BJ4: N/A | BK4: 45532 | BL4: 45566 | BM4: 45568 | BN4: 45566 | BO4: 45572 | BP4: =Tabla4[[#This Row],[RECEPCIÓN INTERINO]]-Tabla4[[#This Row],[ENVIO A INTERINO]] -> 6 | BQ4: 45568 | BR4: 45579 | BS4: 45568 | BT4: 45568 | BU4: 45573 | BV4: SI | BW4: N/A | BX4: 45573 | BY4: 45586 | BZ4: 45595 | CA4: 45595 | CB4: 45604 | CC4: 45674
A5: L-504 | B5: 000 | C5: GEORGE WALES Y MAUZIE-LISA WALES | D5: TRASPASADO | E5: INSCRITO Y DESEMBOLSADO | F5: 45580 | G5: RA2827279 / RA2832821 | H5: AUSTRALIANA | I5: EXTRANJERO NO RESIDENTE | J5: PANAMA PACIFICA REALTY | K5: 21194 | L5: INDEPENDIENTE | M5: AGENTE DE VIAJES | N5: CONTADO | O5: SI | P5: NO | Q5: SI | R5: 13500 | S5: C1 | T5: 73.09 | U5: 0 | V5: =U5+T5 -> 73.09 | X5: =AB5*T5 -> 186379.5 | AA5: 204500 | AB5: 2550 | AC5: =((AD5*1)/AA5) -> 1.0000024 | AD5: =SUMIFS(Tabla35[Abonos],Tabla35[Lote],Tabla4[[#This Row],[UNIDAD APTO]],Tabla35[Cliente],Tabla4[[#This Row],[CLIENTE]],Tabla35[Concepto],"ABONO")+SUMIFS(Tabla35[Abonos],Tabla35[Lote],Tabla4[[#This Row],[UNIDAD APTO]],Tabla35[Cliente],Tabla4[[#This Row],[CLIENTE]],Tabla35[Concepto],"MULTIBANK") -> 204500.5 | AE5: =Tabla4[[#This Row],[VALOR TOTAL]]-Tabla4[[#This Row],[MONTO A MULTIBANK]] -> 204500 | AF5: 0 | AG5: =ABONOS!E6 -> -0.5 | AH5: {=_xlfn.IFS(Tabla4[[#This Row],[RESERVADAS, VENDIDAS]]="DISPONIBLE","",Tabla4[[#This Row],[SALDO PENDIENTE]]=0,"PAZ Y SALVO",Tabla4[[#This Row],[SALDO PENDIENTE]]=Tabla4[[#This Row],[MONTO CPP]],"COBRO CPP",Tabla4[[#This Row],[SALDO PENDIENTE]]>0,"PENDIENTE")} -> #N/A | AI5: N/A | AJ5: N/A | AK5: N/A | AL5: N/A | AM5: N/A | AN5: N/A | AO5: N/A | AP5: N/A | AQ5: Reservada - Con Contrato | AR5: 45627 | AS5: =AA5 -> 204500 | AT5: 30474568 | AU5: GISA | AV5: 2070 | AW5: =ABONOS!O6 -> 0 | AX5: {=_xlfn.IFS(Tabla4[[#This Row],[MONTO5]]=0,"",Tabla4[[#This Row],[SALDO PENDIENTE3]]=0,"PAZ Y SALVO",Tabla4[[#This Row],[SALDO PENDIENTE3]]>0,"PENDIENTE")} -> PAZ Y SALVO | AY5: INSCRITA Y DESEMBOLSADA | AZ5: 45954 | BA5: SI | BB5: 45961 | BC5: =Tabla4[[#This Row],[FECHA RECIBIDO MINUTA LIBERACION]]-Tabla4[[#This Row],[SOLICITUD DE MINUTA LIBERACIÓN]] -> 7 | BD5: SI | BE5: 45969 | BF5: N/A | BG5: N/A | BH5: N/A | BI5: N/A | BJ5: N | BK5: 45969 | BL5: 45975 | BM5: 45975 | BN5: 45975 | BO5: 45984 | BP5: =Tabla4[[#This Row],[RECEPCIÓN INTERINO]]-Tabla4[[#This Row],[ENVIO A INTERINO]] -> 9 | BQ5: 45985 | BR5: 45968 | BS5: 45986 | BT5: 45986 | BU5: N/A | BV5: SI | BW5: 45975 | BX5: 45988 | BY5: 45988 | BZ5: 45992 | CA5: N/A | CB5: N/A | CC5: 45946
A6: L-505 | B6: 000 | C6: ALCIBIADES SOLIS | D6: TRASPASADO | E6: INSCRITO Y DESEMBOLSADO | F6: 45108 | G6: 6-700-2182 | H6: PANAMEÑA | I6: NACIONAL | J6: GESPROBAN | K6: 28088 | L6: ASALARIADO | M6: MEDICO | N6: CONTADO | O6: SI | P6: NO | Q6: NO | R6: 15000 | S6: C1 | T6: 73.09 | U6: 0 | V6: =U6+T6 -> 73.09 | X6: =AB6*T6 -> 186379.5 | AA6: =X6+W6+Y6+Z6 -> 186379.5 | AB6: 2550 | AC6: =((AD6*1)/AA6) -> 1 | AD6: =SUMIFS(Tabla35[Abonos],Tabla35[Lote],Tabla4[[#This Row],[UNIDAD APTO]],Tabla35[Cliente],Tabla4[[#This Row],[CLIENTE]],Tabla35[Concepto],"ABONO")+SUMIFS(Tabla35[Abonos],Tabla35[Lote],Tabla4[[#This Row],[UNIDAD APTO]],Tabla35[Cliente],Tabla4[[#This Row],[CLIENTE]],Tabla35[Concepto],"MULTIBANK") -> 186379.5 | AE6: =Tabla4[[#This Row],[VALOR TOTAL]]-Tabla4[[#This Row],[MONTO A MULTIBANK]] -> 55913.85 | AF6: =AA6*70% -> 130465.65 | AG6: =ABONOS!E7 -> 0 | AH6: {=_xlfn.IFS(Tabla4[[#This Row],[RESERVADAS, VENDIDAS]]="DISPONIBLE","",Tabla4[[#This Row],[SALDO PENDIENTE]]=0,"PAZ Y SALVO",Tabla4[[#This Row],[SALDO PENDIENTE]]=Tabla4[[#This Row],[MONTO CPP]],"COBRO CPP",Tabla4[[#This Row],[SALDO PENDIENTE]]>0,"PENDIENTE")} -> PAZ Y SALVO | AI6: N/A | AJ6: N/A | AK6: N/A | AL6: N/A | AM6: N/A | AN6: N/A | AO6: N/A | AP6: N/A | AQ6: Reservada - Con Contrato | AR6: 45054 | AS6: =AA6 -> 186379.5 | AT6: 30474567 | AU6: GISA | AV6: 1400 | AW6: =ABONOS!O7 -> 0 | AX6: {=_xlfn.IFS(Tabla4[[#This Row],[MONTO5]]=0,"",Tabla4[[#This Row],[SALDO PENDIENTE3]]=0,"PAZ Y SALVO",Tabla4[[#This Row],[SALDO PENDIENTE3]]>0,"PENDIENTE")} -> PAZ Y SALVO | AY6: INSCRITA Y DESEMBOLSADA | AZ6: 45428 | BA6: SI | BB6: 45449 | BC6: =Tabla4[[#This Row],[FECHA RECIBIDO MINUTA LIBERACION]]-Tabla4[[#This Row],[SOLICITUD DE MINUTA LIBERACIÓN]] -> 21 | BD6: SI | BE6: 45450 | BF6: N/A | BG6: N/A | BH6: N/A | BI6: N/A | BJ6: N/A | BK6: 45449 | BL6: 45458 | BM6: 45454 | BN6: 45461 | BO6: 45469 | BP6: =Tabla4[[#This Row],[RECEPCIÓN INTERINO]]-Tabla4[[#This Row],[ENVIO A INTERINO]] -> 8 | BQ6: 45471 | BR6: 45485 | BS6: 45469 | BT6: 45470 | BU6: N/A | BV6: SI | BW6: 45450 | BX6: 45475 | BY6: 45358 | BZ6: 45488 | CA6: N/A | CB6: N/A | CC6: 45422
A7: L-506 | B7: 000 | C7: ERIC WHITAKER | D7: TRASPASADO | E7: INSCRITO Y DESEMBOLSADO | F7: 45139 | G7: 674360401 | H7: ESTADOUNIDENSE | I7: EXTRANJERO NO RESIDENTE | J7: DOO PANAMA | K7: 29184 | L7: INDEPENDIENTE | M7: TERAPEUTA | N7: CONTADO | O7: SI | P7: NO | Q7: SI | S7: C1 | T7: 73.96 | U7: 0 | V7: =U7+T7 -> 73.96 | X7: 209100 | AA7: =X7+W7+Y7+Z7 -> 209100 | AB7: 2550 | AC7: =((AD7*1)/AA7) -> 1 | AD7: =SUMIFS(Tabla35[Abonos],Tabla35[Lote],Tabla4[[#This Row],[UNIDAD APTO]],Tabla35[Cliente],Tabla4[[#This Row],[CLIENTE]],Tabla35[Concepto],"ABONO")+SUMIFS(Tabla35[Abonos],Tabla35[Lote],Tabla4[[#This Row],[UNIDAD APTO]],Tabla35[Cliente],Tabla4[[#This Row],[CLIENTE]],Tabla35[Concepto],"MULTIBANK") -> 209100 | AE7: =Tabla4[[#This Row],[VALOR TOTAL]]-Tabla4[[#This Row],[MONTO A MULTIBANK]] -> 209100 | AF7: 0 | AG7: =ABONOS!E8 -> 0 | AH7: {=_xlfn.IFS(Tabla4[[#This Row],[RESERVADAS, VENDIDAS]]="DISPONIBLE","",Tabla4[[#This Row],[SALDO PENDIENTE]]=0,"PAZ Y SALVO",Tabla4[[#This Row],[SALDO PENDIENTE]]=Tabla4[[#This Row],[MONTO CPP]],"COBRO CPP",Tabla4[[#This Row],[SALDO PENDIENTE]]>0,"PENDIENTE")} -> PAZ Y SALVO | AI7: N/A | AJ7: N/A | AK7: N/A | AL7: N/A | AM7: N/A | AN7: N/A | AO7: ACUERDO FINANCIAMIENTO INTERNO | AP7: N/A | AQ7: Reservada - Con Contrato | AR7: 45189 | AS7: =AA7 -> 209100 | AT7: 30474566 | AU7: GISA | AV7: 3427.6 | AW7: =ABONOS!O8 -> 0 | AX7: {=_xlfn.IFS(Tabla4[[#This Row],[MONTO5]]=0,"",Tabla4[[#This Row],[SALDO PENDIENTE3]]=0,"PAZ Y SALVO",Tabla4[[#This Row],[SALDO PENDIENTE3]]>0,"PENDIENTE")} -> PAZ Y SALVO | AY7: INSCRITA Y DESEMBOLSADA | AZ7: 45862 | BA7: SI | BB7: 45869 | BC7: =Tabla4[[#This Row],[FECHA RECIBIDO MINUTA LIBERACION]]-Tabla4[[#This Row],[SOLICITUD DE MINUTA LIBERACIÓN]] -> 7 | BD7: SI | BE7: 45926 | BF7: N/A | BG7: N/A | BH7: N/A | BI7: N/A | BJ7: N/A | BK7: 45944 | BL7: 45958 | BM7: 45957 | BN7: 45959 | BO7: 45969 | BP7: =Tabla4[[#This Row],[RECEPCIÓN INTERINO]]-Tabla4[[#This Row],[ENVIO A INTERINO]] -> 10 | BQ7: 45974 | BR7: 45968 | BS7: 45982 | BT7: 45979 | BU7: N/A | BV7: SI | BW7: 45957 | BX7: 45980 | BY7: 45982 | BZ7: 46055 | CA7: N/A | CB7: N/A | CC7: 45529
A8: L-507 | B8: 000 | C8: BRUNO LA GROTTA | D8: TRASPASADO | E8: INSCRITO Y DESEMBOLSADO | F8: 44986 | G8: 8-238-1798 | H8: PANAMEÑA | I8: NACIONAL | J8: GESPROBAN | K8: 23907 | L8: INDEPENDIENTE | M8: ARQUITECTO | N8: CONTADO | O8: SI | P8: SI | Q8: N/A | R8: 0 | S8: D | T8: 110.82 | U8: 0 | V8: =U8+T8 -> 110.82 | X8: =AB8*T8 -> 270000 | AA8: =X8+W8+Y8+Z8 -> 270000 | AB8: 2436.3833 | AC8: =((AD8*1)/AA8) -> 1 | AD8: =SUMIFS(Tabla35[Abonos],Tabla35[Lote],Tabla4[[#This Row],[UNIDAD APTO]],Tabla35[Cliente],Tabla4[[#This Row],[CLIENTE]],Tabla35[Concepto],"ABONO")+SUMIFS(Tabla35[Abonos],Tabla35[Lote],Tabla4[[#This Row],[UNIDAD APTO]],Tabla35[Cliente],Tabla4[[#This Row],[CLIENTE]],Tabla35[Concepto],"MULTIBANK") -> 270000 | AE8: =Tabla4[[#This Row],[VALOR TOTAL]]-Tabla4[[#This Row],[MONTO A MULTIBANK]] -> 116000 | AF8: =(AA8-50000)*70% -> 154000 | AG8: =ABONOS!E9 -> 0 | AH8: {=_xlfn.IFS(Tabla4[[#This Row],[RESERVADAS, VENDIDAS]]="DISPONIBLE","",Tabla4[[#This Row],[SALDO PENDIENTE]]=0,"PAZ Y SALVO",Tabla4[[#This Row],[SALDO PENDIENTE]]=Tabla4[[#This Row],[MONTO CPP]],"COBRO CPP",Tabla4[[#This Row],[SALDO PENDIENTE]]>0,"PENDIENTE")} -> PAZ Y SALVO | AI8: N/A | AJ8: N/A | AK8: N/A | AL8: N/A | AM8: N/A | AN8: N/A | AO8: N/A | AP8: N/A | AQ8: Reservada - Con Contrato | AR8: 44973 | AS8: =AA8 -> 270000 | AT8: 30474565 | AU8: GISA | AV8: 1950 | AW8: =ABONOS!O9 -> 0 | AX8: {=_xlfn.IFS(Tabla4[[#This Row],[MONTO5]]=0,"",Tabla4[[#This Row],[SALDO PENDIENTE3]]=0,"PAZ Y SALVO",Tabla4[[#This Row],[SALDO PENDIENTE3]]>0,"PENDIENTE")} -> PAZ Y SALVO | AY8: INSCRITA Y DESEMBOLSADA, POR ENTREGAR ESCRITURA PUBLICA | AZ8: 45779 | BA8: SI | BB8: 45785 | BC8: =Tabla4[[#This Row],[FECHA RECIBIDO MINUTA LIBERACION]]-Tabla4[[#This Row],[SOLICITUD DE MINUTA LIBERACIÓN]] -> 6 | BD8: SI | BE8: 45710 | BF8: N/A | BG8: N/A | BH8: N/A | BI8: N/A | BJ8: N/A | BK8: 45710 | BL8: 45799 | BM8: 45799 | BN8: 45799 | BO8: 45806 | BP8: =Tabla4[[#This Row],[RECEPCIÓN INTERINO]]-Tabla4[[#This Row],[ENVIO A INTERINO]] -> 7 | BQ8: 45820 | BR8: 45825 | BS8: 45820 | BT8: 45820 | BU8: N/A | BV8: SI | BW8: 45796 | BX8: 45818 | BY8: 45827 | BZ8: 45834 | CA8: N/A | CB8: N/A | CC8: 45330
A9: L-508 | B9: 000 | C9: PAUL Y RENATE MIANO | D9: TRASPASADO | E9: INSCRITO Y DESEMBOLSADO | F9: 45017 | G9: 668898941 / 668898940 | H9: ESTADOUNIDENSE | I9: EXTRANJERO NO RESIDENTE | J9: PANAMA PACIFICA REALTY | K9: 18346 | L9: INDEPENDIENTE | M9: BIENES RAICES / CONTABLE | N9: CONTADO | O9: SI | P9: SI | Q9: SI | R9: 20000 | S9: D | T9: 109.27 | U9: 0 | V9: =U9+T9 -> 109.27 | X9: =AB9*T9 -> 278638.5 | AA9: 278683.5 | AB9: 2550 | AC9: =((AD9*1)/AA9) -> 1 | AD9: =SUMIFS(Tabla35[Abonos],Tabla35[Lote],Tabla4[[#This Row],[UNIDAD APTO]],Tabla35[Cliente],Tabla4[[#This Row],[CLIENTE]],Tabla35[Concepto],"ABONO")+SUMIFS(Tabla35[Abonos],Tabla35[Lote],Tabla4[[#This Row],[UNIDAD APTO]],Tabla35[Cliente],Tabla4[[#This Row],[CLIENTE]],Tabla35[Concepto],"MULTIBANK") -> 278683.5 | AE9: =Tabla4[[#This Row],[VALOR TOTAL]]-Tabla4[[#This Row],[MONTO A MULTIBANK]] -> 83592 | AF9: 195091.5 | AG9: =ABONOS!E10 -> 0 | AH9: {=_xlfn.IFS(Tabla4[[#This Row],[RESERVADAS, VENDIDAS]]="DISPONIBLE","",Tabla4[[#This Row],[SALDO PENDIENTE]]=0,"PAZ Y SALVO",Tabla4[[#This Row],[SALDO PENDIENTE]]=Tabla4[[#This Row],[MONTO CPP]],"COBRO CPP",Tabla4[[#This Row],[SALDO PENDIENTE]]>0,"PENDIENTE")} -> PAZ Y SALVO | AI9: N/A | AJ9: N/A | AK9: N/A | AL9: N/A | AM9: N/A | AN9: N/A | AO9: N/A | AP9: N/A | AQ9: Reservada - Con Contrato | AR9: 45040 | AS9: =AA9 -> 278683.5 | AT9: 30474564 | AU9: GISA | AV9: 1950 | AW9: =ABONOS!O10 -> 0 | AX9: {=_xlfn.IFS(Tabla4[[#This Row],[MONTO5]]=0,"",Tabla4[[#This Row],[SALDO PENDIENTE3]]=0,"PAZ Y SALVO",Tabla4[[#This Row],[SALDO PENDIENTE3]]>0,"PENDIENTE")} -> PAZ Y SALVO | AY9: INSCRITA Y DESEMBOLSADA | AZ9: 45428 | BA9: SI | BB9: 45449 | BC9: =Tabla4[[#This Row],[FECHA RECIBIDO MINUTA LIBERACION]]-Tabla4[[#This Row],[SOLICITUD DE MINUTA LIBERACIÓN]] -> 21 | BD9: SI | BE9: 45414 | BF9: N/A | BG9: N/A | BH9: N/A | BI9: N/A | BJ9: N/A | BK9: 45461 | BL9: 45468 | BM9: 45467 | BN9: 45471 | BO9: 45477 | BP9: =Tabla4[[#This Row],[RECEPCIÓN INTERINO]]-Tabla4[[#This Row],[ENVIO A INTERINO]] -> 6 | BQ9: 45482 | BR9: 45485 | BS9: 45485 | BT9: 45482 | BU9: N/A | BV9: SI | BW9: 45462 | BX9: 45483 | BY9: 45485 | BZ9: 45499 | CA9: N/A | CB9: N/A | CC9: 45357
A10: L-509 | B10: 000 | C10: DAYANARA RÍOS | D10: TRASPASADO | E10: INSCRITO Y DESEMBOLSADO | F10: 45108 | G10: 8-729-1993 | H10: PANAMEÑA | I10: NACIONAL | J10: GESPROBAN | K10: 29007 | L10: ASALARIADO | M10: CONTADOR PUBLICO AUTORIZADO | N10: FINANCIAMIENTO | O10: NO | P10: NO | Q10: N/A | R10: 0 | S10: C1 | T10: 73.09 | U10: 0 | V10: =U10+T10 -> 73.09 | X10: =AB10*T10 -> 186379.5 | AA10: =X10+W10+Y10+Z10 -> 186379.5 | AB10: 2550 | AC10: =((AD10*1)/AA10) -> 1 | AD10: =SUMIFS(Tabla35[Abonos],Tabla35[Lote],Tabla4[[#This Row],[UNIDAD APTO]],Tabla35[Cliente],Tabla4[[#This Row],[CLIENTE]],Tabla35[Concepto],"ABONO")+SUMIFS(Tabla35[Abonos],Tabla35[Lote],Tabla4[[#This Row],[UNIDAD APTO]],Tabla35[Cliente],Tabla4[[#This Row],[CLIENTE]],Tabla35[Concepto],"MULTIBANK") -> 186379.5 | AE10: =Tabla4[[#This Row],[VALOR TOTAL]]-Tabla4[[#This Row],[MONTO A MULTIBANK]] -> 37275.9 | AF10: =Tabla4[[#This Row],[MONTO CPP]] -> 149103.6 | AG10: =ABONOS!E11 -> 0 | AH10: {=_xlfn.IFS(Tabla4[[#This Row],[RESERVADAS, VENDIDAS]]="DISPONIBLE","",Tabla4[[#This Row],[SALDO PENDIENTE]]=0,"PAZ Y SALVO",Tabla4[[#This Row],[SALDO PENDIENTE]]=Tabla4[[#This Row],[MONTO CPP]],"COBRO CPP",Tabla4[[#This Row],[SALDO PENDIENTE]]>0,"PENDIENTE")} -> PAZ Y SALVO | AI10: TOWERBANK | AJ10: KERIMA CHONG | AK10: kchong@towerbank.com / 269-6900 | AL10: CON CPP | AM10: 45133 | AN10: 45495 | AO10: CON CPP | AP10: 149103.6 | AQ10: Reservada - Con Contrato | AR10: 45145 | AS10: =AA10 -> 186379.5 | AT10: 30474563 | AU10: TOWERBANK | AV10: BANCO | AW10: =ABONOS!O11 -> 0 | AX10: {=_xlfn.IFS(Tabla4[[#This Row],[MONTO5]]=0,"",Tabla4[[#This Row],[SALDO PENDIENTE3]]=0,"PAZ Y SALVO",Tabla4[[#This Row],[SALDO PENDIENTE3]]>0,"PENDIENTE")} -> PAZ Y SALVO | AY10: INSCRITA Y DESEMBOLSADA | AZ10: 45428 | BA10: SI | BB10: 45455 | BC10: =Tabla4[[#This Row],[FECHA RECIBIDO MINUTA LIBERACION]]-Tabla4[[#This Row],[SOLICITUD DE MINUTA LIBERACIÓN]] -> 27 | BD10: SI | BE10: 45440 | BF10: SI | BG10: 45435 | BH10: SI | BI10: SI | BJ10: SI | BK10: 45476 | BL10: 45472 | BM10: 45477 | BN10: 45477 | BO10: 45481 | BP10: =Tabla4[[#This Row],[RECEPCIÓN INTERINO]]-Tabla4[[#This Row],[ENVIO A INTERINO]] -> 4 | BQ10: 45477 | BR10: 45457 | BS10: 45478 | BT10: 45478 | BU10: 45481 | BV10: SI | BW10: 45470 | BX10: 45484 | BY10: 45485 | BZ10: 45488 | CA10: 45488 | CB10: 45491 | CC10: 45499
A11: L-510 | B11: 000 | C11: NICHOLAS CHILLEMI | D11: TRASPASADO | E11: INSCRITO Y DESEMBOLSADO | F11: 45261 | G11: 533608824 | H11: ESTADOUNIDENSE | I11: EXTRANJERO NO RESIDENTE | J11: PANAMA EQUITY | K11: 20482 | L11: INDEPENDIENTE | M11: BIENES RAICES | N11: CONTADO | O11: SI | P11: SI | Q11: NO | R11: 12000 | S11: B | T11: 59.94 | U11: 0 | V11: =U11+T11 -> 59.94 | X11: =AB11*T11 -> 152847 | AA11: 150000 | AB11: 2550 | AC11: =((AD11*1)/AA11) -> 1 | AD11: =SUMIFS(Tabla35[Abonos],Tabla35[Lote],Tabla4[[#This Row],[UNIDAD APTO]],Tabla35[Cliente],Tabla4[[#This Row],[CLIENTE]],Tabla35[Concepto],"ABONO")+SUMIFS(Tabla35[Abonos],Tabla35[Lote],Tabla4[[#This Row],[UNIDAD APTO]],Tabla35[Cliente],Tabla4[[#This Row],[CLIENTE]],Tabla35[Concepto],"MULTIBANK") -> 150000 | AE11: =Tabla4[[#This Row],[VALOR TOTAL]]-Tabla4[[#This Row],[MONTO A MULTIBANK]] -> 45000 | AF11: =Tabla4[[#This Row],[MONTO CPP]] -> 105000 | AG11: =ABONOS!E12 -> 0 | AH11: {=_xlfn.IFS(Tabla4[[#This Row],[RESERVADAS, VENDIDAS]]="DISPONIBLE","",Tabla4[[#This Row],[SALDO PENDIENTE]]=0,"PAZ Y SALVO",Tabla4[[#This Row],[SALDO PENDIENTE]]=Tabla4[[#This Row],[MONTO CPP]],"COBRO CPP",Tabla4[[#This Row],[SALDO PENDIENTE]]>0,"PENDIENTE")} -> PAZ Y SALVO | AI11: BANCO ALIADO | AJ11: KATHERINE MARTNEZ | AK11: katherine.martinez@bancoaliado.com / 6948-4733 | AL11: CON CPP | AM11: 45377 | AN11: 45558 | AO11: CON CPP | AP11: 105000 | AQ11: Reservada - Con Contrato | AR11: 45337 | AS11: =AA11 -> 150000 | AT11: 30474562 | AU11: GISA | AV11: 1525 | AW11: =ABONOS!O12 -> 0 | AX11: {=_xlfn.IFS(Tabla4[[#This Row],[MONTO5]]=0,"",Tabla4[[#This Row],[SALDO PENDIENTE3]]=0,"PAZ Y SALVO",Tabla4[[#This Row],[SALDO PENDIENTE3]]>0,"PENDIENTE")} -> PAZ Y SALVO | AY11: INSCRITA Y DESEMBOLSADA | AZ11: 45428 | BA11: SI | BB11: 45455 | BC11: =Tabla4[[#This Row],[FECHA RECIBIDO MINUTA LIBERACION]]-Tabla4[[#This Row],[SOLICITUD DE MINUTA LIBERACIÓN]] -> 27 | BD11: SI | BE11: 45446 | BF11: N/A | BG11: N/A | BH11: N/A | BI11: N/A | BJ11: N/A | BK11: 45464 | BL11: 45479 | BM11: 45478 | BN11: 45483 | BO11: 45485 | BP11: =Tabla4[[#This Row],[RECEPCIÓN INTERINO]]-Tabla4[[#This Row],[ENVIO A INTERINO]] -> 2 | BQ11: 45489 | BR11: 45484 | BS11: 45489 | BT11: 45488 | BU11: N/A | BV11: SI | BW11: 45464 | BX11: 45489 | BY11: 45490 | BZ11: 45496 | CA11: 45496 | CB11: 45499 | CC11: 45502
A12: L-511 | B12: 000 | C12: JEANETTE MUNROE | D12: TRASPASADO | E12: INSCRITO Y DESEMBOLSADO | F12: 44986 | G12: 542879367 | H12: ESTADOUNIDENSE | I12: EXTRANJERO NO RESIDENTE | J12: PANAMA PACIFICA REALTY | K12: 23337 | L12: INDEPENDIENTE | M12: ADMINISTRADOR DE EMPRESAS | N12: CONTADO | O12: SI | P12: NO | Q12: SI | S12: A | T12: 65.93 | U12: 0 | V12: =U12+T12 -> 65.93 | X12: =AB12*T12 -> 168121.5 | AA12: =X12+W12+Y12+Z12 -> 168121.5 | AB12: 2550 | AC12: =((AD12*1)/AA12) -> 1 | AD12: =SUMIFS(Tabla35[Abonos],Tabla35[Lote],Tabla4[[#This Row],[UNIDAD APTO]],Tabla35[Cliente],Tabla4[[#This Row],[CLIENTE]],Tabla35[Concepto],"ABONO")+SUMIFS(Tabla35[Abonos],Tabla35[Lote],Tabla4[[#This Row],[UNIDAD APTO]],Tabla35[Cliente],Tabla4[[#This Row],[CLIENTE]],Tabla35[Concepto],"MULTIBANK") -> 168121.5 | AE12: =Tabla4[[#This Row],[VALOR TOTAL]]-Tabla4[[#This Row],[MONTO A MULTIBANK]] -> 58842.525 | AF12: =AA12*65% -> 109278.98 | AG12: =ABONOS!E13 -> 0 | AH12: {=_xlfn.IFS(Tabla4[[#This Row],[RESERVADAS, VENDIDAS]]="DISPONIBLE","",Tabla4[[#This Row],[SALDO PENDIENTE]]=0,"PAZ Y SALVO",Tabla4[[#This Row],[SALDO PENDIENTE]]=Tabla4[[#This Row],[MONTO CPP]],"COBRO CPP",Tabla4[[#This Row],[SALDO PENDIENTE]]>0,"PENDIENTE")} -> PAZ Y SALVO | AI12: N/A | AJ12: N/A | AK12: N/A | AL12: N/A | AM12: N/A | AN12: N/A | AO12: N/A | AP12: N/A | AQ12: Reservada - Con Contrato | AR12: 45058 | AS12: =AA12 -> 168121.5 | AT12: 30474561 | AU12: GISA | AV12: 1600 | AW12: =ABONOS!O13 -> 0 | AX12: {=_xlfn.IFS(Tabla4[[#This Row],[MONTO5]]=0,"",Tabla4[[#This Row],[SALDO PENDIENTE3]]=0,"PAZ Y SALVO",Tabla4[[#This Row],[SALDO PENDIENTE3]]>0,"PENDIENTE")} -> PAZ Y SALVO | AY12: INSCRITA Y DESEMBOLSADA | AZ12: 45478 | BA12: SI | BB12: 45497 | BC12: =Tabla4[[#This Row],[FECHA RECIBIDO MINUTA LIBERACION]]-Tabla4[[#This Row],[SOLICITUD DE MINUTA LIBERACIÓN]] -> 19 | BD12: SI | BE12: 45496 | BF12: N/A | BG12: N/A | BH12: N/A | BI12: N/A | BJ12: N/A | BK12: 45477 | BL12: 45478 | BM12: 45477 | BN12: 45524 | BO12: 45533 | BP12: =Tabla4[[#This Row],[RECEPCIÓN INTERINO]]-Tabla4[[#This Row],[ENVIO A INTERINO]] -> 9 | BQ12: 1396933 | BR12: 45539 | BS12: 45539 | BT12: 45542 | BU12: N/A | BV12: SI | BW12: 45477 | BX12: 45541 | BY12: 45545 | BZ12: 45554 | CA12: N/A | CB12: N/A | CC12: 45572
A13: L-401 | B13: -100 | C13: ROBERT RODRIGUEZ | D13: TRASPASADO | E13: INSCRITO Y DESEMBOLSADO | F13: 44986 | G13: 6-711-23 | H13: PANAMEÑA | I13: NACIONAL | J13: GESPROBAN | K13: 31415 | L13: ASALARIADO | M13: ADMINISTRADOR DE EMPRESAS | N13: FINANCIAMIENTO | O13: SI | P13: NO | Q13: NO | S13: A | T13: 65.93 | U13: 0 | V13: =U13+T13 -> 65.93 | X13: =AB13*T13 -> 161528.5 | Z13: -1528.5 | AA13: =X13+W13+Y13+Z13 -> 160000 | AB13: 2450 | AC13: =((AD13*1)/AA13) -> 1 | AD13: =SUMIFS(Tabla35[Abonos],Tabla35[Lote],Tabla4[[#This Row],[UNIDAD APTO]],Tabla35[Cliente],Tabla4[[#This Row],[CLIENTE]],Tabla35[Concepto],"ABONO")+SUMIFS(Tabla35[Abonos],Tabla35[Lote],Tabla4[[#This Row],[UNIDAD APTO]],Tabla35[Cliente],Tabla4[[#This Row],[CLIENTE]],Tabla35[Concepto],"MULTIBANK") -> 160000 | AE13: =Tabla4[[#This Row],[VALOR TOTAL]]-Tabla4[[#This Row],[MONTO A MULTIBANK]] -> 56000 | AF13: =AA13*65% -> 104000 | AG13: =ABONOS!E14 -> 0 | AH13: {=_xlfn.IFS(Tabla4[[#This Row],[RESERVADAS, VENDIDAS]]="DISPONIBLE","",Tabla4[[#This Row],[SALDO PENDIENTE]]=0,"PAZ Y SALVO",Tabla4[[#This Row],[SALDO PENDIENTE]]=Tabla4[[#This Row],[MONTO CPP]],"COBRO CPP",Tabla4[[#This Row],[SALDO PENDIENTE]]>0,"PENDIENTE")} -> PAZ Y SALVO | AI13: SCOTIABANK | AJ13: RICARDO HERRERA | AK13: ricardo.herrera@pa.scotiabank.com / 6349-7898 | AL13: CON CPP | AM13: 45407 | AN13: 45772 | AO13: CON CPP | AP13: 86000 | AQ13: Reservada - Con Contrato | AR13: 45051 | AS13: =AA13 -> 160000 | AT13: 30474582 | AU13: SCOTIABANK | AV13: BANCO | AW13: =ABONOS!O14 -> 0 | AX13: {=_xlfn.IFS(Tabla4[[#This Row],[MONTO5]]=0,"",Tabla4[[#This Row],[SALDO PENDIENTE3]]=0,"PAZ Y SALVO",Tabla4[[#This Row],[SALDO PENDIENTE3]]>0,"PENDIENTE")} -> PAZ Y SALVO | AY13: INSCRITA Y DESEMBOLSADA | AZ13: 45478 | BA13: SI | BB13: 45496 | BC13: =Tabla4[[#This Row],[FECHA RECIBIDO MINUTA LIBERACION]]-Tabla4[[#This Row],[SOLICITUD DE MINUTA LIBERACIÓN]] -> 18 | BD13: SI | BE13: 45492 | BF13: SI | BG13: 45492 | BH13: SI | BI13: 45476 | BJ13: SI | BK13: 45528 | BL13: 45525 | BM13: 45526 | BN13: 45530 | BO13: 45531 | BP13: =Tabla4[[#This Row],[RECEPCIÓN INTERINO]]-Tabla4[[#This Row],[ENVIO A INTERINO]] -> 1 | BQ13: 45527 | BR13: 45537 | BS13: 45539 | BT13: 45526 | BU13: 45558 | BV13: SI | BW13: 45528 | BX13: 45544 | BY13: 45547 | BZ13: 45551 | CA13: 45551 | CB13: 45555 | CC13: 45811
A14: L-402 | B14: -100 | C14: EDGAR UREÑA | D14: TRASPASADO | E14: INSCRITO Y DESEMBOLSADO | F14: 45413 | G14: 8-735-347 | H14: PANAMEÑA | I14: NACIONAL | J14: GESPROBAN | K14: 29281 | L14: ASALARIADO | M14: CIRUJANO MAXILOFACIAL | N14: FINANCIAMIENTO | S14: B | T14: 59.94 | U14: 0 | V14: =U14+T14 -> 59.94 | X14: =AB14*T14 -> 146853 | AA14: 152500 | AB14: 2450 | AC14: =((AD14*1)/AA14) -> 1 | AD14: =SUMIFS(Tabla35[Abonos],Tabla35[Lote],Tabla4[[#This Row],[UNIDAD APTO]],Tabla35[Cliente],Tabla4[[#This Row],[CLIENTE]],Tabla35[Concepto],"ABONO")+SUMIFS(Tabla35[Abonos],Tabla35[Lote],Tabla4[[#This Row],[UNIDAD APTO]],Tabla35[Cliente],Tabla4[[#This Row],[CLIENTE]],Tabla35[Concepto],"MULTIBANK") -> 152500 | AE14: =Tabla4[[#This Row],[VALOR TOTAL]]-Tabla4[[#This Row],[MONTO A MULTIBANK]] -> 30500 | AF14: =AA14*80% -> 122000 | AG14: =ABONOS!E15 -> 0 | AH14: {=_xlfn.IFS(Tabla4[[#This Row],[RESERVADAS, VENDIDAS]]="DISPONIBLE","",Tabla4[[#This Row],[SALDO PENDIENTE]]=0,"PAZ Y SALVO",Tabla4[[#This Row],[SALDO PENDIENTE]]=Tabla4[[#This Row],[MONTO CPP]],"COBRO CPP",Tabla4[[#This Row],[SALDO PENDIENTE]]>0,"PENDIENTE")} -> PAZ Y SALVO | AI14: CAJA DE AHORROS | AJ14: JOSE PINTO | AK14: jose.pinto@banistmo.com /62352036 | AL14: CON CPP | AO14: CON CPP | AP14: 122000 | AQ14: Reservada - Con Contrato | AR14: 45464 | AS14: =AA14 -> 152500 | AT14: 30474581 | AU14: BANCO | AV14: BANCO | AW14: =ABONOS!O15 -> 0 | AX14: {=_xlfn.IFS(Tabla4[[#This Row],[MONTO5]]=0,"",Tabla4[[#This Row],[SALDO PENDIENTE3]]=0,"PAZ Y SALVO",Tabla4[[#This Row],[SALDO PENDIENTE3]]>0,"PENDIENTE")} -> PAZ Y SALVO | AY14: INSCRITA Y DESEMBOLSADA | AZ14: 45504 | BA14: SI | BB14: 45532 | BC14: =Tabla4[[#This Row],[FECHA RECIBIDO MINUTA LIBERACION]]-Tabla4[[#This Row],[SOLICITUD DE MINUTA LIBERACIÓN]] -> 28 | BD14: SI | BE14: 45535 | BF14: SI | BG14: 45539 | BH14: SI | BI14: SI | BJ14: SI | BK14: 45573 | BL14: 45576 | BM14: 45577 | BN14: 45579 | BO14: 45581 | BP14: =Tabla4[[#This Row],[RECEPCIÓN INTERINO]]-Tabla4[[#This Row],[ENVIO A INTERINO]] -> 2 | BQ14: 45579 | BR14: 45579 | BS14: 45579 | BT14: 45579 | BU14: 45581 | BV14: SI | BW14: 45575 | BX14: 45586 | BY14: 45588 | BZ14: 45597 | CA14: 45597 | CB14: 45604 | CC14: 45604
A15: L-403 | B15: -100 | C15: CARLOS ARAGON / MILAINE DOMINGUEZ | D15: TRASPASADO | E15: INSCRITO Y DESEMBOLSADO | F15: 45658 | G15: 668069351 | H15: ESTADOUNIDENSE | I15: EXTRANJERO NO RESIDENTE | J15: MARISOL CUESTA | K15: 26279 | L15: INDEPENDIENTE | M15: ADMINISTRADOR DE EMPRESAS | N15: CONTADO | S15: C1 | T15: 73.09 | U15: 0 | V15: =U15+T15 -> 73.09 | X15: =AB15*T15 -> 179070.5 | AA15: 185270 | AB15: 2450 | AC15: =((AD15*1)/AA15) -> 0.33494856 | AD15: =SUMIFS(Tabla35[Abonos],Tabla35[Lote],Tabla4[[#This Row],[UNIDAD APTO]],Tabla35[Cliente],Tabla4[[#This Row],[CLIENTE]],Tabla35[Concepto],"ABONO")+SUMIFS(Tabla35[Abonos],Tabla35[Lote],Tabla4[[#This Row],[UNIDAD APTO]],Tabla35[Cliente],Tabla4[[#This Row],[CLIENTE]],Tabla35[Concepto],"MULTIBANK") -> 62055.92 | AE15: =Tabla4[[#This Row],[VALOR TOTAL]]-Tabla4[[#This Row],[MONTO A MULTIBANK]] -> 185270 | AF15: 0 | AG15: =ABONOS!E16 -> 123214.08 | AH15: {=_xlfn.IFS(Tabla4[[#This Row],[RESERVADAS, VENDIDAS]]="DISPONIBLE","",Tabla4[[#This Row],[SALDO PENDIENTE]]=0,"PAZ Y SALVO",Tabla4[[#This Row],[SALDO PENDIENTE]]=Tabla4[[#This Row],[MONTO CPP]],"COBRO CPP",Tabla4[[#This Row],[SALDO PENDIENTE]]>0,"PENDIENTE")} -> PENDIENTE | AI15: N/A | AJ15: N/A | AK15: N/A | AL15: N/A | AM15: N/A | AN15: N/A | AO15: N/A | AP15: N/A | AQ15: Reservada - Con Contrato | AR15: 45686 | AS15: =AA15 -> 185270 | AT15: 30474580 | AU15: BANCO | AW15: =ABONOS!O16 -> 0 | AX15: {=_xlfn.IFS(Tabla4[[#This Row],[MONTO5]]=0,"",Tabla4[[#This Row],[SALDO PENDIENTE3]]=0,"PAZ Y SALVO",Tabla4[[#This Row],[SALDO PENDIENTE3]]>0,"PENDIENTE")} | AY15: 27-07-26: Protocolo retirado firmado por cliente | AZ15: 46211 | BA15: SI | BB15: 46213 | BC15: =Tabla4[[#This Row],[FECHA RECIBIDO MINUTA LIBERACION]]-Tabla4[[#This Row],[SOLICITUD DE MINUTA LIBERACIÓN]] -> 2 | BD15: SI | BE15: 46214 | BF15: SI | BG15: 46214 | BH15: N/A | BI15: N/A | BJ15: N/A | BK15: 46230 | BL15: 46230 | BM15: 46232 | BN15: 46232 | BO15: 46232 | BP15: =Tabla4[[#This Row],[RECEPCIÓN INTERINO]]-Tabla4[[#This Row],[ENVIO A INTERINO]] -> 0 | BU15: N/A | BZ15: 46259 | CC15: 45706
A16: L-404 | B16: -100 | C16: VERA ANN MATTHEWS / RUDOLF MATTHEWS | D16: TRASPASADO | E16: INSCRITO Y DESEMBOLSADO | F16: 45831 | G16: 572606505 / A6716876 | H16: ESTADOUNIDENSE | I16: EXTRANJERO NO RESIDENTE | J16: GESPROBAN | K16: 25895 | L16: ASALARIADO | M16: TRABAJADORA SOCIAL | N16: FINANCIAMIENTO | S16: C1 | T16: 73.09 | U16: 0 | V16: =U16+T16 -> 73.09 | X16: =AB16*T16 -> 179070.5 | AA16: 191892.6 | AB16: 2450 | AC16: =((AD16*1)/AA16) -> 1 | AD16: =SUMIFS(Tabla35[Abonos],Tabla35[Lote],Tabla4[[#This Row],[UNIDAD APTO]],Tabla35[Cliente],Tabla4[[#This Row],[CLIENTE]],Tabla35[Concepto],"ABONO")+SUMIFS(Tabla35[Abonos],Tabla35[Lote],Tabla4[[#This Row],[UNIDAD APTO]],Tabla35[Cliente],Tabla4[[#This Row],[CLIENTE]],Tabla35[Concepto],"MULTIBANK") -> 191892.6 | AE16: =Tabla4[[#This Row],[VALOR TOTAL]]-Tabla4[[#This Row],[MONTO A MULTIBANK]] -> 63751.65 | AF16: 128140.95 | AG16: =ABONOS!E17 -> 0 | AH16: {=_xlfn.IFS(Tabla4[[#This Row],[RESERVADAS, VENDIDAS]]="DISPONIBLE","",Tabla4[[#This Row],[SALDO PENDIENTE]]=0,"PAZ Y SALVO",Tabla4[[#This Row],[SALDO PENDIENTE]]=Tabla4[[#This Row],[MONTO CPP]],"COBRO CPP",Tabla4[[#This Row],[SALDO PENDIENTE]]>0,"PENDIENTE")} -> PAZ Y SALVO | AI16: BANESCO | AJ16: G | AL16: CON CPP | AM16: 45806 | AN16: =Tabla4[[#This Row],[FECHA DE EMISION DE CPP]]+365 -> 46171 | AO16: CON CPP | AP16: 149384.31 | AQ16: Reservada - Con Contrato | AR16: 45805 | AS16: 191892.6 | AT16: 30474579 | AU16: BANCO | AV16: BANCO | AW16: =ABONOS!O17 -> 0 | AX16: {=_xlfn.IFS(Tabla4[[#This Row],[MONTO5]]=0,"",Tabla4[[#This Row],[SALDO PENDIENTE3]]=0,"PAZ Y SALVO",Tabla4[[#This Row],[SALDO PENDIENTE3]]>0,"PENDIENTE")} -> PAZ Y SALVO | AY16: INSCRITA Y DESEMBOLSADA | AZ16: 45828 | BA16: SI | BB16: 45835 | BC16: =Tabla4[[#This Row],[FECHA RECIBIDO MINUTA LIBERACION]]-Tabla4[[#This Row],[SOLICITUD DE MINUTA LIBERACIÓN]] -> 7 | BD16: SI | BE16: 45838 | BF16: SI | BG16: 45838 | BH16: N/A | BI16: N/A | BJ16: N/A | BK16: 45840 | BL16: 45840 | BM16: 45840 | BN16: 45841 | BO16: 45841 | BP16: =Tabla4[[#This Row],[RECEPCIÓN INTERINO]]-Tabla4[[#This Row],[ENVIO A INTERINO]] -> 0 | BQ16: 45842 | BR16: 45825 | BS16: 45842 | BT16: 45845 | BU16: 45845 | BV16: SI | BW16: BANCO | BX16: 45845 | BY16: 45849 | BZ16: 45854 | CA16: 45854 | CB16: 45856 | CC16: 45854
A17: L-405 | B17: -100 | C17: GABRIEL DIAZ / NURIA CASTILLO | D17: TRASPASADO | E17: INSCRITO Y DESEMBOLSADO | F17: 45323 | G17: 8-303-199 | H17: PANAMEÑA | I17: NACIONAL | J17: GESPROBAN | K17: 24987 | L17: INDEPENDIENTE | M17: MEDICO | N17: FINANCIAMIENTO | O17: NO | P17: NO | Q17: N/A | R17: 0 | S17: C1 | T17: 73.09 | U17: 0 | V17: =U17+T17 -> 73.09 | X17: =AB17*T17 -> 179070.5 | AA17: 180000 | AB17: 2450 | AC17: =((AD17*1)/AA17) -> 1 | AD17: =SUMIFS(Tabla35[Abonos],Tabla35[Lote],Tabla4[[#This Row],[UNIDAD APTO]],Tabla35[Cliente],Tabla4[[#This Row],[CLIENTE]],Tabla35[Concepto],"ABONO")+SUMIFS(Tabla35[Abonos],Tabla35[Lote],Tabla4[[#This Row],[UNIDAD APTO]],Tabla35[Cliente],Tabla4[[#This Row],[CLIENTE]],Tabla35[Concepto],"MULTIBANK") -> 180000 | AE17: =Tabla4[[#This Row],[VALOR TOTAL]]-Tabla4[[#This Row],[MONTO A MULTIBANK]] -> 50000 | AF17: =Tabla4[[#This Row],[MONTO CPP]] -> 130000 | AG17: =ABONOS!E18 -> 0 | AH17: {=_xlfn.IFS(Tabla4[[#This Row],[RESERVADAS, VENDIDAS]]="DISPONIBLE","",Tabla4[[#This Row],[SALDO PENDIENTE]]=0,"PAZ Y SALVO",Tabla4[[#This Row],[SALDO PENDIENTE]]=Tabla4[[#This Row],[MONTO CPP]],"COBRO CPP",Tabla4[[#This Row],[SALDO PENDIENTE]]>0,"PENDIENTE")} -> PAZ Y SALVO | AI17: BANCO GENERAL | AL17: CON CPP | AM17: 45665 | AN17: 46030 | AO17: CON CPP | AP17: 130000 | AQ17: Reservada - Con Contrato | AR17: 45490 | AS17: =AA17 -> 180000 | AT17: 30474578 | AU17: CAJA DE AHORROS | AV17: BANCO | AW17: =ABONOS!O18 -> 0 | AX17: {=_xlfn.IFS(Tabla4[[#This Row],[MONTO5]]=0,"",Tabla4[[#This Row],[SALDO PENDIENTE3]]=0,"PAZ Y SALVO",Tabla4[[#This Row],[SALDO PENDIENTE3]]>0,"PENDIENTE")} -> PAZ Y SALVO | AY17: INSCRITA Y DESEMBOLSADA | AZ17: 45665 | BA17: SI | BB17: 45673 | BC17: =Tabla4[[#This Row],[FECHA RECIBIDO MINUTA LIBERACION]]-Tabla4[[#This Row],[SOLICITUD DE MINUTA LIBERACIÓN]] -> 8 | BD17: SI | BE17: 45673 | BF17: SI | BG17: 45673 | BH17: BANCO | BI17: BANCO | BJ17: BANCO | BK17: BANCO | BL17: 45716 | BM17: 45723 | BN17: 45727 | BO17: 45729 | BP17: =Tabla4[[#This Row],[RECEPCIÓN INTERINO]]-Tabla4[[#This Row],[ENVIO A INTERINO]] -> 2 | BQ17: 45726 | BR17: 45705 | BS17: 45726 | BT17: 45726 | BU17: 45729 | BV17: SI | BW17: BANCO | BX17: 45734 | BY17: 45736 | BZ17: 45742 | CA17: 45742 | CB17: 45747 | CC17: 45610
A18: L-406 | B18: -100 | C18: JOHN ESTRELLA / MARIA ESTRELLA | D18: TRASPASADO | E18: INSCRITO Y DESEMBOLSADO | F18: 45200 | G18: HL824486 / HL824480 | H18: CANADIENSE | I18: EXTRANJERO NO RESIDENTE | J18: PANAMA EQUITY | K18: 26057 | L18: INDEPENDIENTE | M18: CONSULTORES | N18: CONTADO | O18: SI | Q18: SI | R18: 15000 | S18: C1 | T18: 73.98 | U18: 0 | V18: =U18+T18 -> 73.98 | X18: =AB18*T18 -> 181251 | AA18: 205422.3 | AB18: 2450 | AC18: =((AD18*1)/AA18) -> 1 | AD18: =SUMIFS(Tabla35[Abonos],Tabla35[Lote],Tabla4[[#This Row],[UNIDAD APTO]],Tabla35[Cliente],Tabla4[[#This Row],[CLIENTE]],Tabla35[Concepto],"ABONO")+SUMIFS(Tabla35[Abonos],Tabla35[Lote],Tabla4[[#This Row],[UNIDAD APTO]],Tabla35[Cliente],Tabla4[[#This Row],[CLIENTE]],Tabla35[Concepto],"MULTIBANK") -> 205422.3 | AE18: =Tabla4[[#This Row],[VALOR TOTAL]]-Tabla4[[#This Row],[MONTO A MULTIBANK]] -> 61626.69 | AF18: =AA18*70% -> 143795.61 | AG18: =ABONOS!E19 -> 0 | AH18: {=_xlfn.IFS(Tabla4[[#This Row],[RESERVADAS, VENDIDAS]]="DISPONIBLE","",Tabla4[[#This Row],[SALDO PENDIENTE]]=0,"PAZ Y SALVO",Tabla4[[#This Row],[SALDO PENDIENTE]]=Tabla4[[#This Row],[MONTO CPP]],"COBRO CPP",Tabla4[[#This Row],[SALDO PENDIENTE]]>0,"PENDIENTE")} -> PAZ Y SALVO | AI18: N/A | AJ18: N/A | AK18: N/A | AL18: N/A | AM18: N/A | AN18: N/A | AO18: N/A | AP18: N/A | AQ18: Reservada - Con Contrato | AR18: 45246 | AS18: =AA18 -> 205422.3 | AT18: 30474577 | AU18: GISA | AV18: 1805 | AW18: =ABONOS!O19 -> 0 | AX18: {=_xlfn.IFS(Tabla4[[#This Row],[MONTO5]]=0,"",Tabla4[[#This Row],[SALDO PENDIENTE3]]=0,"PAZ Y SALVO",Tabla4[[#This Row],[SALDO PENDIENTE3]]>0,"PENDIENTE")} -> PAZ Y SALVO | AY18: INSCRITA Y DESEMBOLSADA | AZ18: 45428 | BA18: SI | BB18: 45449 | BC18: =Tabla4[[#This Row],[FECHA RECIBIDO MINUTA LIBERACION]]-Tabla4[[#This Row],[SOLICITUD DE MINUTA LIBERACIÓN]] -> 21 | BD18: SI | BE18: 45450 | BF18: N/A | BG18: N/A | BH18: N/A | BI18: N/A | BJ18: N/A | BK18: 45449 | BL18: 45503 | BM18: 45454 | BN18: 45503 | BO18: 45526 | BP18: =Tabla4[[#This Row],[RECEPCIÓN INTERINO]]-Tabla4[[#This Row],[ENVIO A INTERINO]] -> 23 | BQ18: 45527 | BR18: 45537 | BS18: 45539 | BT18: 45531 | BU18: N/A | BV18: SI | BW18: 45450 | BX18: 45531 | BY18: 45567 | BZ18: 45568 | CA18: N/A | CB18: N/A | CC18: 45379
A19: L-407 | B19: -100 | C19: LEO MC DONOUGH / JODI ELLIOT | D19: TRASPASADO | E19: INSCRITO Y DESEMBOLSADO | F19: 45717 | G19: 5654432828 / A27056946 | H19: ESTADOUNIDENSE | I19: EXTRANJERO NO RESIDENTE | J19: DO PANAMA | K19: 22768 | L19: ASALARIADO | M19: INSTRUCTOR / ADMINISTRADOR DE EMPRESAS | N19: CONTADO | O19: SI | P19: NO | Q19: NO | S19: D | T19: 110.82 | U19: 0 | V19: =U19+T19 -> 110.82 | X19: =AB19*T19 -> 271509 | AA19: 299000 | AB19: 2450 | AC19: =((AD19*1)/AA19) -> 1 | AD19: =SUMIFS(Tabla35[Abonos],Tabla35[Lote],Tabla4[[#This Row],[UNIDAD APTO]],Tabla35[Cliente],Tabla4[[#This Row],[CLIENTE]],Tabla35[Concepto],"ABONO")+SUMIFS(Tabla35[Abonos],Tabla35[Lote],Tabla4[[#This Row],[UNIDAD APTO]],Tabla35[Cliente],Tabla4[[#This Row],[CLIENTE]],Tabla35[Concepto],"MULTIBANK") -> 299000 | AE19: =Tabla4[[#This Row],[VALOR TOTAL]]-Tabla4[[#This Row],[MONTO A MULTIBANK]] -> 89700 | AF19: =70%*AA19 -> 209300 | AG19: =ABONOS!E20 -> 0 | AH19: {=_xlfn.IFS(Tabla4[[#This Row],[RESERVADAS, VENDIDAS]]="DISPONIBLE","",Tabla4[[#This Row],[SALDO PENDIENTE]]=0,"PAZ Y SALVO",Tabla4[[#This Row],[SALDO PENDIENTE]]=Tabla4[[#This Row],[MONTO CPP]],"COBRO CPP",Tabla4[[#This Row],[SALDO PENDIENTE]]>0,"PENDIENTE")} -> PAZ Y SALVO | AI19: N/A | AJ19: N/A | AK19: N/A | AL19: N/A | AM19: N/A | AN19: N/A | AO19: N/A | AP19: N/A | AQ19: Reservada - Con Contrato | AR19: 45736 | AS19: =AA19 -> 299000 | AT19: 30474576 | AU19: GISA | AV19: 1967 | AW19: =ABONOS!O20 -> 0 | AX19: {=_xlfn.IFS(Tabla4[[#This Row],[MONTO5]]=0,"",Tabla4[[#This Row],[SALDO PENDIENTE3]]=0,"PAZ Y SALVO",Tabla4[[#This Row],[SALDO PENDIENTE3]]>0,"PENDIENTE")} -> PAZ Y SALVO | AY19: INSCRITA Y DESEMBOLSADA | AZ19: 45809 | BA19: SI | BB19: 45821 | BC19: =Tabla4[[#This Row],[FECHA RECIBIDO MINUTA LIBERACION]]-Tabla4[[#This Row],[SOLICITUD DE MINUTA LIBERACIÓN]] -> 12 | BD19: 45808 | BE19: 45808 | BF19: N/A | BG19: N/A | BH19: N/A | BI19: N/A | BJ19: N/A | BK19: 45809 | BL19: 45809 | BM19: 45833 | BN19: 45838 | BO19: 45842 | BP19: =Tabla4[[#This Row],[RECEPCIÓN INTERINO]]-Tabla4[[#This Row],[ENVIO A INTERINO]] -> 4 | BQ19: 45874 | BR19: 45859 | BS19: 45874 | BT19: 45876 | BU19: N/A | BV19: SI | BW19: 45809 | BX19: 45878 | BY19: 45887 | BZ19: 45893 | CA19: N/A | CB19: N/A | CC19: 45814
A20: L-408 | B20: -100 | C20: CONSTRUA INTERNATIONAL | D20: TRASPASADO | E20: INSCRITO Y DESEMBOLSADO | F20: 44986 | G20: 111800167 | H20: COSTARRICENSE | I20: EXTRANJERO RESIDENTE | J20: GESPROBAN | K20: 30567 | L20: INDEPENDIENTE | M20: INGENIERO | N20: CONTADO | O20: SI | P20: NO | Q20: N/A | R20: 0 | S20: D | T20: 109.27 | U20: 0 | V20: =U20+T20 -> 109.27 | X20: =AB20*T20 -> 267711.5 | AA20: =250000 -> 250000 | AB20: 2450 | AC20: =((AD20*1)/AA20) -> 1 | AD20: =SUMIFS(Tabla35[Abonos],Tabla35[Lote],Tabla4[[#This Row],[UNIDAD APTO]],Tabla35[Cliente],Tabla4[[#This Row],[CLIENTE]],Tabla35[Concepto],"ABONO")+SUMIFS(Tabla35[Abonos],Tabla35[Lote],Tabla4[[#This Row],[UNIDAD APTO]],Tabla35[Cliente],Tabla4[[#This Row],[CLIENTE]],Tabla35[Concepto],"MULTIBANK") -> 250000 | AE20: =Tabla4[[#This Row],[VALOR TOTAL]]-Tabla4[[#This Row],[MONTO A MULTIBANK]] -> 250000 | AF20: 0 | AG20: =ABONOS!E21 -> 0 | AH20: {=_xlfn.IFS(Tabla4[[#This Row],[RESERVADAS, VENDIDAS]]="DISPONIBLE","",Tabla4[[#This Row],[SALDO PENDIENTE]]=0,"PAZ Y SALVO",Tabla4[[#This Row],[SALDO PENDIENTE]]=Tabla4[[#This Row],[MONTO CPP]],"COBRO CPP",Tabla4[[#This Row],[SALDO PENDIENTE]]>0,"PENDIENTE")} -> PAZ Y SALVO | AI20: N/A | AJ20: N/A | AK20: N/A | AL20: N/A | AM20: N/A | AN20: N/A | AO20: N/A | AP20: N/A | AQ20: Reservada - Con Contrato | AR20: 45100 | AS20: =AA20 -> 250000 | AT20: 30474575 | AU20: GISA | AV20: 2078 | AW20: =ABONOS!O21 -> 0 | AX20: {=_xlfn.IFS(Tabla4[[#This Row],[MONTO5]]=0,"",Tabla4[[#This Row],[SALDO PENDIENTE3]]=0,"PAZ Y SALVO",Tabla4[[#This Row],[SALDO PENDIENTE3]]>0,"PENDIENTE")} -> PAZ Y SALVO | AY20: INSCRITA Y DESEMBOLSADA | AZ20: 45862 | BA20: SI | BB20: 45869 | BC20: =Tabla4[[#This Row],[FECHA RECIBIDO MINUTA LIBERACION]]-Tabla4[[#This Row],[SOLICITUD DE MINUTA LIBERACIÓN]] -> 7 | BD20: SI | BE20: 45637 | BF20: N/A | BG20: N/A | BH20: N/A | BI20: N/A | BJ20: N/A | BK20: 45637 | BL20: 45637 | BM20: 45637 | BN20: 45945 | BO20: 45952 | BP20: =Tabla4[[#This Row],[RECEPCIÓN INTERINO]]-Tabla4[[#This Row],[ENVIO A INTERINO]] -> 7 | BQ20: 45985 | BR20: 45968 | BS20: 45986 | BT20: 45986 | BU20: N/A | BV20: SI | BW20: 45637 | BX20: 45988 | BY20: 45992 | BZ20: 46004 | CA20: N/A | CB20: N/A | CC20: 45649
A21: L-409 | B21: -100 | C21: BOJAN MALISEVIC / ZORAN MALISEVIC | D21: TRASPASADO | E21: INSCRITO Y DESEMBOLSADO | F21: 45793 | G21: X6314258 | H21: SUIZA | I21: EXTRANJERO RESIDENTE | J21: JINELLY ROJAS | K21: 20513 | L21: INDEPENDIENTE | M21: VENTAS | N21: CONTADO | O21: SI | P21: NO | Q21: SI | R21: 15000 | S21: C1 | T21: 73.09 | U21: 0 | V21: =U21+T21 -> 73.09 | X21: =AB21*T21 -> 179070.5 | AA21: 205000 | AB21: 2450 | AC21: =((AD21*1)/AA21) -> 1 | AD21: =SUMIFS(Tabla35[Abonos],Tabla35[Lote],Tabla4[[#This Row],[UNIDAD APTO]],Tabla35[Cliente],Tabla4[[#This Row],[CLIENTE]],Tabla35[Concepto],"ABONO")+SUMIFS(Tabla35[Abonos],Tabla35[Lote],Tabla4[[#This Row],[UNIDAD APTO]],Tabla35[Cliente],Tabla4[[#This Row],[CLIENTE]],Tabla35[Concepto],"MULTIBANK") -> 205000 | AE21: =Tabla4[[#This Row],[VALOR TOTAL]]-Tabla4[[#This Row],[MONTO A MULTIBANK]] -> 155000 | AF21: 50000 | AG21: =ABONOS!E22 -> 0 | AH21: {=_xlfn.IFS(Tabla4[[#This Row],[RESERVADAS, VENDIDAS]]="DISPONIBLE","",Tabla4[[#This Row],[SALDO PENDIENTE]]=0,"PAZ Y SALVO",Tabla4[[#This Row],[SALDO PENDIENTE]]=Tabla4[[#This Row],[MONTO CPP]],"COBRO CPP",Tabla4[[#This Row],[SALDO PENDIENTE]]>0,"PENDIENTE")} -> PAZ Y SALVO | AI21: N/A | AJ21: N/A | AK21: N/A | AL21: N/A | AM21: N/A | AN21: N/A | AO21: N/A | AP21: N/A | AQ21: Reservada - Con Contrato | AR21: 45800 | AS21: =AA21 -> 205000 | AT21: 30474574 | AU21: GISA | AV21: 1900 | AW21: =ABONOS!O22 -> 0 | AX21: {=_xlfn.IFS(Tabla4[[#This Row],[MONTO5]]=0,"",Tabla4[[#This Row],[SALDO PENDIENTE3]]=0,"PAZ Y SALVO",Tabla4[[#This Row],[SALDO PENDIENTE3]]>0,"PENDIENTE")} -> PAZ Y SALVO | AY21: INSCRITA Y DESEMBOLSADA | AZ21: 45875 | BA21: SI | BB21: 45881 | BC21: =Tabla4[[#This Row],[FECHA RECIBIDO MINUTA LIBERACION]]-Tabla4[[#This Row],[SOLICITUD DE MINUTA LIBERACIÓN]] -> 6 | BD21: SI | BE21: 45883 | BF21: N/A | BG21: N/A | BH21: N/A | BI21: N/A | BJ21: N/A | BK21: 45889 | BL21: 45920 | BM21: 45892 | BN21: 45940 | BO21: 45950 | BP21: =Tabla4[[#This Row],[RECEPCIÓN INTERINO]]-Tabla4[[#This Row],[ENVIO A INTERINO]] -> 10 | BQ21: 45950 | BR21: 45931 | BS21: 45951 | BT21: 45951 | BU21: N/A | BV21: SI | BW21: 45951 | BX21: 45951 | BY21: 45959 | BZ21: 45961 | CA21: N/A | CB21: N/A | CC21: 45892
A22: L-410 | B22: -100 | C22: MICHAEL BELANGER | D22: TRASPASADO | E22: INSCRITO Y DESEMBOLSADO | F22: 45108 | G22: 8-812-1508 | H22: PANAMEÑA | I22: NACIONAL | J22: BELANGER REALTY PANAMA | K22: 32177 | L22: ASALARIADO | M22: COMUNICADOR CORPORATIVO | N22: CONTADO | O22: SI | P22: NO | Q22: NO | R22: 12000 | S22: B | T22: 59.94 | U22: 0 | V22: =U22+T22 -> 59.94 | X22: =AB22*T22 -> 146853 | AA22: =X22+W22+Y22+Z22 -> 146853 | AB22: 2450 | AC22: =((AD22*1)/AA22) -> 1 | AD22: =SUMIFS(Tabla35[Abonos],Tabla35[Lote],Tabla4[[#This Row],[UNIDAD APTO]],Tabla35[Cliente],Tabla4[[#This Row],[CLIENTE]],Tabla35[Concepto],"ABONO")+SUMIFS(Tabla35[Abonos],Tabla35[Lote],Tabla4[[#This Row],[UNIDAD APTO]],Tabla35[Cliente],Tabla4[[#This Row],[CLIENTE]],Tabla35[Concepto],"MULTIBANK") -> 146853 | AE22: =Tabla4[[#This Row],[VALOR TOTAL]]-Tabla4[[#This Row],[MONTO A MULTIBANK]] -> 44055.9 | AF22: =AA22*70% -> 102797.1 | AG22: =ABONOS!E23 -> 0 | AH22: {=_xlfn.IFS(Tabla4[[#This Row],[RESERVADAS, VENDIDAS]]="DISPONIBLE","",Tabla4[[#This Row],[SALDO PENDIENTE]]=0,"PAZ Y SALVO",Tabla4[[#This Row],[SALDO PENDIENTE]]=Tabla4[[#This Row],[MONTO CPP]],"COBRO CPP",Tabla4[[#This Row],[SALDO PENDIENTE]]>0,"PENDIENTE")} -> PAZ Y SALVO | AI22: N/A | AJ22: N/A | AK22: N/A | AL22: N/A | AM22: N/A | AN22: N/A | AO22: N/A | AP22: N/A | AQ22: Reservada - Con Contrato | AR22: 45167 | AS22: =AA22 -> 146853 | AT22: 30474573 | AU22: GISA | AV22: 450 | AW22: =ABONOS!O23 -> 0 | AX22: {=_xlfn.IFS(Tabla4[[#This Row],[MONTO5]]=0,"",Tabla4[[#This Row],[SALDO PENDIENTE3]]=0,"PAZ Y SALVO",Tabla4[[#This Row],[SALDO PENDIENTE3]]>0,"PENDIENTE")} -> PAZ Y SALVO | AY22: INSCRITA Y DESEMBOLSADA | AZ22: 45485 | BA22: SI | BB22: 45497 | BC22: =Tabla4[[#This Row],[FECHA RECIBIDO MINUTA LIBERACION]]-Tabla4[[#This Row],[SOLICITUD DE MINUTA LIBERACIÓN]] -> 12 | BD22: SI | BE22: 45499 | BF22: N/A | BG22: N/A | BH22: N/A | BI22: N/A | BJ22: N/A | BK22: 45503 | BL22: 45543 | BM22: 45524 | BN22: 45530 | BO22: 45534 | BP22: =Tabla4[[#This Row],[RECEPCIÓN INTERINO]]-Tabla4[[#This Row],[ENVIO A INTERINO]] -> 4 | BQ22: 45540 | BR22: 45540 | BS22: 45539 | BT22: 45540 | BU22: N/A | BV22: SI | BW22: 45505 | BX22: 45544 | BY22: 45551 | BZ22: 45553 | CA22: N/A | CB22: N/A | CC22: 45548
A23: L-411 | B23: -100 | C23: KOYNE LOISELLE | D23: TRASPASADO | E23: INSCRITO Y DESEMBOLSADO | F23: 44986 | G23: HD813149 | H23: CANADIENSE | I23: EXTRANJERO NO RESIDENTE | J23: PANAMA PACIFICA REALTY | K23: 25833 | L23: INDEPENDIENTE | M23: BIENES RAICES | N23: CONTADO | O23: SI | P23: NO | Q23: N/A | S23: A | T23: 65.93 | U23: 0 | V23: =U23+T23 -> 65.93 | X23: =AB23*T23 -> 161528.5 | AA23: =X23+W23+Y23+Z23 -> 161528.5 | AB23: 2450 | AC23: =((AD23*1)/AA23) -> 1 | AD23: =SUMIFS(Tabla35[Abonos],Tabla35[Lote],Tabla4[[#This Row],[UNIDAD APTO]],Tabla35[Cliente],Tabla4[[#This Row],[CLIENTE]],Tabla35[Concepto],"ABONO")+SUMIFS(Tabla35[Abonos],Tabla35[Lote],Tabla4[[#This Row],[UNIDAD APTO]],Tabla35[Cliente],Tabla4[[#This Row],[CLIENTE]],Tabla35[Concepto],"MULTIBANK") -> 161528.5 | AE23: =Tabla4[[#This Row],[VALOR TOTAL]]-Tabla4[[#This Row],[MONTO A MULTIBANK]] -> 48458.55 | AF23: =AA23*70% -> 113069.95 | AG23: =ABONOS!E24 -> 0 | AH23: {=_xlfn.IFS(Tabla4[[#This Row],[RESERVADAS, VENDIDAS]]="DISPONIBLE","",Tabla4[[#This Row],[SALDO PENDIENTE]]=0,"PAZ Y SALVO",Tabla4[[#This Row],[SALDO PENDIENTE]]=Tabla4[[#This Row],[MONTO CPP]],"COBRO CPP",Tabla4[[#This Row],[SALDO PENDIENTE]]>0,"PENDIENTE")} -> PAZ Y SALVO | AI23: N/A | AJ23: N/A | AK23: N/A | AL23: N/A | AM23: N/A | AN23: N/A | AO23: N/A | AP23: N/A | AQ23: Reservada - Con Contrato | AR23: 45073 | AS23: =AA23 -> 161528.5 | AT23: 30474572 | AU23: GISA | AV23: 1550 | AW23: =ABONOS!O24 -> 77.1 | AX23: {=_xlfn.IFS(Tabla4[[#This Row],[MONTO5]]=0,"",Tabla4[[#This Row],[SALDO PENDIENTE3]]=0,"PAZ Y SALVO",Tabla4[[#This Row],[SALDO PENDIENTE3]]>0,"PENDIENTE")} -> PENDIENTE | AY23: INSCRITA Y DESEMBOLSADA | AZ23: 45455 | BA23: SI | BB23: 45495 | BC23: =Tabla4[[#This Row],[FECHA RECIBIDO MINUTA LIBERACION]]-Tabla4[[#This Row],[SOLICITUD DE MINUTA LIBERACIÓN]] -> 40 | BD23: SI | BE23: 45458 | BF23: N/A | BG23: N/A | BH23: N/A | BI23: N/A | BJ23: N/A | BK23: 45510 | BL23: 45517 | BM23: 45510 | BN23: 45530 | BO23: 45533 | BP23: =Tabla4[[#This Row],[RECEPCIÓN INTERINO]]-Tabla4[[#This Row],[ENVIO A INTERINO]] -> 3 | BQ23: 45544 | BR23: 45540 | BS23: 45539 | BT23: 45545 | BU23: N/A | BV23: SI | BW23: 45511 | BX23: 45546 | BY23: 45547 | BZ23: 45553 | CA23: N/A | CB23: N/A | CC23: 45511
A24: L-301 | B24: -200 | C24: SCOTT WAYNE / THI LE NETTIE | D24: TRASPASADO | E24: INSCRITO Y DESEMBOLSADO | F24: 45170 | G24: E-8-204924 / E-8-204917 | H24: CANADIENSE | I24: EXTRANJERO NO RESIDENTE | J24: PANAMA EQUITY | K24: 23264 | L24: INDEPENDIENTE | M24: ADMINISTRADOR DE EMPRESAS | N24: CONTADO | O24: SI | P24: SI | Q24: SI | R24: 14000 | S24: A | T24: 65.93 | U24: 0 | V24: =U24+T24 -> 65.93 | X24: 202000 | AA24: =X24+W24+Y24+Z24 -> 202000 | AB24: 2400 | AC24: =((AD24*1)/AA24) -> 1 | AD24: =SUMIFS(Tabla35[Abonos],Tabla35[Lote],Tabla4[[#This Row],[UNIDAD APTO]],Tabla35[Cliente],Tabla4[[#This Row],[CLIENTE]],Tabla35[Concepto],"ABONO")+SUMIFS(Tabla35[Abonos],Tabla35[Lote],Tabla4[[#This Row],[UNIDAD APTO]],Tabla35[Cliente],Tabla4[[#This Row],[CLIENTE]],Tabla35[Concepto],"MULTIBANK") -> 202000 | AE24: =Tabla4[[#This Row],[VALOR TOTAL]]-Tabla4[[#This Row],[MONTO A MULTIBANK]] -> 70700 | AF24: =AA24*65% -> 131300 | AG24: =ABONOS!E25 -> 0 | AH24: {=_xlfn.IFS(Tabla4[[#This Row],[RESERVADAS, VENDIDAS]]="DISPONIBLE","",Tabla4[[#This Row],[SALDO PENDIENTE]]=0,"PAZ Y SALVO",Tabla4[[#This Row],[SALDO PENDIENTE]]=Tabla4[[#This Row],[MONTO CPP]],"COBRO CPP",Tabla4[[#This Row],[SALDO PENDIENTE]]>0,"PENDIENTE")} -> PAZ Y SALVO | AI24: TOWERBANK | AJ24: N/A | AK24: N/A | AL24: CON CPP | AM24: 45456 | AN24: 45635 | AO24: FONDO PROPIOS PIGNORADOS | AP24: 73016.96 | AQ24: Reservada - Con Contrato | AR24: 45229 | AS24: =AA24 -> 202000 | AT24: 30474594 | AU24: GISA | AV24: 1870 | AW24: =ABONOS!O25 -> 0 | AX24: {=_xlfn.IFS(Tabla4[[#This Row],[MONTO5]]=0,"",Tabla4[[#This Row],[SALDO PENDIENTE3]]=0,"PAZ Y SALVO",Tabla4[[#This Row],[SALDO PENDIENTE3]]>0,"PENDIENTE")} -> PAZ Y SALVO | AY24: INSCRITA Y DESEMBOLSADA | AZ24: 45478 | BA24: SI | BB24: 45497 | BC24: =Tabla4[[#This Row],[FECHA RECIBIDO MINUTA LIBERACION]]-Tabla4[[#This Row],[SOLICITUD DE MINUTA LIBERACIÓN]] -> 19 | BD24: SI | BE24: 45497 | BF24: N/A | BG24: N/A | BH24: N/A | BI24: N/A | BJ24: N/A | BK24: 45502 | BL24: 45533 | BM24: 45533 | BN24: 45533 | BO24: 45539 | BP24: =Tabla4[[#This Row],[RECEPCIÓN INTERINO]]-Tabla4[[#This Row],[ENVIO A INTERINO]] -> 6 | BQ24: 45544 | BR24: 45539 | BS24: 45539 | BT24: 45545 | BU24: N/A | BV24: SI | BW24: 45502 | BX24: 45546 | BY24: 45559 | BZ24: 45560 | CA24: 45560 | CB24: 45567 | CC24: 45536
A25: L-302 | B25: -200 | C25: CARLOS ARAGON | D25: TRASPASADO | E25: INSCRITO Y DESEMBOLSADO | F25: 45292 | G25: 668069351 | H25: ESTADOUNIDENSE | I25: EXTRANJERO NO RESIDENTE | J25: MARISOL CUESTA Y BELANGER REALTY PANAMA S.A. | K25: 26279 | L25: INDEPENDIENTE | M25: ADMINISTRADOR DE EMPRESAS | N25: CONTADO | O25: SI | P25: NO | Q25: N/A | R25: N/A | S25: B | T25: 59.94 | U25: 0 | V25: =U25+T25 -> 59.94 | X25: =AB25*T25 -> 143856 | AA25: 145000 | AB25: 2400 | AC25: =((AD25*1)/AA25) -> 0.99960621 | AD25: =SUMIFS(Tabla35[Abonos],Tabla35[Lote],Tabla4[[#This Row],[UNIDAD APTO]],Tabla35[Cliente],Tabla4[[#This Row],[CLIENTE]],Tabla35[Concepto],"ABONO")+SUMIFS(Tabla35[Abonos],Tabla35[Lote],Tabla4[[#This Row],[UNIDAD APTO]],Tabla35[Cliente],Tabla4[[#This Row],[CLIENTE]],Tabla35[Concepto],"MULTIBANK") -> 144942.9 | AE25: =Tabla4[[#This Row],[VALOR TOTAL]]-Tabla4[[#This Row],[MONTO A MULTIBANK]] -> 145000 | AF25: 0 | AG25: =ABONOS!E26 -> 57.1 | AH25: {=_xlfn.IFS(Tabla4[[#This Row],[RESERVADAS, VENDIDAS]]="DISPONIBLE","",Tabla4[[#This Row],[SALDO PENDIENTE]]=0,"PAZ Y SALVO",Tabla4[[#This Row],[SALDO PENDIENTE]]=Tabla4[[#This Row],[MONTO CPP]],"COBRO CPP",Tabla4[[#This Row],[SALDO PENDIENTE]]>0,"PENDIENTE")} -> PENDIENTE | AI25: N/A | AJ25: N/A | AK25: N/A | AL25: N/A | AM25: N/A | AN25: N/A | AO25: ACUERDO FINANCIAMIENTO INTERNO | AP25: N/A | AQ25: Reservada - Con Contrato | AR25: 45464 | AS25: =AA25 -> 145000 | AT25: 30474593 | AU25: GISA | AV25: 1593 | AW25: =ABONOS!O26 -> 0 | AX25: {=_xlfn.IFS(Tabla4[[#This Row],[MONTO5]]=0,"",Tabla4[[#This Row],[SALDO PENDIENTE3]]=0,"PAZ Y SALVO",Tabla4[[#This Row],[SALDO PENDIENTE3]]>0,"PENDIENTE")} -> PAZ Y SALVO | AY25: INSCRITA Y DESEMBOLSADA | AZ25: 45862 | BA25: SI | BB25: 45869 | BC25: =Tabla4[[#This Row],[FECHA RECIBIDO MINUTA LIBERACION]]-Tabla4[[#This Row],[SOLICITUD DE MINUTA LIBERACIÓN]] -> 7 | BD25: SI | BE25: 45967 | BF25: N/A | BG25: N/A | BH25: N/A | BI25: N/A | BJ25: N | BK25: 45967 | BL25: 45969 | BM25: 45969 | BN25: 45975 | BO25: 45984 | BP25: =Tabla4[[#This Row],[RECEPCIÓN INTERINO]]-Tabla4[[#This Row],[ENVIO A INTERINO]] -> 9 | BQ25: 45985 | BR25: 45968 | BS25: 45986 | BT25: 45986 | BU25: N/A | BV25: SI | BW25: 45969 | BX25: 45988 | BY25: 45988 | BZ25: 45996 | CA25: N/A | CB25: N/A | CC25: 45478
A26: L-303 | B26: -200 | C26: INDIRA GARCIA | D26: TRASPASADO | E26: INSCRITO Y DESEMBOLSADO | F26: 45658 | G26: 6-710-242 | H26: PANAMEÑA | I26: NACIONAL | J26: GESPROBAN | K26: 31216 | L26: ASALARIADO | M26: MEDICO | N26: FINANCIAMIENTO | O26: NO | P26: NO | Q26: N/A | R26: N/A | S26: C1 | T26: 73.09 | U26: 0 | V26: =U26+T26 -> 73.09 | X26: =AB26*T26 -> 175416 | AA26: 187000 | AB26: 2400 | AC26: =((AD26*1)/AA26) -> 1 | AD26: =SUMIFS(Tabla35[Abonos],Tabla35[Lote],Tabla4[[#This Row],[UNIDAD APTO]],Tabla35[Cliente],Tabla4[[#This Row],[CLIENTE]],Tabla35[Concepto],"ABONO")+SUMIFS(Tabla35[Abonos],Tabla35[Lote],Tabla4[[#This Row],[UNIDAD APTO]],Tabla35[Cliente],Tabla4[[#This Row],[CLIENTE]],Tabla35[Concepto],"MULTIBANK") -> 187000 | AE26: =Tabla4[[#This Row],[VALOR TOTAL]]-Tabla4[[#This Row],[MONTO A MULTIBANK]] -> 17692.69 | AF26: =Tabla4[[#This Row],[MONTO CPP]] -> 169307.31 | AG26: =ABONOS!E27 -> 0 | AH26: {=_xlfn.IFS(Tabla4[[#This Row],[RESERVADAS, VENDIDAS]]="DISPONIBLE","",Tabla4[[#This Row],[SALDO PENDIENTE]]=0,"PAZ Y SALVO",Tabla4[[#This Row],[SALDO PENDIENTE]]=Tabla4[[#This Row],[MONTO CPP]],"COBRO CPP",Tabla4[[#This Row],[SALDO PENDIENTE]]>0,"PENDIENTE")} -> PAZ Y SALVO | AI26: COOPERATIVA DE PROFESIONALES, R.L. | AL26: CON CPP | AM26: 45728 | AN26: 46093 | AO26: CON CPP | AP26: 169307.31 | AQ26: Reservada - Con Contrato | AR26: 45677 | AS26: =AA26 -> 187000 | AT26: 30474592 | AU26: BANCO | AV26: BANCO | AW26: =ABONOS!O27 -> 0 | AX26: {=_xlfn.IFS(Tabla4[[#This Row],[MONTO5]]=0,"",Tabla4[[#This Row],[SALDO PENDIENTE3]]=0,"PAZ Y SALVO",Tabla4[[#This Row],[SALDO PENDIENTE3]]>0,"PENDIENTE")} -> PAZ Y SALVO | AY26: INSCRITA Y DESEMBOLSADA | AZ26: 45736 | BA26: SI | BB26: 45749 | BC26: =Tabla4[[#This Row],[FECHA RECIBIDO MINUTA LIBERACION]]-Tabla4[[#This Row],[SOLICITUD DE MINUTA LIBERACIÓN]] -> 13 | BD26: SI | BE26: 45748 | BF26: SI | BG26: 45744 | BH26: 45744 | BI26: 45757 | BJ26: PANAMERICANA DE AVALUOS | BK26: BANCO | BL26: 45771 | BM26: 45782 | BN26: 45772 | BO26: 45775 | BP26: =Tabla4[[#This Row],[RECEPCIÓN INTERINO]]-Tabla4[[#This Row],[ENVIO A INTERINO]] -> 3 | BQ26: 45779 | BR26: 45762 | BS26: 45779 | BT26: 45779 | BU26: 45780 | BV26: SI | BW26: 45770 | BX26: 45789 | BY26: 45792 | BZ26: 45804 | CA26: 45804 | CB26: 45811 | CC26: 45871
A27: L-304 | B27: -200 | C27: JAMES STORK Y RUTH URIETA | D27: TRASPASADO | E27: INSCRITO Y DESEMBOLSADO | F27: 45717 | G27: 556318808 / 8-297-14 | H27: PANAMEÑA | I27: NACIONAL | J27: GESPROBAN | K27: 21859 | L27: ASALARIADO | N27: CONTADO | O27: NO | P27: NO | Q27: N/A | R27: N/A | S27: C1 | T27: 73.09 | U27: 0 | V27: =U27+T27 -> 73.09 | X27: =AB27*T27 -> 175416 | AA27: 183000 | AB27: 2400 | AC27: =((AD27*1)/AA27) -> 1 | AD27: =SUMIFS(Tabla35[Abonos],Tabla35[Lote],Tabla4[[#This Row],[UNIDAD APTO]],Tabla35[Cliente],Tabla4[[#This Row],[CLIENTE]],Tabla35[Concepto],"ABONO")+SUMIFS(Tabla35[Abonos],Tabla35[Lote],Tabla4[[#This Row],[UNIDAD APTO]],Tabla35[Cliente],Tabla4[[#This Row],[CLIENTE]],Tabla35[Concepto],"MULTIBANK") -> 183000 | AE27: =Tabla4[[#This Row],[VALOR TOTAL]]-AF27 -> 54900 | AF27: =Tabla4[[#This Row],[VALOR TOTAL]]*70% -> 128100 | AG27: =ABONOS!E28 -> 0 | AH27: {=_xlfn.IFS(Tabla4[[#This Row],[RESERVADAS, VENDIDAS]]="DISPONIBLE","",Tabla4[[#This Row],[SALDO PENDIENTE]]=0,"PAZ Y SALVO",Tabla4[[#This Row],[SALDO PENDIENTE]]=Tabla4[[#This Row],[MONTO CPP]],"COBRO CPP",Tabla4[[#This Row],[SALDO PENDIENTE]]>0,"PENDIENTE")} -> PAZ Y SALVO | AI27: N/A | AJ27: N/A | AK27: N/A | AL27: N/A | AM27: N/A | AN27: N/A | AO27: N/A | AP27: N/A | AQ27: Reservada - Con Contrato | AR27: 45736 | AT27: 30474591 | AU27: GISA | AV27: 1619 | AW27: =ABONOS!O28 -> 0 | AX27: {=_xlfn.IFS(Tabla4[[#This Row],[MONTO5]]=0,"",Tabla4[[#This Row],[SALDO PENDIENTE3]]=0,"PAZ Y SALVO",Tabla4[[#This Row],[SALDO PENDIENTE3]]>0,"PENDIENTE")} -> PAZ Y SALVO | AY27: INSCRITA Y DESEMBOLSADA | AZ27: 45804 | BA27: SI | BB27: 45814 | BC27: =Tabla4[[#This Row],[FECHA RECIBIDO MINUTA LIBERACION]]-Tabla4[[#This Row],[SOLICITUD DE MINUTA LIBERACIÓN]] -> 10 | BD27: SI | BE27: 45821 | BF27: N/A | BG27: N/A | BH27: N/A | BI27: N/A | BJ27: N/A | BK27: 45831 | BL27: 45835 | BM27: 45833 | BN27: 45838 | BO27: 45842 | BP27: =Tabla4[[#This Row],[RECEPCIÓN INTERINO]]-Tabla4[[#This Row],[ENVIO A INTERINO]] -> 4 | BQ27: 45874 | BR27: 45859 | BS27: 45874 | BT27: 45876 | BU27: N/A | BV27: SI | BW27: 45831 | BX27: 45878 | BY27: 45887 | BZ27: 45893 | CA27: N/A | CB27: N/A | CC27: 45803
A28: L-305 | B28: -200 | C28: GRUPO DICOS | D28: VENDIDO | E28: CON CLIENTE | F28: 45712 | H28: PANAMEÑA | I28: NACIONAL | J28: GESPROBAN | L28: INDEPENDIENTE | M28: EMPRESA ELECTRICIDAD | N28: CONTADO | S28: C1 | T28: 73.09 | U28: 0 | V28: =U28+T28 -> 73.09 | X28: =AB28*T28 -> 175416 | AA28: 187976.82 | AB28: 2400 | AC28: =((AD28*1)/AA28) -> 0.49474185 | AD28: =SUMIFS(Tabla35[Abonos],Tabla35[Lote],Tabla4[[#This Row],[UNIDAD APTO]],Tabla35[Cliente],Tabla4[[#This Row],[CLIENTE]],Tabla35[Concepto],"ABONO")+SUMIFS(Tabla35[Abonos],Tabla35[Lote],Tabla4[[#This Row],[UNIDAD APTO]],Tabla35[Cliente],Tabla4[[#This Row],[CLIENTE]],Tabla35[Concepto],"MULTIBANK") -> 93000 | AE28: =Tabla4[[#This Row],[VALOR TOTAL]]-Tabla4[[#This Row],[MONTO A MULTIBANK]] -> 187976.82 | AF28: 0 | AG28: =ABONOS!E29 -> 94976.82 | AH28: {=_xlfn.IFS(Tabla4[[#This Row],[RESERVADAS, VENDIDAS]]="DISPONIBLE","",Tabla4[[#This Row],[SALDO PENDIENTE]]=0,"PAZ Y SALVO",Tabla4[[#This Row],[SALDO PENDIENTE]]=Tabla4[[#This Row],[MONTO CPP]],"COBRO CPP",Tabla4[[#This Row],[SALDO PENDIENTE]]>0,"PENDIENTE")} -> PENDIENTE | AI28: N/A | AJ28: N/A | AK28: N/A | AL28: N/A | AM28: N/A | AN28: N/A | AO28: N/A | AP28: N/A | AQ28: Reservada - Con Contrato | AR28: 45713 | AS28: 187976.82 | AT28: 30474590 | AW28: =ABONOS!O29 -> 0 | AX28: {=_xlfn.IFS(Tabla4[[#This Row],[MONTO5]]=0,"",Tabla4[[#This Row],[SALDO PENDIENTE3]]=0,"PAZ Y SALVO",Tabla4[[#This Row],[SALDO PENDIENTE3]]>0,"PENDIENTE")} | AY28: CONTRATO FIRMADO | AZ28: 45862 | BA28: SI | BB28: 45869 | BC28: =Tabla4[[#This Row],[FECHA RECIBIDO MINUTA LIBERACION]]-Tabla4[[#This Row],[SOLICITUD DE MINUTA LIBERACIÓN]] -> 7 | BP28: =Tabla4[[#This Row],[RECEPCIÓN INTERINO]]-Tabla4[[#This Row],[ENVIO A INTERINO]] -> 0 | BU28: N/A | CC28: 45813
A29: L-306 | B29: -200 | C29: LUIS ENRIQUE QUIROS CORDERO | D29: VENDIDO | E29: CON CLIENTE | F29: 45658 | G29: G385623 | H29: COSTARRICENSE | I29: EXTRANJERO NO RESIDENTE | J29: GESPROBAN | K29: 27955 | L29: INDEPENDIENTE | M29: GANADERO / COMERCIANTE | N29: CONTADO | O29: SI | P29: SI | Q29: SI | R29: 15000 | S29: C1 | T29: 73.98 | U29: 0 | V29: =U29+T29 -> 73.98 | X29: =AB29*T29 -> 177552 | AA29: 198850 | AB29: 2400 | AC29: =((AD29*1)/AA29) -> 0 | AD29: =SUMIFS(Tabla35[Abonos],Tabla35[Lote],Tabla4[[#This Row],[UNIDAD APTO]],Tabla35[Cliente],Tabla4[[#This Row],[CLIENTE]],Tabla35[Concepto],"ABONO")+SUMIFS(Tabla35[Abonos],Tabla35[Lote],Tabla4[[#This Row],[UNIDAD APTO]],Tabla35[Cliente],Tabla4[[#This Row],[CLIENTE]],Tabla35[Concepto],"MULTIBANK") -> 0 | AE29: =Tabla4[[#This Row],[VALOR TOTAL]]-Tabla4[[#This Row],[MONTO A MULTIBANK]] -> 198850 | AF29: 0 | AG29: =ABONOS!E30 -> 198850 | AH29: {=_xlfn.IFS(Tabla4[[#This Row],[RESERVADAS, VENDIDAS]]="DISPONIBLE","",Tabla4[[#This Row],[SALDO PENDIENTE]]=0,"PAZ Y SALVO",Tabla4[[#This Row],[SALDO PENDIENTE]]=Tabla4[[#This Row],[MONTO CPP]],"COBRO CPP",Tabla4[[#This Row],[SALDO PENDIENTE]]>0,"PENDIENTE")} | AI29: N/A | AJ29: N/A | AK29: N/A | AL29: N/A | AM29: N/A | AN29: N/A | AO29: N/A | AP29: N/A | AQ29: Reservada - Con Contrato | AR29: 45688 | AT29: 30474589 | AW29: =ABONOS!O30 -> 0 | AX29: {=_xlfn.IFS(Tabla4[[#This Row],[MONTO5]]=0,"",Tabla4[[#This Row],[SALDO PENDIENTE3]]=0,"PAZ Y SALVO",Tabla4[[#This Row],[SALDO PENDIENTE3]]>0,"PENDIENTE")} | AY29: CONTRATO FIRMADO | BC29: =Tabla4[[#This Row],[FECHA RECIBIDO MINUTA LIBERACION]]-Tabla4[[#This Row],[SOLICITUD DE MINUTA LIBERACIÓN]] -> 0 | BP29: =Tabla4[[#This Row],[RECEPCIÓN INTERINO]]-Tabla4[[#This Row],[ENVIO A INTERINO]] -> 0 | BU29: N/A | CC29: 45870
A30: L-307 | B30: -200 | C30: YANIRED GONZALEZ ALVARADO DE ADAMS | D30: TRASPASADO | E30: INSCRITO Y DESEMBOLSADO | F30: 45658 | G30: 8-307-182 | H30: PANAMEÑA | I30: NACIONAL | J30: GESPROBAN | K30: 25201 | L30: INDEPENDIENTE | M30: ADMINISTRADOR DE EMPRESAS | N30: CONTADO | O30: NO | P30: NO | Q30: NO | R30: 0 | S30: C1 | T30: 73.98 | U30: 0 | V30: =U30+T30 -> 73.98 | X30: =AB30*T30 -> 177552 | AA30: 187000 | AB30: 2400 | AC30: =((AD30*1)/AA30) -> 1 | AD30: =SUMIFS(Tabla35[Abonos],Tabla35[Lote],Tabla4[[#This Row],[UNIDAD APTO]],Tabla35[Cliente],Tabla4[[#This Row],[CLIENTE]],Tabla35[Concepto],"ABONO")+SUMIFS(Tabla35[Abonos],Tabla35[Lote],Tabla4[[#This Row],[UNIDAD APTO]],Tabla35[Cliente],Tabla4[[#This Row],[CLIENTE]],Tabla35[Concepto],"MULTIBANK") -> 187000 | AE30: =Tabla4[[#This Row],[VALOR TOTAL]]-Tabla4[[#This Row],[MONTO A MULTIBANK]] -> 56100 | AF30: =Tabla4[[#This Row],[VALOR TOTAL]]*70% -> 130900 | AG30: =ABONOS!E31 -> 0 | AH30: {=_xlfn.IFS(Tabla4[[#This Row],[RESERVADAS, VENDIDAS]]="DISPONIBLE","",Tabla4[[#This Row],[SALDO PENDIENTE]]=0,"PAZ Y SALVO",Tabla4[[#This Row],[SALDO PENDIENTE]]=Tabla4[[#This Row],[MONTO CPP]],"COBRO CPP",Tabla4[[#This Row],[SALDO PENDIENTE]]>0,"PENDIENTE")} -> PAZ Y SALVO | AI30: N/A | AJ30: N/A | AK30: N/A | AL30: N/A | AM30: N/A | AN30: N/A | AO30: N/A | AP30: N/A | AQ30: Reservada - Con Contrato | AR30: 45676 | AS30: =Tabla4[[#This Row],[VALOR TOTAL]] -> 187000 | AT30: 30474588 | AU30: GISA | AV30: 1330 | AW30: =ABONOS!O31 -> 0 | AX30: {=_xlfn.IFS(Tabla4[[#This Row],[MONTO5]]=0,"",Tabla4[[#This Row],[SALDO PENDIENTE3]]=0,"PAZ Y SALVO",Tabla4[[#This Row],[SALDO PENDIENTE3]]>0,"PENDIENTE")} -> PAZ Y SALVO | AY30: INSCRITA Y DESEMBOLSADA | AZ30: 45721 | BA30: SI | BB30: 45729 | BC30: =Tabla4[[#This Row],[FECHA RECIBIDO MINUTA LIBERACION]]-Tabla4[[#This Row],[SOLICITUD DE MINUTA LIBERACIÓN]] -> 8 | BD30: SI | BE30: 45730 | BF30: N/A | BG30: N/A | BH30: N/A | BI30: N/A | BJ30: NA | BK30: 45721 | BL30: 45728 | BM30: 45728 | BN30: 45740 | BO30: 45747 | BP30: =Tabla4[[#This Row],[RECEPCIÓN INTERINO]]-Tabla4[[#This Row],[ENVIO A INTERINO]] -> 7 | BQ30: 45786 | BR30: 45762 | BS30: 45787 | BT30: 45787 | BU30: N/A | BV30: SI | BW30: 45785 | BX30: 45786 | BY30: 45786 | BZ30: 45796 | CA30: N/A | CB30: N/A | CC30: 45727
A31: L-308 | B31: -200 | C31: NORA MORENO | D31: TRASPASADO | E31: INSCRITO Y DESEMBOLSADO | F31: 45474 | G31: 8-799-2141 | H31: PANAMEÑA | I31: NACIONAL | J31: GESPROBAN | K31: 30976 | L31: INDEPENDIENTE | N31: FINANCIAMIENTO | S31: C1 | T31: 73.09 | U31: 0 | V31: =U31+T31 -> 73.09 | X31: =AB31*T31 -> 175416 | AA31: 185000 | AB31: 2400 | AC31: =((AD31*1)/AA31) -> 0.97025065 | AD31: =SUMIFS(Tabla35[Abonos],Tabla35[Lote],Tabla4[[#This Row],[UNIDAD APTO]],Tabla35[Cliente],Tabla4[[#This Row],[CLIENTE]],Tabla35[Concepto],"ABONO")+SUMIFS(Tabla35[Abonos],Tabla35[Lote],Tabla4[[#This Row],[UNIDAD APTO]],Tabla35[Cliente],Tabla4[[#This Row],[CLIENTE]],Tabla35[Concepto],"MULTIBANK") -> 179496.37 | AE31: =Tabla4[[#This Row],[VALOR TOTAL]]-Tabla4[[#This Row],[MONTO A MULTIBANK]] -> 31000 | AF31: =Tabla4[[#This Row],[MONTO CPP]] -> 154000 | AG31: =ABONOS!E32 -> 5503.63 | AH31: {=_xlfn.IFS(Tabla4[[#This Row],[RESERVADAS, VENDIDAS]]="DISPONIBLE","",Tabla4[[#This Row],[SALDO PENDIENTE]]=0,"PAZ Y SALVO",Tabla4[[#This Row],[SALDO PENDIENTE]]=Tabla4[[#This Row],[MONTO CPP]],"COBRO CPP",Tabla4[[#This Row],[SALDO PENDIENTE]]>0,"PENDIENTE")} -> PENDIENTE | AI31: MULTIBANK | AJ31: ALEJANDRO SANCHEZ | AK31: alejandro.sanchez@multibank.com.pa | AL31: CON CPP | AM31: 45478 | AN31: N/A | AO31: CON CPP | AP31: 154000 | AQ31: Reservada - Con Contrato | AR31: 45484 | AS31: 185000 | AT31: 30474587 | AU31: BANCO | AV31: BANCO | AW31: =ABONOS!O32 -> 0 | AX31: {=_xlfn.IFS(Tabla4[[#This Row],[MONTO5]]=0,"",Tabla4[[#This Row],[SALDO PENDIENTE3]]=0,"PAZ Y SALVO",Tabla4[[#This Row],[SALDO PENDIENTE3]]>0,"PENDIENTE")} -> PAZ Y SALVO | AY31: INSCRITA Y DESEMBOLSADA | AZ31: 45483 | BA31: SI | BB31: 45532 | BC31: =Tabla4[[#This Row],[FECHA RECIBIDO MINUTA LIBERACION]]-Tabla4[[#This Row],[SOLICITUD DE MINUTA LIBERACIÓN]] -> 49 | BD31: SI | BE31: 45535 | BF31: SI | BG31: 45539 | BH31: SI | BI31: 45561 | BJ31: AVANCE | BK31: 45547 | BL31: 45548 | BM31: 45551 | BN31: 45551 | BO31: 45555 | BP31: =Tabla4[[#This Row],[RECEPCIÓN INTERINO]]-Tabla4[[#This Row],[ENVIO A INTERINO]] -> 4 | BQ31: 45555 | BR31: 45539 | BS31: 45554 | BT31: 45555 | BU31: 45558 | BV31: SI | BW31: 45548 | BX31: 45567 | BY31: 45567 | BZ31: 45568 | CA31: 45568 | CB31: 45574 | CC31: 45577
A32: L-309 | B32: -200 | C32: SHAROMAY OSMA | D32: TRASPASADO | E32: INSCRITO Y DESEMBOLSADO | F32: 45413 | G32: 8-460-62 | H32: PANAMEÑA | I32: NACIONAL | J32: GESPROBAN | K32: 26994 | L32: ASALARIADO | M32: CIRUJANO MAXILOFACIAL | N32: FINANCIAMIENTO | S32: C1 | T32: 73.09 | U32: 0 | V32: =U32+T32 -> 73.09 | X32: =AB32*T32 -> 175416 | AA32: 180000 | AB32: 2400 | AC32: =((AD32*1)/AA32) -> 1 | AD32: =SUMIFS(Tabla35[Abonos],Tabla35[Lote],Tabla4[[#This Row],[UNIDAD APTO]],Tabla35[Cliente],Tabla4[[#This Row],[CLIENTE]],Tabla35[Concepto],"ABONO")+SUMIFS(Tabla35[Abonos],Tabla35[Lote],Tabla4[[#This Row],[UNIDAD APTO]],Tabla35[Cliente],Tabla4[[#This Row],[CLIENTE]],Tabla35[Concepto],"MULTIBANK") -> 180000 | AE32: =Tabla4[[#This Row],[VALOR TOTAL]]-Tabla4[[#This Row],[MONTO A MULTIBANK]] -> 27000 | AF32: =Tabla4[[#This Row],[MONTO CPP]] -> 153000 | AG32: =ABONOS!E33 -> 0 | AH32: {=_xlfn.IFS(Tabla4[[#This Row],[RESERVADAS, VENDIDAS]]="DISPONIBLE","",Tabla4[[#This Row],[SALDO PENDIENTE]]=0,"PAZ Y SALVO",Tabla4[[#This Row],[SALDO PENDIENTE]]=Tabla4[[#This Row],[MONTO CPP]],"COBRO CPP",Tabla4[[#This Row],[SALDO PENDIENTE]]>0,"PENDIENTE")} -> PAZ Y SALVO | AI32: COOPERATIVA DE PROFESIONALES, R.L. | AL32: CON CPP | AM32: 45533 | AN32: 45898 | AO32: CON CPP | AP32: 153000 | AQ32: Reservada - Con Contrato | AR32: 45505 | AS32: =AA32 -> 180000 | AT32: 30474586 | AU32: BANCO | AV32: BANCO | AW32: =ABONOS!O33 -> 0 | AX32: {=_xlfn.IFS(Tabla4[[#This Row],[MONTO5]]=0,"",Tabla4[[#This Row],[SALDO PENDIENTE3]]=0,"PAZ Y SALVO",Tabla4[[#This Row],[SALDO PENDIENTE3]]>0,"PENDIENTE")} -> PAZ Y SALVO | AY32: INSCRITA Y DESEMBOLSADA | AZ32: 45544 | BA32: SI | BB32: 45565 | BC32: =Tabla4[[#This Row],[FECHA RECIBIDO MINUTA LIBERACION]]-Tabla4[[#This Row],[SOLICITUD DE MINUTA LIBERACIÓN]] -> 21 | BD32: SI | BE32: 45546 | BF32: SI | BG32: 45565 | BH32: 45569 | BI32: 45551 | BJ32: CORPORACIÓN DE INGENIEROS | BK32: 45580 | BL32: 45581 | BM32: 45582 | BN32: 45582 | BO32: 45583 | BP32: =Tabla4[[#This Row],[RECEPCIÓN INTERINO]]-Tabla4[[#This Row],[ENVIO A INTERINO]] -> 1 | BQ32: 45582 | BR32: 45579 | BS32: 45582 | BT32: 45565 | BU32: 45583 | BV32: SI | BW32: 45580 | BX32: 45587 | BY32: 45588 | BZ32: 45589 | CA32: 45589 | CB32: 45614 | CC32: 45656
A33: L-310 | B33: -200 | C33: GERMAN SANCHEZ | D33: TRASPASADO | E33: INSCRITO Y DESEMBOLSADO | F33: 45597 | G33: 9-726-1097 | H33: PANAMEÑA | I33: NACIONAL | J33: GESPROBAN | K33: 31874 | L33: ASALARIADO | M33: INGENIERO NAVAL | N33: FINANCIAMIENTO | O33: NO | P33: NO | Q33: N/A | S33: C1 | T33: 73.09 | U33: 0 | V33: =U33+T33 -> 73.09 | X33: =AB33*T33 -> 175416 | AA33: 185000 | AB33: 2400 | AC33: =((AD33*1)/AA33) -> 1 | AD33: =SUMIFS(Tabla35[Abonos],Tabla35[Lote],Tabla4[[#This Row],[UNIDAD APTO]],Tabla35[Cliente],Tabla4[[#This Row],[CLIENTE]],Tabla35[Concepto],"ABONO")+SUMIFS(Tabla35[Abonos],Tabla35[Lote],Tabla4[[#This Row],[UNIDAD APTO]],Tabla35[Cliente],Tabla4[[#This Row],[CLIENTE]],Tabla35[Concepto],"MULTIBANK") -> 185000 | AE33: =Tabla4[[#This Row],[VALOR TOTAL]]-Tabla4[[#This Row],[MONTO A MULTIBANK]] -> 31000 | AF33: =Tabla4[[#This Row],[MONTO CPP]] -> 154000 | AG33: =ABONOS!E34 -> 0 | AH33: {=_xlfn.IFS(Tabla4[[#This Row],[RESERVADAS, VENDIDAS]]="DISPONIBLE","",Tabla4[[#This Row],[SALDO PENDIENTE]]=0,"PAZ Y SALVO",Tabla4[[#This Row],[SALDO PENDIENTE]]=Tabla4[[#This Row],[MONTO CPP]],"COBRO CPP",Tabla4[[#This Row],[SALDO PENDIENTE]]>0,"PENDIENTE")} -> PAZ Y SALVO | AI33: MULTIBANK | AJ33: ILEANA QUINTERO | AL33: CON CPP | AM33: 45660 | AN33: N/A | AO33: CON CPP | AP33: 154000 | AQ33: Reservada - Con Contrato | AR33: 45605 | AS33: =Tabla4[[#This Row],[VALOR TOTAL]] -> 185000 | AT33: 30474585 | AU33: BANCO | AV33: BANCO | AW33: =ABONOS!O34 -> 0 | AX33: {=_xlfn.IFS(Tabla4[[#This Row],[MONTO5]]=0,"",Tabla4[[#This Row],[SALDO PENDIENTE3]]=0,"PAZ Y SALVO",Tabla4[[#This Row],[SALDO PENDIENTE3]]>0,"PENDIENTE")} -> PAZ Y SALVO | AY33: INSCRITA Y DESEMBOLSADA | AZ33: 45663 | BA33: SI | BB33: 45673 | BC33: =Tabla4[[#This Row],[FECHA RECIBIDO MINUTA LIBERACION]]-Tabla4[[#This Row],[SOLICITUD DE MINUTA LIBERACIÓN]] -> 10 | BD33: SI | BE33: 45673 | BF33: SI | BG33: 45673 | BH33: 45673 | BI33: 45691 | BJ33: AIR AVALUOS | BK33: 45701 | BL33: 45702 | BM33: 45707 | BN33: 45702 | BO33: 45702 | BP33: =Tabla4[[#This Row],[RECEPCIÓN INTERINO]]-Tabla4[[#This Row],[ENVIO A INTERINO]] -> 0 | BQ33: 45706 | BR33: 45706 | BS33: 45706 | BT33: 45706 | BU33: 45706 | BV33: SI | BW33: 45702 | BX33: 45722 | BY33: 45723 | BZ33: 45727 | CA33: 45727 | CB33: 45728 | CC33: 45656
A34: L-311 | B34: -200 | C34: MELINDA MOORE | D34: TRASPASADO | E34: INSCRITO Y DESEMBOLSADO | F34: 45505 | G34: A03717675 | H34: ESTADOUNIDENSE | I34: EXTRANJERO NO RESIDENTE | J34: PANAMA PACIFICA REALTY | K34: 21589 | L34: ASALARIADO | M34: BARTENDER | N34: CONTADO | O34: SI | P34: NO | Q34: NO | R34: 14000 | S34: B | T34: 59.94 | U34: 0 | V34: =U34+T34 -> 59.94 | X34: =AB34*T34 -> 143856 | AA34: 150000 | AB34: 2400 | AC34: =((AD34*1)/AA34) -> 1 | AD34: =SUMIFS(Tabla35[Abonos],Tabla35[Lote],Tabla4[[#This Row],[UNIDAD APTO]],Tabla35[Cliente],Tabla4[[#This Row],[CLIENTE]],Tabla35[Concepto],"ABONO")+SUMIFS(Tabla35[Abonos],Tabla35[Lote],Tabla4[[#This Row],[UNIDAD APTO]],Tabla35[Cliente],Tabla4[[#This Row],[CLIENTE]],Tabla35[Concepto],"MULTIBANK") -> 150000 | AE34: =Tabla4[[#This Row],[VALOR TOTAL]]-Tabla4[[#This Row],[MONTO A MULTIBANK]] -> 45000 | AF34: =70%*AA34 -> 105000 | AG34: =ABONOS!E35 -> 0 | AH34: {=_xlfn.IFS(Tabla4[[#This Row],[RESERVADAS, VENDIDAS]]="DISPONIBLE","",Tabla4[[#This Row],[SALDO PENDIENTE]]=0,"PAZ Y SALVO",Tabla4[[#This Row],[SALDO PENDIENTE]]=Tabla4[[#This Row],[MONTO CPP]],"COBRO CPP",Tabla4[[#This Row],[SALDO PENDIENTE]]>0,"PENDIENTE")} -> PAZ Y SALVO | AI34: N/A | AJ34: N/A | AK34: N/A | AL34: N/A | AM34: N/A | AN34: N/A | AO34: FONDO PROPIOS PIGNORADOS | AP34: N/A | AQ34: Reservada - Con Contrato | AR34: 45708 | AS34: =Tabla4[[#This Row],[VALOR TOTAL]] -> 150000 | AT34: 30474584 | AU34: GISA | AV34: 950 | AW34: =ABONOS!O35 -> 0 | AX34: {=_xlfn.IFS(Tabla4[[#This Row],[MONTO5]]=0,"",Tabla4[[#This Row],[SALDO PENDIENTE3]]=0,"PAZ Y SALVO",Tabla4[[#This Row],[SALDO PENDIENTE3]]>0,"PENDIENTE")} -> PAZ Y SALVO | AY34: INSCRITA Y DESEMBOLSADA | AZ34: 45779 | BA34: SI | BB34: 45784 | BC34: =Tabla4[[#This Row],[FECHA RECIBIDO MINUTA LIBERACION]]-Tabla4[[#This Row],[SOLICITUD DE MINUTA LIBERACIÓN]] -> 5 | BD34: SI | BE34: 45786 | BF34: N/A | BG34: N/A | BH34: N/A | BI34: N/A | BJ34: N/A | BK34: 45796 | BL34: 46038 | BM34: 45789 | BN34: 46041 | BO34: 46042 | BP34: =Tabla4[[#This Row],[RECEPCIÓN INTERINO]]-Tabla4[[#This Row],[ENVIO A INTERINO]] -> 1 | BQ34: 46051 | BR34: 46043 | BS34: 46052 | BT34: 46052 | BU34: N/A | BV34: SI | BW34: 46055 | BX34: 46055 | BY34: 46057 | BZ34: 46079 | CA34: N/A | CB34: N/A
A35: L-312 | B35: -200 | C35: ALVARO MORENO | D35: TRASPASADO | E35: INSCRITO Y DESEMBOLSADO | F35: 45505 | G35: 8-239-2489 | H35: PANAMEÑA | I35: NACIONAL | J35: GESPROBAN | K35: 23297 | L35: ASALARIADO | M35: PRACTICO DEL CANAL | N35: FINANCIAMIENTO | O35: N/A | P35: NO | Q35: N/A | S35: A | T35: 65.93 | U35: 0 | V35: =U35+T35 -> 65.93 | X35: =AB35*T35 -> 158232 | AA35: 172500 | AB35: 2400 | AC35: =((AD35*1)/AA35) -> 1 | AD35: =SUMIFS(Tabla35[Abonos],Tabla35[Lote],Tabla4[[#This Row],[UNIDAD APTO]],Tabla35[Cliente],Tabla4[[#This Row],[CLIENTE]],Tabla35[Concepto],"ABONO")+SUMIFS(Tabla35[Abonos],Tabla35[Lote],Tabla4[[#This Row],[UNIDAD APTO]],Tabla35[Cliente],Tabla4[[#This Row],[CLIENTE]],Tabla35[Concepto],"MULTIBANK") -> 172500 | AE35: =Tabla4[[#This Row],[VALOR TOTAL]]-Tabla4[[#This Row],[MONTO A MULTIBANK]] -> 40000 | AF35: =Tabla4[[#This Row],[MONTO CPP]] -> 132500 | AG35: =ABONOS!E36 -> 0 | AH35: {=_xlfn.IFS(Tabla4[[#This Row],[RESERVADAS, VENDIDAS]]="DISPONIBLE","",Tabla4[[#This Row],[SALDO PENDIENTE]]=0,"PAZ Y SALVO",Tabla4[[#This Row],[SALDO PENDIENTE]]=Tabla4[[#This Row],[MONTO CPP]],"COBRO CPP",Tabla4[[#This Row],[SALDO PENDIENTE]]>0,"PENDIENTE")} -> PAZ Y SALVO | AI35: COOPERATIVA DEL CANAL | AL35: CON CPP | AM35: 45935 | AN35: 45662 | AP35: 132500 | AQ35: Reservada - Con Contrato | AR35: 45551 | AS35: =Tabla4[[#This Row],[VALOR TOTAL]] -> 172500 | AT35: 30474583 | AU35: BANCO | AV35: BANCO | AW35: =ABONOS!O36 -> 0 | AX35: {=_xlfn.IFS(Tabla4[[#This Row],[MONTO5]]=0,"",Tabla4[[#This Row],[SALDO PENDIENTE3]]=0,"PAZ Y SALVO",Tabla4[[#This Row],[SALDO PENDIENTE3]]>0,"PENDIENTE")} -> PAZ Y SALVO | AY35: INSCRITA Y DESEMBOLSADA | AZ35: 45572 | BA35: SI | BB35: 45580 | BC35: =Tabla4[[#This Row],[FECHA RECIBIDO MINUTA LIBERACION]]-Tabla4[[#This Row],[SOLICITUD DE MINUTA LIBERACIÓN]] -> 8 | BD35: SI | BE35: 45576 | BF35: SI | BG35: 45580 | BH35: N/A | BI35: N/A | BJ35: N/A | BK35: 45593 | BL35: 45596 | BM35: 45598 | BN35: 45603 | BO35: 45611 | BP35: =Tabla4[[#This Row],[RECEPCIÓN INTERINO]]-Tabla4[[#This Row],[ENVIO A INTERINO]] -> 8 | BQ35: 45602 | BR35: 45602 | BS35: 45602 | BT35: 45602 | BU35: 45604 | BV35: SI | BW35: 45611 | BX35: 45614 | BY35: 45615 | BZ35: 45626 | CA35: 45626 | CB35: 45638 | CC35: 45626
A36: L-201 | B36: -300 | C36: SIMON LEWIS CHAPELLE | D36: TRASPASADO | E36: INSCRITO Y DESEMBOLSADO | F36: 45323 | G36: 679659135 / 651130541 | H36: ESTADOUNIDENSE | I36: EXTRANJERO NO RESIDENTE | J36: SCOTT NETTIE Y AILEEN VEGA | K36: 21988 | L36: INDEPENDIENTE | M36: ADMINISTRADOR DE EMPRESAS | N36: CONTADO | O36: SI | P36: SI | Q36: SI | R36: 16000 | S36: A | T36: 65.93 | U36: 0 | V36: =U36+T36 -> 65.93 | X36: =AB36*T36 -> 154935.5 | AA36: 202000 | AB36: 2350 | AC36: =((AD36*1)/AA36) -> 1 | AD36: =SUMIFS(Tabla35[Abonos],Tabla35[Lote],Tabla4[[#This Row],[UNIDAD APTO]],Tabla35[Cliente],Tabla4[[#This Row],[CLIENTE]],Tabla35[Concepto],"ABONO")+SUMIFS(Tabla35[Abonos],Tabla35[Lote],Tabla4[[#This Row],[UNIDAD APTO]],Tabla35[Cliente],Tabla4[[#This Row],[CLIENTE]],Tabla35[Concepto],"MULTIBANK") -> 202000 | AE36: =Tabla4[[#This Row],[VALOR TOTAL]]-Tabla4[[#This Row],[MONTO A MULTIBANK]] -> 60000 | AF36: =Tabla4[[#This Row],[MONTO CPP]] -> 142000 | AG36: =ABONOS!E37 -> 0 | AH36: {=_xlfn.IFS(Tabla4[[#This Row],[RESERVADAS, VENDIDAS]]="DISPONIBLE","",Tabla4[[#This Row],[SALDO PENDIENTE]]=0,"PAZ Y SALVO",Tabla4[[#This Row],[SALDO PENDIENTE]]=Tabla4[[#This Row],[MONTO CPP]],"COBRO CPP",Tabla4[[#This Row],[SALDO PENDIENTE]]>0,"PENDIENTE")} -> PAZ Y SALVO | AI36: TOWERBANK | AL36: CON CPP | AM36: 45544 | AN36: 45721 | AO36: FONDO PROPIOS PIGNORADOS | AP36: 142000 | AQ36: Reservada - Con Contrato | AR36: 45465 | AS36: =AA36 -> 202000 | AT36: 30474606 | AU36: GISA | AV36: 2070 | AW36: =ABONOS!O37 -> 0 | AX36: {=_xlfn.IFS(Tabla4[[#This Row],[MONTO5]]=0,"",Tabla4[[#This Row],[SALDO PENDIENTE3]]=0,"PAZ Y SALVO",Tabla4[[#This Row],[SALDO PENDIENTE3]]>0,"PENDIENTE")} -> PAZ Y SALVO | AY36: INSCRITA Y DESEMBOLSADA | AZ36: 45555 | BA36: SI | BB36: 45565 | BC36: =Tabla4[[#This Row],[FECHA RECIBIDO MINUTA LIBERACION]]-Tabla4[[#This Row],[SOLICITUD DE MINUTA LIBERACIÓN]] -> 10 | BD36: SI | BE36: 45567 | BF36: N/A | BG36: 45569 | BH36: N/A | BI36: N/A | BJ36: N/A | BK36: 45569 | BL36: 45598 | BM36: 45598 | BN36: 45603 | BO36: 45611 | BP36: =Tabla4[[#This Row],[RECEPCIÓN INTERINO]]-Tabla4[[#This Row],[ENVIO A INTERINO]] -> 8 | BQ36: 45611 | BR36: 45602 | BS36: 45611 | BT36: 45611 | BU36: N/A | BV36: SI | BW36: 45569 | BX36: 45614 | BY36: 45614 | BZ36: 45625 | CA36: 45625 | CB36: 45631 | CC36: 45600
A37: L-202 | B37: -300 | C37: RUTH WINSLOW | D37: TRASPASADO | E37: INSCRITO Y DESEMBOLSADO | F37: 44986 | G37: E-8-129577 | H37: ESTADOUNIDENSE | I37: EXTRANJERO NO RESIDENTE | J37: GESPROBAN | K37: 14256 | L37: INDEPENDIENTE / JUBILADO | M37: ADMINISTRADOR DE EMPRESAS | N37: CONTADO | O37: N/A | P37: N/A | Q37: N/A | R37: 0 | S37: B | T37: 59.94 | U37: 0 | V37: =U37+T37 -> 59.94 | X37: =AB37*T37 -> 137862 | AA37: =X37+W37+Y37+Z37 -> 137862 | AB37: 2300 | AC37: =((AD37*1)/AA37) -> 0.99981866 | AD37: =SUMIFS(Tabla35[Abonos],Tabla35[Lote],Tabla4[[#This Row],[UNIDAD APTO]],Tabla35[Cliente],Tabla4[[#This Row],[CLIENTE]],Tabla35[Concepto],"ABONO")+SUMIFS(Tabla35[Abonos],Tabla35[Lote],Tabla4[[#This Row],[UNIDAD APTO]],Tabla35[Cliente],Tabla4[[#This Row],[CLIENTE]],Tabla35[Concepto],"MULTIBANK") -> 137837 | AE37: =Tabla4[[#This Row],[VALOR TOTAL]]-Tabla4[[#This Row],[MONTO A MULTIBANK]] -> 41358.6 | AF37: =AA37*70% -> 96503.4 | AG37: =ABONOS!E38 -> 25 | AH37: {=_xlfn.IFS(Tabla4[[#This Row],[RESERVADAS, VENDIDAS]]="DISPONIBLE","",Tabla4[[#This Row],[SALDO PENDIENTE]]=0,"PAZ Y SALVO",Tabla4[[#This Row],[SALDO PENDIENTE]]=Tabla4[[#This Row],[MONTO CPP]],"COBRO CPP",Tabla4[[#This Row],[SALDO PENDIENTE]]>0,"PENDIENTE")} -> PENDIENTE | AI37: N/A | AJ37: N/A | AK37: N/A | AL37: N/A | AM37: N/A | AN37: N/A | AO37: N/A | AP37: N/A | AQ37: Reservada - Con Contrato | AR37: 45093 | AS37: =AA37 -> 137862 | AT37: 30474605 | AU37: GISA | AV37: 1725 | AW37: =ABONOS!O38 -> 20 | AX37: {=_xlfn.IFS(Tabla4[[#This Row],[MONTO5]]=0,"",Tabla4[[#This Row],[SALDO PENDIENTE3]]=0,"PAZ Y SALVO",Tabla4[[#This Row],[SALDO PENDIENTE3]]>0,"PENDIENTE")} -> PENDIENTE | AY37: INSCRITA Y DESEMBOLSADA | AZ37: 45470 | BA37: SI | BB37: 45495 | BC37: =Tabla4[[#This Row],[FECHA RECIBIDO MINUTA LIBERACION]]-Tabla4[[#This Row],[SOLICITUD DE MINUTA LIBERACIÓN]] -> 25 | BD37: SI | BE37: 45458 | BF37: N/A | BG37: N/A | BH37: N/A | BI37: N/A | BJ37: N/A | BK37: 45464 | BL37: 45469 | BM37: 45471 | BN37: 45516 | BO37: 45518 | BP37: =Tabla4[[#This Row],[RECEPCIÓN INTERINO]]-Tabla4[[#This Row],[ENVIO A INTERINO]] -> 2 | BQ37: 45540 | BR37: 45537 | BS37: 45539 | BT37: 45542 | BU37: N/A | BV37: SI | BW37: 45464 | BX37: 45544 | BY37: 45559 | BZ37: 45560 | CA37: N/A | CB37: N/A | CC37: 45575
A38: L-203 | B38: -300 | C38: JOSE ALEJANDRO DE LEON | D38: TRASPASADO | E38: INSCRITO Y DESEMBOLSADO | F38: 45971 | G38: 8-422-830 | H38: PANAMEÑA | I38: NACIONAL | K38: 26653 | L38: INDEPENDIENTE | M38: ABOGADO | N38: CONTADO | O38: NO | P38: NO | S38: C | T38: 73.09 | U38: 0 | V38: =U38+T38 -> 73.09 | X38: =AB38*T38 -> 171761.5 | AA38: 179900 | AB38: 2350 | AC38: =((AD38*1)/AA38) -> 1 | AD38: =SUMIFS(Tabla35[Abonos],Tabla35[Lote],Tabla4[[#This Row],[UNIDAD APTO]],Tabla35[Cliente],Tabla4[[#This Row],[CLIENTE]],Tabla35[Concepto],"ABONO")+SUMIFS(Tabla35[Abonos],Tabla35[Lote],Tabla4[[#This Row],[UNIDAD APTO]],Tabla35[Cliente],Tabla4[[#This Row],[CLIENTE]],Tabla35[Concepto],"MULTIBANK") -> 179900 | AE38: =Tabla4[[#This Row],[VALOR TOTAL]] -> 179900 | AG38: =ABONOS!E39 -> 0 | AH38: {=_xlfn.IFS(Tabla4[[#This Row],[RESERVADAS, VENDIDAS]]="DISPONIBLE","",Tabla4[[#This Row],[SALDO PENDIENTE]]=0,"PAZ Y SALVO",Tabla4[[#This Row],[SALDO PENDIENTE]]=Tabla4[[#This Row],[MONTO CPP]],"COBRO CPP",Tabla4[[#This Row],[SALDO PENDIENTE]]>0,"PENDIENTE")} -> PAZ Y SALVO | AI38: N/A | AJ38: N/A | AK38: N/A | AL38: N/A | AM38: N/A | AN38: N/A | AO38: FONDO PROPIOS PIGNORADOS | AP38: N/A | AQ38: Reservada - Con Contrato | AR38: 45985 | AS38: 179900 | AT38: 30474604 | AU38: GISA | AV38: 1750 | AW38: =ABONOS!O39 -> 0 | AX38: {=_xlfn.IFS(Tabla4[[#This Row],[MONTO5]]=0,"",Tabla4[[#This Row],[SALDO PENDIENTE3]]=0,"PAZ Y SALVO",Tabla4[[#This Row],[SALDO PENDIENTE3]]>0,"PENDIENTE")} -> PAZ Y SALVO | AY38: INSCRITA Y DESEMBOLSADA | AZ38: 46002 | BA38: SI | BB38: 46010 | BC38: =Tabla4[[#This Row],[FECHA RECIBIDO MINUTA LIBERACION]]-Tabla4[[#This Row],[SOLICITUD DE MINUTA LIBERACIÓN]] -> 8 | BD38: SI | BE38: 46015 | BF38: N/A | BG38: N/A | BH38: N/A | BI38: N/A | BJ38: N/A | BK38: 46015 | BL38: 46026 | BM38: 46025 | BN38: 46025 | BO38: 46027 | BP38: =Tabla4[[#This Row],[RECEPCIÓN INTERINO]]-Tabla4[[#This Row],[ENVIO A INTERINO]] -> 2 | BQ38: 46051 | BR38: 46043 | BS38: 46052 | BT38: 46052 | BU38: N/A | BV38: SI | BW38: 46055 | BX38: 46055 | BY38: 46057 | BZ38: 46066 | CA38: N/A | CB38: N/A | CC38: 45996
A39: L-204 | B39: -300 | C39: MELVA BELTRAN | D39: TRASPASADO | E39: INSCRITO Y DESEMBOLSADO | F39: 46137 | G39: 2-702-48 | H39: PANAMEÑA | I39: NACIONAL | J39: GESPROBAN | M39: GERENTE DE RECURSOS HUMANOS | O39: NO | P39: NO | Q39: NO | R39: N/A | S39: C | T39: 73.09 | U39: 0 | V39: =U39+T39 -> 73.09 | X39: =AB39*T39 -> 171761.5 | AA39: 184000 | AB39: 2350 | AC39: =((AD39*1)/AA39) -> 0.070652174 | AD39: =SUMIFS(Tabla35[Abonos],Tabla35[Lote],Tabla4[[#This Row],[UNIDAD APTO]],Tabla35[Cliente],Tabla4[[#This Row],[CLIENTE]],Tabla35[Concepto],"ABONO")+SUMIFS(Tabla35[Abonos],Tabla35[Lote],Tabla4[[#This Row],[UNIDAD APTO]],Tabla35[Cliente],Tabla4[[#This Row],[CLIENTE]],Tabla35[Concepto],"MULTIBANK") -> 13000 | AE39: =Tabla4[[#This Row],[VALOR TOTAL]]-AF39 -> 184000 | AF39: 0 | AG39: =ABONOS!E40 -> 171000 | AH39: {=_xlfn.IFS(Tabla4[[#This Row],[RESERVADAS, VENDIDAS]]="DISPONIBLE","",Tabla4[[#This Row],[SALDO PENDIENTE]]=0,"PAZ Y SALVO",Tabla4[[#This Row],[SALDO PENDIENTE]]=Tabla4[[#This Row],[MONTO CPP]],"COBRO CPP",Tabla4[[#This Row],[SALDO PENDIENTE]]>0,"PENDIENTE")} -> PENDIENTE | AI39: BANISTMO | AL39: CON CPP | AM39: 46171 | AN39: N/A | AO39: CON CPP | AP39: 165000 | AQ39: Reservada - Con Contrato | AR39: 46175 | AS39: 184000 | AT39: 30474603 | AU39: BANCO | AV39: BANCO | AW39: 0 | AX39: {=_xlfn.IFS(Tabla4[[#This Row],[MONTO5]]=0,"",Tabla4[[#This Row],[SALDO PENDIENTE3]]=0,"PAZ Y SALVO",Tabla4[[#This Row],[SALDO PENDIENTE3]]>0,"PENDIENTE")} -> PAZ Y SALVO | AY39: INSCRITA Y DESEMBOLSADA | AZ39: 46175 | BA39: SI | BB39: 46184 | BC39: =Tabla4[[#This Row],[FECHA RECIBIDO MINUTA LIBERACION]]-Tabla4[[#This Row],[SOLICITUD DE MINUTA LIBERACIÓN]] -> 9 | BD39: SI | BE39: 46189 | BF39: SI | BG39: 46189 | BH39: 46189 | BI39: 46190 | BJ39: BANCO | BK39: 46202 | BL39: 46202 | BM39: 46205 | BN39: 46204 | BO39: 46204 | BP39: =Tabla4[[#This Row],[RECEPCIÓN INTERINO]]-Tabla4[[#This Row],[ENVIO A INTERINO]] -> 0 | BQ39: 46204 | BR39: 46204 | BS39: 46204 | BT39: 46204 | BU39: 46205 | BV39: SI | BW39: 46212 | BX39: 46212 | BY39: 46219 | BZ39: 46224 | CA39: 46224 | CB39: 46230 | CC39: 46225
A40: L-205 | B40: -300 | C40: ISABELLE BELANGER/DANIEL CARON | D40: TRASPASADO | E40: INSCRITO Y DESEMBOLSADO | F40: 46049 | G40: HL394139 | H40: CANADIENSE | I40: EXTRANJERO NO RESIDENTE | J40: GESPROBAN | K40: 26678 | L40: INDEPENDIENTE | M40: CONSULTORA COMERCIAL | N40: FINANCIAMIENTO | O40: SI | Q40: SI | R40: 14000 | S40: C | T40: 73.09 | U40: 0 | V40: =U40+T40 -> 73.09 | X40: =AB40*T40 -> 171761.5 | AA40: 194000 | AB40: 2350 | AC40: =((AD40*1)/AA40) -> 0.37148402 | AD40: =SUMIFS(Tabla35[Abonos],Tabla35[Lote],Tabla4[[#This Row],[UNIDAD APTO]],Tabla35[Cliente],Tabla4[[#This Row],[CLIENTE]],Tabla35[Concepto],"ABONO")+SUMIFS(Tabla35[Abonos],Tabla35[Lote],Tabla4[[#This Row],[UNIDAD APTO]],Tabla35[Cliente],Tabla4[[#This Row],[CLIENTE]],Tabla35[Concepto],"MULTIBANK") -> 72067.9 | AE40: =Tabla4[[#This Row],[VALOR TOTAL]] -> 194000 | AF40: 0 | AG40: =ABONOS!E41 -> 121932.1 | AH40: {=_xlfn.IFS(Tabla4[[#This Row],[RESERVADAS, VENDIDAS]]="DISPONIBLE","",Tabla4[[#This Row],[SALDO PENDIENTE]]=0,"PAZ Y SALVO",Tabla4[[#This Row],[SALDO PENDIENTE]]=Tabla4[[#This Row],[MONTO CPP]],"COBRO CPP",Tabla4[[#This Row],[SALDO PENDIENTE]]>0,"PENDIENTE")} -> PENDIENTE | AI40: LAFISE | AL40: CON CPP | AM40: 46087 | AN40: 46447 | AO40: CON CPP | AP40: 121900 | AQ40: Reservada - Con Contrato | AR40: 46064 | AS40: 194000 | AT40: 30474602 | AU40: GISA | AV40: =2883+73.55 -> 2956.55 | AW40: =ABONOS!O41 -> 2956.55 | AX40: {=_xlfn.IFS(Tabla4[[#This Row],[MONTO5]]=0,"",Tabla4[[#This Row],[SALDO PENDIENTE3]]=0,"PAZ Y SALVO",Tabla4[[#This Row],[SALDO PENDIENTE3]]>0,"PENDIENTE")} -> PENDIENTE | AY40: INSCRITA Y DESEMBOLSADA | AZ40: 46093 | BA40: SI | BB40: 46101 | BC40: =Tabla4[[#This Row],[FECHA RECIBIDO MINUTA LIBERACION]]-Tabla4[[#This Row],[SOLICITUD DE MINUTA LIBERACIÓN]] -> 8 | BD40: SI | BE40: 46130 | BF40: SI | BG40: 46093 | BH40: 46093 | BI40: BANCO | BJ40: AIR AVALUOS | BK40: 46130 | BL40: 46142 | BM40: 46131 | BN40: 46159 | BO40: 46160 | BP40: =Tabla4[[#This Row],[RECEPCIÓN INTERINO]]-Tabla4[[#This Row],[ENVIO A INTERINO]] -> 1 | BQ40: 46181 | BR40: 46240 | BS40: 46240 | BT40: 46171 | BU40: 46157 | BV40: SI | BW40: 46181 | BX40: 46182 | BY40: 46183 | BZ40: 46199 | CA40: 46199 | CC40: 46198
A41: L-206 | B41: -300 | C41: DARKO VASIC Y DANIEL KRAUSKOPF | D41: TRASPASADO | E41: INSCRITO Y DESEMBOLSADO | F41: 45993 | G41: P961231QS Y P350367BI | H41: CANADIENSE | I41: EXTRANJERO NO RESIDENTE | J41: ? | L41: INDEPENDIENTE | M41: PROJECT MANAGER / IT CYBER SECURITY | N41: CONTADO | O41: SI | P41: NO | Q41: SI | S41: C | T41: 73.98 | U41: 0 | V41: =U41+T41 -> 73.98 | X41: =AB41*T41 -> 173853 | AA41: 204000 | AB41: 2350 | AC41: =((AD41*1)/AA41) -> 0.34995098 | AD41: =SUMIFS(Tabla35[Abonos],Tabla35[Lote],Tabla4[[#This Row],[UNIDAD APTO]],Tabla35[Cliente],Tabla4[[#This Row],[CLIENTE]],Tabla35[Concepto],"ABONO")+SUMIFS(Tabla35[Abonos],Tabla35[Lote],Tabla4[[#This Row],[UNIDAD APTO]],Tabla35[Cliente],Tabla4[[#This Row],[CLIENTE]],Tabla35[Concepto],"MULTIBANK") -> 71390 | AE41: =Tabla4[[#This Row],[VALOR TOTAL]] -> 204000 | AF41: 0 | AG41: =ABONOS!E42 -> 132610 | AH41: {=_xlfn.IFS(Tabla4[[#This Row],[RESERVADAS, VENDIDAS]]="DISPONIBLE","",Tabla4[[#This Row],[SALDO PENDIENTE]]=0,"PAZ Y SALVO",Tabla4[[#This Row],[SALDO PENDIENTE]]=Tabla4[[#This Row],[MONTO CPP]],"COBRO CPP",Tabla4[[#This Row],[SALDO PENDIENTE]]>0,"PENDIENTE")} -> PENDIENTE | AI41: LAFISE | AL41: CON CPP | AM41: 46128 | AN41: 46488 | AO41: CON CPP | AP41: 132600 | AQ41: Reservada - Con Contrato | AR41: 46017 | AS41: 201000 | AT41: 30474601 | AU41: GISA | AV41: 2966 | AW41: =ABONOS!O42 -> 42.45 | AX41: {=_xlfn.IFS(Tabla4[[#This Row],[MONTO5]]=0,"",Tabla4[[#This Row],[SALDO PENDIENTE3]]=0,"PAZ Y SALVO",Tabla4[[#This Row],[SALDO PENDIENTE3]]>0,"PENDIENTE")} -> PENDIENTE | AY41: INSCRITA Y DESEMBOLSADA | AZ41: 46136 | BA41: SI | BB41: 29-04-2026 | BC41: =Tabla4[[#This Row],[FECHA RECIBIDO MINUTA LIBERACION]]-Tabla4[[#This Row],[SOLICITUD DE MINUTA LIBERACIÓN]] -> #VALUE! | BD41: SI | BE41: 46135 | BF41: SI | BG41: 46135 | BH41: 46136 | BI41: 46155 | BJ41: AVANCE | BK41: 46182 | BL41: 46189 | BM41: 46183 | BN41: 46195 | BO41: 46196 | BP41: =Tabla4[[#This Row],[RECEPCIÓN INTERINO]]-Tabla4[[#This Row],[ENVIO A INTERINO]] -> 1 | BQ41: 46219 | BR41: 46196 | BS41: 46219 | BT41: 46219 | BU41: 46205 | BV41: SI | BW41: 46220 | BX41: 46220 | BY41: 46220 | BZ41: 46237 | CA41: 46237
A42: L-207 | B42: -300 | D42: DISPONIBLE | E42: PENDIENTE | S42: C | T42: 73.98 | U42: 0 | V42: =U42+T42 -> 73.98 | X42: =AB42*T42 -> 173853 | AA42: 201000 | AB42: 2350 | AC42: =((AD42*1)/AA42) -> 0 | AD42: =SUMIFS(Tabla35[Abonos],Tabla35[Lote],Tabla4[[#This Row],[UNIDAD APTO]],Tabla35[Cliente],Tabla4[[#This Row],[CLIENTE]],Tabla35[Concepto],"ABONO")+SUMIFS(Tabla35[Abonos],Tabla35[Lote],Tabla4[[#This Row],[UNIDAD APTO]],Tabla35[Cliente],Tabla4[[#This Row],[CLIENTE]],Tabla35[Concepto],"MULTIBANK") -> 0 | AE42: =Tabla4[[#This Row],[VALOR TOTAL]] -> 201000 | AG42: =ABONOS!E43 -> 201000 | AH42: {=_xlfn.IFS(Tabla4[[#This Row],[RESERVADAS, VENDIDAS]]="DISPONIBLE","",Tabla4[[#This Row],[SALDO PENDIENTE]]=0,"PAZ Y SALVO",Tabla4[[#This Row],[SALDO PENDIENTE]]=Tabla4[[#This Row],[MONTO CPP]],"COBRO CPP",Tabla4[[#This Row],[SALDO PENDIENTE]]>0,"PENDIENTE")} | AQ42: Pendiente contrato | AT42: 30474600 | AW42: =ABONOS!O43 -> 0 | AX42: {=_xlfn.IFS(Tabla4[[#This Row],[MONTO5]]=0,"",Tabla4[[#This Row],[SALDO PENDIENTE3]]=0,"PAZ Y SALVO",Tabla4[[#This Row],[SALDO PENDIENTE3]]>0,"PENDIENTE")} | BC42: =Tabla4[[#This Row],[FECHA RECIBIDO MINUTA LIBERACION]]-Tabla4[[#This Row],[SOLICITUD DE MINUTA LIBERACIÓN]] -> 0 | BP42: =Tabla4[[#This Row],[RECEPCIÓN INTERINO]]-Tabla4[[#This Row],[ENVIO A INTERINO]] -> 0
A43: L-208 | B43: -300 | C43: SANDRA KAVANAUGH/SHARON BOMFALK | D43: TRASPASADO | E43: INSCRITO Y DESEMBOLSADO | F43: 45979 | G43: 532922899 | H43: ESTADOUNIDENSE | I43: EXTRANJERO NO RESIDENTE | J43: GESPROBAN | K43: 19755 | L43: INDEPENDIENTE | M43: CURADORA | N43: CONTADO | O43: SI | P43: NO | Q43: SI | S43: C | T43: 73.09 | U43: 0 | V43: =U43+T43 -> 73.09 | X43: =AB43*T43 -> 171761.5 | AA43: 201000 | AB43: 2350 | AC43: =((AD43*1)/AA43) -> 1 | AD43: =SUMIFS(Tabla35[Abonos],Tabla35[Lote],Tabla4[[#This Row],[UNIDAD APTO]],Tabla35[Cliente],Tabla4[[#This Row],[CLIENTE]],Tabla35[Concepto],"ABONO")+SUMIFS(Tabla35[Abonos],Tabla35[Lote],Tabla4[[#This Row],[UNIDAD APTO]],Tabla35[Cliente],Tabla4[[#This Row],[CLIENTE]],Tabla35[Concepto],"MULTIBANK") -> 201000 | AE43: =Tabla4[[#This Row],[VALOR TOTAL]]-AF43 -> 201000 | AF43: 0 | AG43: =ABONOS!E44 -> 0 | AH43: {=_xlfn.IFS(Tabla4[[#This Row],[RESERVADAS, VENDIDAS]]="DISPONIBLE","",Tabla4[[#This Row],[SALDO PENDIENTE]]=0,"PAZ Y SALVO",Tabla4[[#This Row],[SALDO PENDIENTE]]=Tabla4[[#This Row],[MONTO CPP]],"COBRO CPP",Tabla4[[#This Row],[SALDO PENDIENTE]]>0,"PENDIENTE")} -> PAZ Y SALVO | AI43: N/A | AJ43: N/A | AK43: N/A | AL43: N/A | AM43: N/A | AN43: N/A | AO43: FONDO PROPIOS PIGNORADOS | AP43: N/A | AQ43: Reservada - Con Contrato | AR43: 46017 | AS43: 201000 | AT43: 30474599 | AU43: GISA | AV43: 1830 | AW43: =ABONOS!O44 -> 0 | AX43: {=_xlfn.IFS(Tabla4[[#This Row],[MONTO5]]=0,"",Tabla4[[#This Row],[SALDO PENDIENTE3]]=0,"PAZ Y SALVO",Tabla4[[#This Row],[SALDO PENDIENTE3]]>0,"PENDIENTE")} -> PAZ Y SALVO | AY43: Escritura inscrita | AZ43: 46063 | BA43: SI | BB43: 46071 | BC43: =Tabla4[[#This Row],[FECHA RECIBIDO MINUTA LIBERACION]]-Tabla4[[#This Row],[SOLICITUD DE MINUTA LIBERACIÓN]] -> 8 | BD43: SI | BE43: 46085 | BF43: N/A | BG43: N/A | BH43: N/A | BI43: N/A | BJ43: N/A | BK43: 46088 | BL43: 46101 | BM43: 46121 | BN43: 46121 | BO43: 46122 | BP43: =Tabla4[[#This Row],[RECEPCIÓN INTERINO]]-Tabla4[[#This Row],[ENVIO A INTERINO]] -> 1 | BQ43: 46140 | BR43: 46136 | BS43: 46141 | BT43: 46141 | BU43: N/A | BV43: SI | BW43: 46140 | BX43: 46141 | BY43: 46142 | BZ43: 46161 | CA43: N/A | CB43: N/A | CC43: 46131
A44: L-209 | B44: -300 | C44: CONSTRUA INTERNATIONAL | D44: TRASPASADO | E44: INSCRITO Y DESEMBOLSADO | F44: 45947 | G44: 111800167 | H44: COSTARRICENSE | I44: EXTRANJERO RESIDENTE | J44: GESPROBAN | K44: 30567 | L44: INDEPENDIENTE | M44: INGENIERO | N44: CONTADO | S44: C | T44: 73.09 | U44: 0 | V44: =U44+T44 -> 73.09 | X44: =AB44*T44 -> 171761.5 | AA44: 130000 | AB44: 2350 | AC44: =((AD44*1)/AA44) -> 1 | AD44: =SUMIFS(Tabla35[Abonos],Tabla35[Lote],Tabla4[[#This Row],[UNIDAD APTO]],Tabla35[Cliente],Tabla4[[#This Row],[CLIENTE]],Tabla35[Concepto],"ABONO")+SUMIFS(Tabla35[Abonos],Tabla35[Lote],Tabla4[[#This Row],[UNIDAD APTO]],Tabla35[Cliente],Tabla4[[#This Row],[CLIENTE]],Tabla35[Concepto],"MULTIBANK") -> 130000 | AE44: =Tabla4[[#This Row],[VALOR TOTAL]]-AF44 -> 130000 | AF44: 0 | AG44: =ABONOS!E45 -> 0 | AH44: {=_xlfn.IFS(Tabla4[[#This Row],[RESERVADAS, VENDIDAS]]="DISPONIBLE","",Tabla4[[#This Row],[SALDO PENDIENTE]]=0,"PAZ Y SALVO",Tabla4[[#This Row],[SALDO PENDIENTE]]=Tabla4[[#This Row],[MONTO CPP]],"COBRO CPP",Tabla4[[#This Row],[SALDO PENDIENTE]]>0,"PENDIENTE")} -> PAZ Y SALVO | AI44: N/A | AJ44: N/A | AK44: N/A | AL44: N/A | AM44: N/A | AN44: N/A | AO44: N/A | AP44: N/A | AQ44: Reservada - Con Contrato | AT44: 30474598 | AU44: GISA | AV44: 1726 | AW44: =ABONOS!O45 -> 0 | AX44: {=_xlfn.IFS(Tabla4[[#This Row],[MONTO5]]=0,"",Tabla4[[#This Row],[SALDO PENDIENTE3]]=0,"PAZ Y SALVO",Tabla4[[#This Row],[SALDO PENDIENTE3]]>0,"PENDIENTE")} -> PAZ Y SALVO | AY44: INSCRITA Y DESEMBOLSADA | AZ44: 45954 | BA44: SI | BB44: 45961 | BC44: =Tabla4[[#This Row],[FECHA RECIBIDO MINUTA LIBERACION]]-Tabla4[[#This Row],[SOLICITUD DE MINUTA LIBERACIÓN]] -> 7 | BD44: SI | BE44: 45973 | BF44: N/A | BG44: N/A | BH44: N/A | BI44: N/A | BJ44: N/A | BK44: 45972 | BL44: 45978 | BM44: 45978 | BN44: 45979 | BO44: 45992 | BP44: =Tabla4[[#This Row],[RECEPCIÓN INTERINO]]-Tabla4[[#This Row],[ENVIO A INTERINO]] -> 13 | BQ44: 45996 | BR44: 45968 | BS44: 45996 | BT44: 45996 | BU44: N/A | BV44: SI | BW44: 45996 | BX44: 45996 | BY44: 45996 | BZ44: 46007 | CA44: N/A | CB44: N/A | CC44: 45946
A45: L-210 | B45: -300 | C45: NADIA RODRIGUEZ | D45: TRASPASADO | E45: INSCRITO Y DESEMBOLSADO | F45: 46137 | G45: 9-709-177 | H45: PANAMEÑA | I45: NACIONAL | J45: GESPROBAN | M45: FARMACÉTUTICA | N45: CPP | O45: NO | P45: NO | Q45: NO | R45: N/A | S45: C | T45: 73.09 | U45: 0 | V45: =U45+T45 -> 73.09 | X45: =AB45*T45 -> 171761.5 | AA45: 180000 | AB45: 2350 | AC45: =((AD45*1)/AA45) -> 0.44444444 | AD45: =SUMIFS(Tabla35[Abonos],Tabla35[Lote],Tabla4[[#This Row],[UNIDAD APTO]],Tabla35[Cliente],Tabla4[[#This Row],[CLIENTE]],Tabla35[Concepto],"ABONO")+SUMIFS(Tabla35[Abonos],Tabla35[Lote],Tabla4[[#This Row],[UNIDAD APTO]],Tabla35[Cliente],Tabla4[[#This Row],[CLIENTE]],Tabla35[Concepto],"MULTIBANK") -> 80000 | AE45: =Tabla4[[#This Row],[VALOR TOTAL]]-AF45 -> 180000 | AF45: 0 | AG45: =ABONOS!E46 -> 100000 | AH45: PAZ Y SALVO | AI45: CAJA DE AHORROS | AM45: 46158 | AN45: 47254 | AO45: CON CPP | AP45: 100000 | AQ45: Reservada - Con Contrato | AR45: 46175 | AS45: 180000 | AT45: 30474597 | AU45: BANCO | AV45: BANCO | AW45: 0 | AX45: PAZ Y SALVO | AY45: INSCRITA Y DESEMBOLSADA | AZ45: 46176 | BA45: SI | BB45: 46184 | BC45: =Tabla4[[#This Row],[FECHA RECIBIDO MINUTA LIBERACION]]-Tabla4[[#This Row],[SOLICITUD DE MINUTA LIBERACIÓN]] -> 8 | BD45: SI | BE45: 46189 | BF45: SI | BG45: 46189 | BH45: 46189 | BI45: 46199 | BJ45: BANCO | BK45: 46234 | BL45: 46238 | BM45: 46239 | BN45: 46239 | BO45: 46240 | BP45: =Tabla4[[#This Row],[RECEPCIÓN INTERINO]]-Tabla4[[#This Row],[ENVIO A INTERINO]] -> 1 | BQ45: 46238 | BR45: 46238 | BS45: 46238 | BT45: 46238 | BU45: 46241 | BZ45: 46254
A46: L-211 | B46: -300 | C46: MICHAEL RIVAS | D46: TRASPASADO | E46: INSCRITO Y DESEMBOLSADO | F46: 45292 | G46: 2-731-1908 | H46: PANAMEÑA | I46: NACIONAL | J46: GESPROBAN | K46: 34094 | L46: ASALARIADO | M46: PROFESIONAL DE LA SALUD | N46: FINANCIAMIENTO | O46: SI | P46: NO | Q46: NO | R46: 12000 | S46: B | T46: 59.94 | U46: 0 | V46: =U46+T46 -> 59.94 | X46: =136483.38 -> 136483.38 | AA46: 143389.44 | AB46: 2350 | AC46: =((AD46*1)/AA46) -> 1 | AD46: =SUMIFS(Tabla35[Abonos],Tabla35[Lote],Tabla4[[#This Row],[UNIDAD APTO]],Tabla35[Cliente],Tabla4[[#This Row],[CLIENTE]],Tabla35[Concepto],"ABONO")+SUMIFS(Tabla35[Abonos],Tabla35[Lote],Tabla4[[#This Row],[UNIDAD APTO]],Tabla35[Cliente],Tabla4[[#This Row],[CLIENTE]],Tabla35[Concepto],"MULTIBANK") -> 143389.44 | AE46: =Tabla4[[#This Row],[VALOR TOTAL]]-Tabla4[[#This Row],[MONTO A MULTIBANK]] -> 17000 | AF46: =Tabla4[[#This Row],[MONTO CPP]] -> 126389.44 | AG46: =ABONOS!E47 -> 0 | AH46: {=_xlfn.IFS(Tabla4[[#This Row],[RESERVADAS, VENDIDAS]]="DISPONIBLE","",Tabla4[[#This Row],[SALDO PENDIENTE]]=0,"PAZ Y SALVO",Tabla4[[#This Row],[SALDO PENDIENTE]]=Tabla4[[#This Row],[MONTO CPP]],"COBRO CPP",Tabla4[[#This Row],[SALDO PENDIENTE]]>0,"PENDIENTE")} -> PAZ Y SALVO | AI46: SCOTIABANK | AJ46: GENIFER MUÑOZ | AL46: CON CPP | AM46: 45610 | AN46: 45975 | AO46: CON CPP | AP46: 126389.44 | AQ46: Reservada - Con Contrato | AR46: 45317 | AS46: =AA46 -> 143389.44 | AT46: 30474596 | AU46: SCOTIABANK | AV46: BANCO | AW46: =ABONOS!O47 -> 0 | AX46: {=_xlfn.IFS(Tabla4[[#This Row],[MONTO5]]=0,"",Tabla4[[#This Row],[SALDO PENDIENTE3]]=0,"PAZ Y SALVO",Tabla4[[#This Row],[SALDO PENDIENTE3]]>0,"PENDIENTE")} -> PAZ Y SALVO | AY46: INSCRITA Y DESEMBOLSADA | AZ46: 45623 | BA46: SI | BB46: 45630 | BC46: =Tabla4[[#This Row],[FECHA RECIBIDO MINUTA LIBERACION]]-Tabla4[[#This Row],[SOLICITUD DE MINUTA LIBERACIÓN]] -> 7 | BD46: SI | BE46: 45631 | BF46: SI | BG46: 45631 | BH46: BANCO | BI46: BANCO | BJ46: BANCO | BK46: BANCO | BL46: 45653 | BM46: 45654 | BN46: 45657 | BO46: 45663 | BP46: =Tabla4[[#This Row],[RECEPCIÓN INTERINO]]-Tabla4[[#This Row],[ENVIO A INTERINO]] -> 6 | BQ46: 45663 | BR46: 45638 | BS46: 45663 | BT46: 45663 | BU46: 45664 | BV46: SI | BW46: BANCO | BX46: 45667 | BY46: 45671 | BZ46: 45674 | CA46: 45674 | CB46: 45679 | CC46: 45707
A47: L-212 | B47: -300 | C47: ALESSANDRO GANCI CERRUD | D47: TRASPASADO | E47: INSCRITO Y DESEMBOLSADO | F47: 45566 | G47: PE-92339 | H47: PANAMEÑA | I47: NACIONAL | J47: GESPROBAN | K47: 24705 | L47: ASALARIADO | M47: MEDICO | N47: FINANCIAMIENTO | O47: SI | P47: NO | Q47: SI | R47: 15000 | S47: A | T47: 65.93 | U47: 0 | V47: =U47+T47 -> 65.93 | X47: =AB47*T47 -> 154935.5 | AA47: 185000 | AB47: 2350 | AC47: =((AD47*1)/AA47) -> 1 | AD47: =SUMIFS(Tabla35[Abonos],Tabla35[Lote],Tabla4[[#This Row],[UNIDAD APTO]],Tabla35[Cliente],Tabla4[[#This Row],[CLIENTE]],Tabla35[Concepto],"ABONO")+SUMIFS(Tabla35[Abonos],Tabla35[Lote],Tabla4[[#This Row],[UNIDAD APTO]],Tabla35[Cliente],Tabla4[[#This Row],[CLIENTE]],Tabla35[Concepto],"MULTIBANK") -> 185000 | AE47: =Tabla4[[#This Row],[VALOR TOTAL]]-Tabla4[[#This Row],[MONTO A MULTIBANK]] -> 14801 | AF47: =Tabla4[[#This Row],[MONTO CPP]] -> 170199 | AG47: =ABONOS!E48 -> 0 | AH47: {=_xlfn.IFS(Tabla4[[#This Row],[RESERVADAS, VENDIDAS]]="DISPONIBLE","",Tabla4[[#This Row],[SALDO PENDIENTE]]=0,"PAZ Y SALVO",Tabla4[[#This Row],[SALDO PENDIENTE]]=Tabla4[[#This Row],[MONTO CPP]],"COBRO CPP",Tabla4[[#This Row],[SALDO PENDIENTE]]>0,"PENDIENTE")} -> PAZ Y SALVO | AI47: COOPERATIVA DE PROFESIONALES, R.L. | AL47: CON CPP | AM47: 45670 | AN47: 46035 | AO47: CON CPP | AP47: 170199 | AQ47: Reservada - Con Contrato | AR47: 45587 | AS47: 185000 | AT47: 30474595 | AU47: BANCO | AV47: BANCO | AW47: =ABONOS!O48 -> 0 | AX47: {=_xlfn.IFS(Tabla4[[#This Row],[MONTO5]]=0,"",Tabla4[[#This Row],[SALDO PENDIENTE3]]=0,"PAZ Y SALVO",Tabla4[[#This Row],[SALDO PENDIENTE3]]>0,"PENDIENTE")} -> PAZ Y SALVO | AY47: INSCRITA Y DESEMBOLSADA | AZ47: 45672 | BA47: SI | BB47: 45678 | BC47: =Tabla4[[#This Row],[FECHA RECIBIDO MINUTA LIBERACION]]-Tabla4[[#This Row],[SOLICITUD DE MINUTA LIBERACIÓN]] -> 6 | BD47: SI | BE47: 45678 | BF47: SI | BG47: 45678 | BH47: 45679 | BI47: 45689 | BJ47: CORPORACIÓN DE INGENIEROS | BK47: BANCO | BL47: 45714 | BM47: 45714 | BN47: 45714 | BO47: 45714 | BP47: =Tabla4[[#This Row],[RECEPCIÓN INTERINO]]-Tabla4[[#This Row],[ENVIO A INTERINO]] -> 0 | BQ47: 45713 | BR47: 45713 | BS47: 45713 | BT47: 45713 | BU47: 45722 | BV47: SI | BW47: BANCO | BX47: 45735 | BY47: 45736 | BZ47: 45761 | CA47: 45761 | CB47: 45776 | CC47: 45819
A48: L-101 | B48: -400 | D48: DISPONIBLE | E48: PENDIENTE | S48: A | T48: 65.93 | U48: 97.72 | V48: =U48+T48 -> 163.65 | W48: =U48*80 -> 7817.6 | X48: =AB48*T48 -> 154935.5 | AA48: 220862.25 | AB48: 2350 | AC48: =((AD48*1)/AA48) -> 0 | AD48: =SUMIFS(Tabla35[Abonos],Tabla35[Lote],Tabla4[[#This Row],[UNIDAD APTO]],Tabla35[Cliente],Tabla4[[#This Row],[CLIENTE]],Tabla35[Concepto],"ABONO")+SUMIFS(Tabla35[Abonos],Tabla35[Lote],Tabla4[[#This Row],[UNIDAD APTO]],Tabla35[Cliente],Tabla4[[#This Row],[CLIENTE]],Tabla35[Concepto],"MULTIBANK") -> 0 | AG48: =ABONOS!E49 -> 0 | AH48: {=_xlfn.IFS(Tabla4[[#This Row],[RESERVADAS, VENDIDAS]]="DISPONIBLE","",Tabla4[[#This Row],[SALDO PENDIENTE]]=0,"PAZ Y SALVO",Tabla4[[#This Row],[SALDO PENDIENTE]]=Tabla4[[#This Row],[MONTO CPP]],"COBRO CPP",Tabla4[[#This Row],[SALDO PENDIENTE]]>0,"PENDIENTE")} | AQ48: Por vender | AT48: 30474617 | AW48: =ABONOS!O49 -> 0 | AX48: {=_xlfn.IFS(Tabla4[[#This Row],[MONTO5]]=0,"",Tabla4[[#This Row],[SALDO PENDIENTE3]]=0,"PAZ Y SALVO",Tabla4[[#This Row],[SALDO PENDIENTE3]]>0,"PENDIENTE")} | BC48: =Tabla4[[#This Row],[FECHA RECIBIDO MINUTA LIBERACION]]-Tabla4[[#This Row],[SOLICITUD DE MINUTA LIBERACIÓN]] -> 0 | BP48: =Tabla4[[#This Row],[RECEPCIÓN INTERINO]]-Tabla4[[#This Row],[ENVIO A INTERINO]] -> 0
A49: L-102 | B49: -400 | C49: PAUL HINSHAW | D49: TRASPASADO | E49: INSCRITO Y DESEMBOLSADO | F49: 45867 | G49: 558796241 | H49: ESTADOUNIDENSE | I49: EXTRANJERO NO RESIDENTE | J49: PANAMA EQUITY | K49: 22693 | L49: INDEPENDIENTE / JUBILADO | N49: CONTADO | S49: B | T49: 59.94 | U49: 19.3 | V49: =U49+T49 -> 79.24 | W49: =U49*80 -> 1544 | X49: =AB49*T49 -> 140859 | AA49: 182000 | AB49: 2350 | AC49: =((AD49*1)/AA49) -> 1 | AD49: =SUMIFS(Tabla35[Abonos],Tabla35[Lote],Tabla4[[#This Row],[UNIDAD APTO]],Tabla35[Cliente],Tabla4[[#This Row],[CLIENTE]],Tabla35[Concepto],"ABONO")+SUMIFS(Tabla35[Abonos],Tabla35[Lote],Tabla4[[#This Row],[UNIDAD APTO]],Tabla35[Cliente],Tabla4[[#This Row],[CLIENTE]],Tabla35[Concepto],"MULTIBANK") -> 182000 | AE49: =Tabla4[[#This Row],[VALOR TOTAL]]-Tabla4[[#This Row],[MONTO A MULTIBANK]] -> 182000 | AF49: 0 | AG49: =ABONOS!E50 -> 0 | AH49: {=_xlfn.IFS(Tabla4[[#This Row],[RESERVADAS, VENDIDAS]]="DISPONIBLE","",Tabla4[[#This Row],[SALDO PENDIENTE]]=0,"PAZ Y SALVO",Tabla4[[#This Row],[SALDO PENDIENTE]]=Tabla4[[#This Row],[MONTO CPP]],"COBRO CPP",Tabla4[[#This Row],[SALDO PENDIENTE]]>0,"PENDIENTE")} -> PAZ Y SALVO | AI49: N/A | AJ49: N/A | AK49: N/A | AL49: N/A | AM49: N/A | AN49: N/A | AO49: N/A | AP49: N/A | AQ49: Reservada - Con Contrato | AR49: 45869 | AS49: 182000 | AT49: 30474616 | AU49: GISA | AV49: 1704 | AW49: =ABONOS!O50 -> 0 | AX49: {=_xlfn.IFS(Tabla4[[#This Row],[MONTO5]]=0,"",Tabla4[[#This Row],[SALDO PENDIENTE3]]=0,"PAZ Y SALVO",Tabla4[[#This Row],[SALDO PENDIENTE3]]>0,"PENDIENTE")} -> PAZ Y SALVO | AY49: INSCRITA Y DESEMBOLSADA | AZ49: 45926 | BA49: SI | BB49: 45933 | BC49: =Tabla4[[#This Row],[FECHA RECIBIDO MINUTA LIBERACION]]-Tabla4[[#This Row],[SOLICITUD DE MINUTA LIBERACIÓN]] -> 7 | BD49: SI | BE49: 45945 | BF49: N/A | BG49: N/A | BH49: N/A | BI49: N/A | BJ49: N/A | BK49: 45945 | BL49: 45950 | BM49: 45945 | BN49: 45950 | BO49: 45951 | BP49: =Tabla4[[#This Row],[RECEPCIÓN INTERINO]]-Tabla4[[#This Row],[ENVIO A INTERINO]] -> 1 | BQ49: 45974 | BR49: 45968 | BS49: 45974 | BT49: 45974 | BU49: N/A | BV49: SI | BW49: 45974 | BX49: 45975 | BY49: 45975 | BZ49: 45981 | CA49: N/A | CB49: 45952 | CC49: 45943
A50: L-103 | B50: -400 | C50: ALLISON SMITH HARRIS | D50: TRASPASADO | E50: INSCRITO Y DESEMBOLSADO | F50: 45675 | G50: 682638818 | H50: ESTADOUNIDENSE | I50: EXTRANJERO NO RESIDENTE | J50: PANAMA EQUITY | K50: 28066 | L50: ASALARIADO | M50: ADMINISTRADOR DE EMPRESAS | N50: FINANCIAMIENTO | O50: NO | P50: NO | Q50: N/A | S50: C | T50: 73.09 | U50: 19.95 | V50: =U50+T50 -> 93.04 | W50: =U50*80 -> 1596 | X50: =AB50*T50 -> 171761.5 | AA50: 236000 | AB50: 2350 | AC50: =((AD50*1)/AA50) -> 1 | AD50: =SUMIFS(Tabla35[Abonos],Tabla35[Lote],Tabla4[[#This Row],[UNIDAD APTO]],Tabla35[Cliente],Tabla4[[#This Row],[CLIENTE]],Tabla35[Concepto],"ABONO")+SUMIFS(Tabla35[Abonos],Tabla35[Lote],Tabla4[[#This Row],[UNIDAD APTO]],Tabla35[Cliente],Tabla4[[#This Row],[CLIENTE]],Tabla35[Concepto],"MULTIBANK") -> 236000 | AE50: =Tabla4[[#This Row],[VALOR TOTAL]]-Tabla4[[#This Row],[MONTO A MULTIBANK]] -> 68700 | AF50: =Tabla4[[#This Row],[MONTO CPP]] -> 167300 | AG50: =ABONOS!E51 -> 0 | AH50: {=_xlfn.IFS(Tabla4[[#This Row],[RESERVADAS, VENDIDAS]]="DISPONIBLE","",Tabla4[[#This Row],[SALDO PENDIENTE]]=0,"PAZ Y SALVO",Tabla4[[#This Row],[SALDO PENDIENTE]]=Tabla4[[#This Row],[MONTO CPP]],"COBRO CPP",Tabla4[[#This Row],[SALDO PENDIENTE]]>0,"PENDIENTE")} -> PAZ Y SALVO | AI50: BANESCO | AL50: CON CPP | AM50: 45783 | AO50: CON CPP | AP50: 167300 | AQ50: Reservada - Con Contrato | AR50: 45785 | AS50: 236000 | AT50: 30474615 | AU50: BANCO | AV50: BANCO | AW50: =ABONOS!O51 -> 0 | AX50: {=_xlfn.IFS(Tabla4[[#This Row],[MONTO5]]=0,"",Tabla4[[#This Row],[SALDO PENDIENTE3]]=0,"PAZ Y SALVO",Tabla4[[#This Row],[SALDO PENDIENTE3]]>0,"PENDIENTE")} -> PAZ Y SALVO | AY50: INSCRITA Y DESEMBOLSADA | AZ50: 45796 | BA50: SI | BB50: 45800 | BC50: =Tabla4[[#This Row],[FECHA RECIBIDO MINUTA LIBERACION]]-Tabla4[[#This Row],[SOLICITUD DE MINUTA LIBERACIÓN]] -> 4 | BD50: SI | BE50: 45801 | BF50: SI | BG50: 45801 | BH50: N/A | BI50: N/A | BJ50: N/A | BK50: 45825 | BL50: 45824 | BM50: 45828 | BN50: 45828 | BO50: 45831 | BP50: =Tabla4[[#This Row],[RECEPCIÓN INTERINO]]-Tabla4[[#This Row],[ENVIO A INTERINO]] -> 3 | BQ50: 45833 | BR50: 45825 | BS50: 45833 | BT50: 45825 | BU50: 45834 | BV50: SI | BW50: BANCO | BX50: 45845 | BY50: 45849 | BZ50: 45849 | CA50: 45849 | CB50: 45856 | CC50: 45873
A51: L-104 | B51: -400 | C51: PEDRO GALVEZ | D51: TRASPASADO | E51: INSCRITO Y DESEMBOLSADO | F51: 45413 | G51: E-8-182664 | H51: GUATEMALTECO | I51: EXTRANJERO RESIDENTE | J51: GESPROBAN | K51: 31368 | L51: INDEPENDIENTE | M51: ADMINISTRADOR DE EMPRESAS | N51: FINANCIAMIENTO | O51: SI | Q51: SI | S51: C | T51: 73.09 | U51: 19.95 | V51: =U51+T51 -> 93.04 | W51: =U51*80 -> 1596 | X51: =AB51*T51 -> 171761.5 | AA51: 212650 | AB51: 2350 | AC51: =((AD51*1)/AA51) -> 1 | AD51: =SUMIFS(Tabla35[Abonos],Tabla35[Lote],Tabla4[[#This Row],[UNIDAD APTO]],Tabla35[Cliente],Tabla4[[#This Row],[CLIENTE]],Tabla35[Concepto],"ABONO")+SUMIFS(Tabla35[Abonos],Tabla35[Lote],Tabla4[[#This Row],[UNIDAD APTO]],Tabla35[Cliente],Tabla4[[#This Row],[CLIENTE]],Tabla35[Concepto],"MULTIBANK") -> 212650 | AE51: =Tabla4[[#This Row],[VALOR TOTAL]]-Tabla4[[#This Row],[MONTO A MULTIBANK]] -> 74427.5 | AF51: =Tabla4[[#This Row],[VALOR TOTAL]]*65% -> 138222.5 | AG51: =ABONOS!E52 -> 0 | AH51: {=_xlfn.IFS(Tabla4[[#This Row],[RESERVADAS, VENDIDAS]]="DISPONIBLE","",Tabla4[[#This Row],[SALDO PENDIENTE]]=0,"PAZ Y SALVO",Tabla4[[#This Row],[SALDO PENDIENTE]]=Tabla4[[#This Row],[MONTO CPP]],"COBRO CPP",Tabla4[[#This Row],[SALDO PENDIENTE]]>0,"PENDIENTE")} -> PAZ Y SALVO | AI51: MULTIBANK | AJ51: ANA LUCIA SOTO | AK51: Ana.Soto@multibank.com.pa / 6607-9679 | AL51: CON CPP | AM51: 45454 | AN51: N/A | AO51: CON CPP | AP51: 111650 | AQ51: Reservada - Con Contrato | AR51: 45423 | AS51: =AA51 -> 212650 | AT51: 30474614 | AU51: MULTIBANK | AV51: BANCO | AW51: =ABONOS!O52 -> 0 | AX51: {=_xlfn.IFS(Tabla4[[#This Row],[MONTO5]]=0,"",Tabla4[[#This Row],[SALDO PENDIENTE3]]=0,"PAZ Y SALVO",Tabla4[[#This Row],[SALDO PENDIENTE3]]>0,"PENDIENTE")} -> PAZ Y SALVO | AY51: INSCRITA Y DESEMBOLSADA | AZ51: 45455 | BA51: SI | BB51: 45496 | BC51: =Tabla4[[#This Row],[FECHA RECIBIDO MINUTA LIBERACION]]-Tabla4[[#This Row],[SOLICITUD DE MINUTA LIBERACIÓN]] -> 41 | BD51: SI | BE51: 45468 | BF51: SI | BG51: 45468 | BH51: 45468 | BI51: 45481 | BJ51: AVANCE | BK51: 45504 | BL51: 45503 | BM51: 45504 | BN51: 45504 | BO51: 45511 | BP51: =Tabla4[[#This Row],[RECEPCIÓN INTERINO]]-Tabla4[[#This Row],[ENVIO A INTERINO]] -> 7 | BQ51: 45511 | BR51: 45511 | BS51: 45511 | BT51: 45511 | BU51: 45512 | BV51: SI | BW51: 45503 | BX51: 45517 | BY51: 45520 | BZ51: 45524 | CA51: 45524 | CB51: 45530 | CC51: 45534
A52: L-105 | B52: -400 | D52: DISPONIBLE | E52: PENDIENTE | S52: C | T52: 73.09 | U52: 19.88 | V52: =U52+T52 -> 92.97 | W52: =U52*80 -> 1590.4 | X52: =AB52*T52 -> 171761.5 | AA52: 250000 | AB52: 2350 | AC52: =((AD52*1)/AA52) -> 0 | AD52: =SUMIFS(Tabla35[Abonos],Tabla35[Lote],Tabla4[[#This Row],[UNIDAD APTO]],Tabla35[Cliente],Tabla4[[#This Row],[CLIENTE]],Tabla35[Concepto],"ABONO")+SUMIFS(Tabla35[Abonos],Tabla35[Lote],Tabla4[[#This Row],[UNIDAD APTO]],Tabla35[Cliente],Tabla4[[#This Row],[CLIENTE]],Tabla35[Concepto],"MULTIBANK") -> 0 | AG52: =ABONOS!E53 -> 0 | AH52: {=_xlfn.IFS(Tabla4[[#This Row],[RESERVADAS, VENDIDAS]]="DISPONIBLE","",Tabla4[[#This Row],[SALDO PENDIENTE]]=0,"PAZ Y SALVO",Tabla4[[#This Row],[SALDO PENDIENTE]]=Tabla4[[#This Row],[MONTO CPP]],"COBRO CPP",Tabla4[[#This Row],[SALDO PENDIENTE]]>0,"PENDIENTE")} | AQ52: Por vender | AT52: 30474613 | AW52: =ABONOS!O53 -> 0 | AX52: {=_xlfn.IFS(Tabla4[[#This Row],[MONTO5]]=0,"",Tabla4[[#This Row],[SALDO PENDIENTE3]]=0,"PAZ Y SALVO",Tabla4[[#This Row],[SALDO PENDIENTE3]]>0,"PENDIENTE")} | BC52: =Tabla4[[#This Row],[FECHA RECIBIDO MINUTA LIBERACION]]-Tabla4[[#This Row],[SOLICITUD DE MINUTA LIBERACIÓN]] -> 0 | BP52: =Tabla4[[#This Row],[RECEPCIÓN INTERINO]]-Tabla4[[#This Row],[ENVIO A INTERINO]] -> 0
A53: L-106 | B53: -400 | C53: SANDRA KAVANAUGH | D53: TRASPASADO | E53: INSCRITO Y DESEMBOLSADO | F53: 45505 | G53: 532922899 | H53: ESTADOUNIDENSE | I53: EXTRANJERO NO RESIDENTE | J53: PANAMA PACIFICA REALTY | K53: 19755 | L53: INDEPENDIENTE | M53: CURADORA | N53: CONTADO | S53: C | T53: 73.98 | U53: 28.43 | V53: =U53+T53 -> 102.41 | W53: =U53*80 -> 2274.4 | X53: =AB53*T53 -> 173853 | AA53: 250000 | AB53: 2350 | AC53: =((AD53*1)/AA53) -> 1 | AD53: =SUMIFS(Tabla35[Abonos],Tabla35[Lote],Tabla4[[#This Row],[UNIDAD APTO]],Tabla35[Cliente],Tabla4[[#This Row],[CLIENTE]],Tabla35[Concepto],"ABONO")+SUMIFS(Tabla35[Abonos],Tabla35[Lote],Tabla4[[#This Row],[UNIDAD APTO]],Tabla35[Cliente],Tabla4[[#This Row],[CLIENTE]],Tabla35[Concepto],"MULTIBANK") -> 250000 | AE53: =Tabla4[[#This Row],[VALOR TOTAL]]-Tabla4[[#This Row],[MONTO A MULTIBANK]] -> 75000 | AF53: =Tabla4[[#This Row],[MONTO CPP]] -> 175000 | AG53: =ABONOS!E54 -> 0 | AH53: {=_xlfn.IFS(Tabla4[[#This Row],[RESERVADAS, VENDIDAS]]="DISPONIBLE","",Tabla4[[#This Row],[SALDO PENDIENTE]]=0,"PAZ Y SALVO",Tabla4[[#This Row],[SALDO PENDIENTE]]=Tabla4[[#This Row],[MONTO CPP]],"COBRO CPP",Tabla4[[#This Row],[SALDO PENDIENTE]]>0,"PENDIENTE")} -> PAZ Y SALVO | AI53: BANCO ALIADO | AJ53: N/A | AK53: N/A | AL53: CON CPP | AM53: 45629 | AN53: 45719 | AO53: FONDO PROPIOS PIGNORADOS | AP53: 175000 | AQ53: Reservada - Con Contrato | AR53: 45582 | AS53: =AA53 -> 250000 | AT53: 30474612 | AU53: GISA | AV53: 2100 | AW53: =ABONOS!O54 -> 0 | AX53: {=_xlfn.IFS(Tabla4[[#This Row],[MONTO5]]=0,"",Tabla4[[#This Row],[SALDO PENDIENTE3]]=0,"PAZ Y SALVO",Tabla4[[#This Row],[SALDO PENDIENTE3]]>0,"PENDIENTE")} -> PAZ Y SALVO | AY53: INSCRITA Y DESEMBOLSADA | AZ53: 45643 | BA53: SI | BB53: 45656 | BC53: =Tabla4[[#This Row],[FECHA RECIBIDO MINUTA LIBERACION]]-Tabla4[[#This Row],[SOLICITUD DE MINUTA LIBERACIÓN]] -> 13 | BD53: SI | BE53: 45625 | BF53: N/A | BG53: N/A | BH53: N/A | BI53: N/A | BJ53: N/A | BK53: 45625 | BL53: 45630 | BM53: 45667 | BN53: 45663 | BO53: 45665 | BP53: =Tabla4[[#This Row],[RECEPCIÓN INTERINO]]-Tabla4[[#This Row],[ENVIO A INTERINO]] -> 2 | BQ53: 45667 | BR53: 45667 | BS53: 45667 | BT53: 45667 | BU53: N/A | BV53: SI | BW53: 45625 | BX53: 45667 | BY53: 45667 | BZ53: 45678 | CA53: 45678 | CB53: 45685 | CC53: 45638
A54: L-107 | B54: -400 | C54: ADELI ZAVALETA | D54: TRASPASADO | E54: INSCRITO Y DESEMBOLSADO | F54: 46127 | G54: E-8-227576 | H54: PERUANA | I54: EXTRANJERO RESIDENTE | J54: GESPROBAN | L54: INDEPENDIENTE | M54: INGENIERA | N54: CONTADO | O54: NO | P54: NO | Q54: NO | R54: N/A | S54: C | T54: 73.09 | U54: 22.62 | V54: =U54+T54 -> 95.71 | W54: =U54*80 -> 1809.6 | X54: =AB54*T54 -> 171761.5 | AA54: 220000 | AB54: 2350 | AC54: =((AD54*1)/AA54) -> 0.5 | AD54: =SUMIFS(Tabla35[Abonos],Tabla35[Lote],Tabla4[[#This Row],[UNIDAD APTO]],Tabla35[Cliente],Tabla4[[#This Row],[CLIENTE]],Tabla35[Concepto],"ABONO")+SUMIFS(Tabla35[Abonos],Tabla35[Lote],Tabla4[[#This Row],[UNIDAD APTO]],Tabla35[Cliente],Tabla4[[#This Row],[CLIENTE]],Tabla35[Concepto],"MULTIBANK") -> 110000 | AE54: =Tabla4[[#This Row],[VALOR TOTAL]]-AF54 -> 220000 | AF54: 0 | AG54: =ABONOS!E55 -> 110000 | AH54: {=_xlfn.IFS(Tabla4[[#This Row],[RESERVADAS, VENDIDAS]]="DISPONIBLE","",Tabla4[[#This Row],[SALDO PENDIENTE]]=0,"PAZ Y SALVO",Tabla4[[#This Row],[SALDO PENDIENTE]]=Tabla4[[#This Row],[MONTO CPP]],"COBRO CPP",Tabla4[[#This Row],[SALDO PENDIENTE]]>0,"PENDIENTE")} -> COBRO CPP | AI54: BANESCO | AL54: CON CPP | AM54: 46142 | AN54: =Tabla4[[#This Row],[FECHA DE EMISION DE CPP]]+90 -> 46232 | AO54: FONDO PROPIOS PIGNORADOS | AP54: 110000 | AQ54: Reservada - Con Contrato | AR54: 46135 | AS54: 220000 | AT54: 30474611 | AU54: CLIENTE | AW54: =ABONOS!O55 -> 0 | AX54: {=_xlfn.IFS(Tabla4[[#This Row],[MONTO5]]=0,"",Tabla4[[#This Row],[SALDO PENDIENTE3]]=0,"PAZ Y SALVO",Tabla4[[#This Row],[SALDO PENDIENTE3]]>0,"PENDIENTE")} | AY54: INSCRITA Y DESEMBOLSADA | AZ54: 46136 | BA54: NO | BB54: 46156 | BC54: =Tabla4[[#This Row],[FECHA RECIBIDO MINUTA LIBERACION]]-Tabla4[[#This Row],[SOLICITUD DE MINUTA LIBERACIÓN]] -> 20 | BD54: SI | BE54: 46156 | BF54: N/A | BG54: N/A | BH54: N/A | BI54: N/A | BJ54: N/A | BK54: 46162 | BL54: 46162 | BM54: 46162 | BN54: 46163 | BO54: 46163 | BP54: =Tabla4[[#This Row],[RECEPCIÓN INTERINO]]-Tabla4[[#This Row],[ENVIO A INTERINO]] -> 0 | BQ54: 46162 | BR54: 46155 | BS54: 46155 | BT54: 46155 | BU54: N/A | BV54: SI | BW54: 46162 | BX54: 46162 | BY54: 46169 | BZ54: 46175 | CA54: 46175 | CB54: 46190 | CC54: 46168
A55: L-108 | B55: -400 | C55: ADELI ZAVALETA | D55: TRASPASADO | E55: INSCRITO Y DESEMBOLSADO | F55: 46230 | G55: E-8-227576 | H55: PERUANA | I55: EXTRANJERO RESIDENTE | J55: GESPROBAN | L55: INDEPENDIENTE | M55: INGENIERA | N55: CONTADO | O55: NO | P55: NO | Q55: NO | R55: N/A | S55: C | T55: 73.09 | U55: 22.62 | V55: =U55+T55 -> 95.71 | W55: =U55*80 -> 1809.6 | X55: =AB55*T55 -> 171761.5 | AA55: 217000 | AB55: 2350 | AC55: =((AD55*1)/AA55) -> 0.5 | AD55: 108500 | AE55: =Tabla4[[#This Row],[VALOR TOTAL]]-AF55 -> 217000 | AF55: 0 | AG55: 108500 | AH55: {=_xlfn.IFS(Tabla4[[#This Row],[RESERVADAS, VENDIDAS]]="DISPONIBLE","",Tabla4[[#This Row],[SALDO PENDIENTE]]=0,"PAZ Y SALVO",Tabla4[[#This Row],[SALDO PENDIENTE]]=Tabla4[[#This Row],[MONTO CPP]],"COBRO CPP",Tabla4[[#This Row],[SALDO PENDIENTE]]>0,"PENDIENTE")} -> PENDIENTE | AI55: N/A | AJ55: N/A | AK55: N/A | AL55: N/A | AM55: N/A | AN55: N/A | AO55: N/A | AP55: N/A | AQ55: Reservada - Con Contrato | AR55: 46232 | AS55: 217000 | AT55: 30474610 | AU55: CLIENTE | AW55: =ABONOS!O56 -> 0 | AX55: {=_xlfn.IFS(Tabla4[[#This Row],[MONTO5]]=0,"",Tabla4[[#This Row],[SALDO PENDIENTE3]]=0,"PAZ Y SALVO",Tabla4[[#This Row],[SALDO PENDIENTE3]]>0,"PENDIENTE")} | AY55: 06-08-26: EN CONFECCIÓN DE ESCRITURAS | AZ55: 46232 | BA55: SI | BB55: 46239 | BC55: =Tabla4[[#This Row],[FECHA RECIBIDO MINUTA LIBERACION]]-Tabla4[[#This Row],[SOLICITUD DE MINUTA LIBERACIÓN]] -> 7 | BD55: SI | BE55: 46237 | BF55: N/A | BG55: 46240 | BH55: N/A | BI55: N/A | BJ55: N/A | BK55: 46240 | BP55: =Tabla4[[#This Row],[RECEPCIÓN INTERINO]]-Tabla4[[#This Row],[ENVIO A INTERINO]] -> 0 | BZ55: 46261
A56: L-109 | B56: -400 | C56: CARMEN BERNASCONI | D56: TRASPASADO | E56: INSCRITO Y DESEMBOLSADO | F56: 45747 | G56: 544315117 | H56: ESTADOUNIDENSE | I56: EXTRANJERO NO RESIDENTE | J56: GESPROBAN | K56: 24591 | L56: INDEPENDIENTE / JUBILADO | M56: EDUCADOR | N56: CONTADO | O56: NO | P56: NO | Q56: N/A | R56: N/A | S56: C | T56: 73.09 | U56: 19.97 | V56: =U56+T56 -> 93.06 | W56: =U56*80 -> 1597.6 | X56: =AB56*T56 -> 171761.5 | AA56: 221338.98 | AB56: 2350 | AC56: =((AD56*1)/AA56) -> 1 | AD56: =SUMIFS(Tabla35[Abonos],Tabla35[Lote],Tabla4[[#This Row],[UNIDAD APTO]],Tabla35[Cliente],Tabla4[[#This Row],[CLIENTE]],Tabla35[Concepto],"ABONO")+SUMIFS(Tabla35[Abonos],Tabla35[Lote],Tabla4[[#This Row],[UNIDAD APTO]],Tabla35[Cliente],Tabla4[[#This Row],[CLIENTE]],Tabla35[Concepto],"MULTIBANK") -> 221338.98 | AE56: =Tabla4[[#This Row],[VALOR TOTAL]]-Tabla4[[#This Row],[MONTO A MULTIBANK]] -> 221338.98 | AF56: 0 | AG56: =ABONOS!E57 -> 0 | AH56: {=_xlfn.IFS(Tabla4[[#This Row],[RESERVADAS, VENDIDAS]]="DISPONIBLE","",Tabla4[[#This Row],[SALDO PENDIENTE]]=0,"PAZ Y SALVO",Tabla4[[#This Row],[SALDO PENDIENTE]]=Tabla4[[#This Row],[MONTO CPP]],"COBRO CPP",Tabla4[[#This Row],[SALDO PENDIENTE]]>0,"PENDIENTE")} -> PAZ Y SALVO | AI56: N/A | AJ56: N/A | AK56: N/A | AL56: N/A | AM56: N/A | AN56: N/A | AO56: N/A | AP56: N/A | AQ56: Reservada - Con Contrato | AR56: 45784 | AS56: =Tabla4[[#This Row],[VALOR TOTAL]] -> 221338.98 | AT56: 30474609 | AU56: GISA | AV56: 1824 | AW56: =ABONOS!O57 -> 57.1 | AX56: {=_xlfn.IFS(Tabla4[[#This Row],[MONTO5]]=0,"",Tabla4[[#This Row],[SALDO PENDIENTE3]]=0,"PAZ Y SALVO",Tabla4[[#This Row],[SALDO PENDIENTE3]]>0,"PENDIENTE")} -> PENDIENTE | AY56: INSCRITA Y DESEMBOLSADA | AZ56: 45954 | BA56: SI | BB56: 45961 | BC56: =Tabla4[[#This Row],[FECHA RECIBIDO MINUTA LIBERACION]]-Tabla4[[#This Row],[SOLICITUD DE MINUTA LIBERACIÓN]] -> 7 | BD56: SI | BE56: 45973 | BF56: N/A | BG56: N/A | BH56: N/A | BI56: N/A | BJ56: N/A | BK56: 45973 | BL56: 46030 | BM56: 45973 | BN56: 46033 | BO56: 46034 | BP56: =Tabla4[[#This Row],[RECEPCIÓN INTERINO]]-Tabla4[[#This Row],[ENVIO A INTERINO]] -> 1 | BQ56: 46051 | BR56: 46045 | BS56: 46052 | BT56: 46052 | BU56: N/A | BV56: SI | BW56: 46055 | BX56: 46055 | BY56: 46057 | BZ56: 46066 | CA56: N/A | CB56: N/A | CC56: 46020
A57: L-110 | B57: -400 | D57: TRASPASADO | E57: CON CLIENTE | F57: 46238 | G57: 646120672 | O57: SI | Q57: SI | S57: C | T57: 73.09 | U57: 19.97 | V57: =U57+T57 -> 93.06 | W57: =U57*80 -> 1597.6 | X57: =AB57*T57 -> 171761.5 | AA57: 204000 | AB57: 2350 | AC57: =((AD57*1)/AA57) -> 0 | AD57: =SUMIFS(Tabla35[Abonos],Tabla35[Lote],Tabla4[[#This Row],[UNIDAD APTO]],Tabla35[Cliente],Tabla4[[#This Row],[CLIENTE]],Tabla35[Concepto],"ABONO")+SUMIFS(Tabla35[Abonos],Tabla35[Lote],Tabla4[[#This Row],[UNIDAD APTO]],Tabla35[Cliente],Tabla4[[#This Row],[CLIENTE]],Tabla35[Concepto],"MULTIBANK") -> 0 | AG57: =ABONOS!E58 -> 0 | AH57: {=_xlfn.IFS(Tabla4[[#This Row],[RESERVADAS, VENDIDAS]]="DISPONIBLE","",Tabla4[[#This Row],[SALDO PENDIENTE]]=0,"PAZ Y SALVO",Tabla4[[#This Row],[SALDO PENDIENTE]]=Tabla4[[#This Row],[MONTO CPP]],"COBRO CPP",Tabla4[[#This Row],[SALDO PENDIENTE]]>0,"PENDIENTE")} -> PAZ Y SALVO | AQ57: Por vender | AT57: 30474608 | AW57: =ABONOS!O58 -> 0 | AX57: {=_xlfn.IFS(Tabla4[[#This Row],[MONTO5]]=0,"",Tabla4[[#This Row],[SALDO PENDIENTE3]]=0,"PAZ Y SALVO",Tabla4[[#This Row],[SALDO PENDIENTE3]]>0,"PENDIENTE")} | BC57: =Tabla4[[#This Row],[FECHA RECIBIDO MINUTA LIBERACION]]-Tabla4[[#This Row],[SOLICITUD DE MINUTA LIBERACIÓN]] -> 0 | BP57: =Tabla4[[#This Row],[RECEPCIÓN INTERINO]]-Tabla4[[#This Row],[ENVIO A INTERINO]] -> 0
A58: L-111 | B58: -400 | D58: DISPONIBLE | E58: PENDIENTE | S58: B | T58: 59.94 | U58: 19.34 | V58: =U58+T58 -> 79.28 | W58: =U58*80 -> 1547.2 | X58: =AB58*T58 -> 140859 | AA58: 194230.69 | AB58: 2350 | AC58: =((AD58*1)/AA58) -> 0 | AD58: =SUMIFS(Tabla35[Abonos],Tabla35[Lote],Tabla4[[#This Row],[UNIDAD APTO]],Tabla35[Cliente],Tabla4[[#This Row],[CLIENTE]],Tabla35[Concepto],"ABONO")+SUMIFS(Tabla35[Abonos],Tabla35[Lote],Tabla4[[#This Row],[UNIDAD APTO]],Tabla35[Cliente],Tabla4[[#This Row],[CLIENTE]],Tabla35[Concepto],"MULTIBANK") -> 0 | AG58: =ABONOS!E59 -> 0 | AH58: {=_xlfn.IFS(Tabla4[[#This Row],[RESERVADAS, VENDIDAS]]="DISPONIBLE","",Tabla4[[#This Row],[SALDO PENDIENTE]]=0,"PAZ Y SALVO",Tabla4[[#This Row],[SALDO PENDIENTE]]=Tabla4[[#This Row],[MONTO CPP]],"COBRO CPP",Tabla4[[#This Row],[SALDO PENDIENTE]]>0,"PENDIENTE")} | AQ58: Por vender | AT58: 30474607 | AW58: =ABONOS!O59 -> 0 | AX58: {=_xlfn.IFS(Tabla4[[#This Row],[MONTO5]]=0,"",Tabla4[[#This Row],[SALDO PENDIENTE3]]=0,"PAZ Y SALVO",Tabla4[[#This Row],[SALDO PENDIENTE3]]>0,"PENDIENTE")} | BC58: =Tabla4[[#This Row],[FECHA RECIBIDO MINUTA LIBERACION]]-Tabla4[[#This Row],[SOLICITUD DE MINUTA LIBERACIÓN]] -> 0 | BP58: =Tabla4[[#This Row],[RECEPCIÓN INTERINO]]-Tabla4[[#This Row],[ENVIO A INTERINO]] -> 0
B59: TOTAL | AE59: =SUM(AF2:AF58) -> 4600000
H96: LIBRE
H97: CON CLIENTE
H98: DESEMBOLSADO
H99: DESEMBOLSADO Y TRASPASADO

Sheet ABONOS
B2: APTO | C2: CLIENTE | D2: VALOR VENTA | E2: PENDIENTE PRECIO APTO | F2: TOTAL PENDIENTE | G2: MONTO GISA | H2: ABONO GISA COBRADO | I2: PENDIENTE GISA | J2: MONTO MULTIBANK | K2: COBRADO MULTIBANK | L2: PENDIENTE MULTIBANK | M2: GASTOS LEGALES | N2: GASTOS LEGALES COBRADOS | O2: PENDIENTE GASTOS LEGALES | P2: FONDO ADMIN | Q2: FONDO ADM COBRADO | R2: FONDO ADM PENDIENTE | S2: MEDIDOR | T2: MEDIDOR COBRADO | U2: MEDIDOR PENDIENTE | V2: PENALIZACIÓN | W2: PENALIZACIÓN COBRADO | X2: PENALIZACIÓN PENDIENTE
B3: L-501 | C3: ='BASE DATOS'!C2 -> KEVIN FORSYTH | D3: ='BASE DATOS'!AA2 -> 168121.5 | E3: =I3+L3 -> 0 | F3: =Tabla5[[#This Row],[PENDIENTE GISA]]+Tabla5[[#This Row],[PENDIENTE MULTIBANK]]+Tabla5[[#This Row],[PENDIENTE GASTOS LEGALES]]+Tabla5[[#This Row],[FONDO ADM PENDIENTE]]+Tabla5[[#This Row],[MEDIDOR PENDIENTE]]+Tabla5[[#This Row],[PENALIZACIÓN PENDIENTE]] -> 0 | G3: ='BASE DATOS'!AE2 -> 50461.45 | H3: =SUMIFS(Tabla35[Abonos],Tabla35[Lote],B3,Tabla35[Cliente],C3,Tabla35[Concepto],"ABONO") -> 50461.45 | I3: =G3-H3 -> 0 | J3: ='BASE DATOS'!AF2 -> 117660.05 | K3: =SUMIFS(Tabla35[Abonos],Tabla35[Lote],B3,Tabla35[Cliente],C3,Tabla35[Concepto],"MULTIBANK") -> 117660.05 | L3: =J3-K3 -> 0 | M3: ='BASE DATOS'!AV2 -> 1600 | N3: =SUMIFS(Tabla35[Abonos],Tabla35[Lote],B3,Tabla35[Cliente],C3,Tabla35[Concepto],"GASTOS LEGALES") -> 1600 | O3: =M3-N3 -> 0 | P3: 500 | Q3: =SUMIFS(Tabla35[Abonos],Tabla35[Lote],B3,Tabla35[Cliente],C3,Tabla35[Concepto],"FONDO ADM") -> 500 | R3: =P3-Q3 -> 0 | S3: 300 | T3: =SUMIFS(Tabla35[Abonos],Tabla35[Lote],B3,Tabla35[Cliente],C3,Tabla35[Concepto],"MEDIDOR") -> 300 | U3: =S3-T3 -> 0 | W3: =SUMIFS(Tabla35[Abonos],Tabla35[Lote],B3,Tabla35[Cliente],C3,Tabla35[Concepto],"PENALIZACIÓN") -> 0 | X3: =V3-W3 -> 0
B4: L-502 | C4: ='BASE DATOS'!C3 -> LANCE Y RADANA MORGAN | D4: ='BASE DATOS'!AA3 -> 170000 | E4: =I4+L4 -> 0 | F4: =Tabla5[[#This Row],[PENDIENTE GISA]]+Tabla5[[#This Row],[PENDIENTE MULTIBANK]]+Tabla5[[#This Row],[PENDIENTE GASTOS LEGALES]]+Tabla5[[#This Row],[FONDO ADM PENDIENTE]]+Tabla5[[#This Row],[MEDIDOR PENDIENTE]]+Tabla5[[#This Row],[PENALIZACIÓN PENDIENTE]] -> 0 | G4: ='BASE DATOS'!AE3 -> 51000 | H4: =SUMIFS(Tabla35[Abonos],Tabla35[Lote],B4,Tabla35[Cliente],C4,Tabla35[Concepto],"ABONO") -> 51000 | I4: =G4-H4 -> 0 | J4: ='BASE DATOS'!AF3 -> 119000 | K4: =SUMIFS(Tabla35[Abonos],Tabla35[Lote],B4,Tabla35[Cliente],C4,Tabla35[Concepto],"MULTIBANK") -> 119000 | L4: =J4-K4 -> 0 | M4: ='BASE DATOS'!AV3 -> 1900 | N4: =SUMIFS(Tabla35[Abonos],Tabla35[Lote],B4,Tabla35[Cliente],C4,Tabla35[Concepto],"GASTOS LEGALES") -> 1900 | O4: =M4-N4 -> 0 | P4: 500 | Q4: =SUMIFS(Tabla35[Abonos],Tabla35[Lote],B4,Tabla35[Cliente],C4,Tabla35[Concepto],"FONDO ADM") -> 500 | R4: =P4-Q4 -> 0 | S4: 300 | T4: =SUMIFS(Tabla35[Abonos],Tabla35[Lote],B4,Tabla35[Cliente],C4,Tabla35[Concepto],"MEDIDOR") -> 300 | U4: =S4-T4 -> 0 | W4: =SUMIFS(Tabla35[Abonos],Tabla35[Lote],B4,Tabla35[Cliente],C4,Tabla35[Concepto],"PENALIZACIÓN") -> 0 | X4: =V4-W4 -> 0
B5: L-503 | C5: ='BASE DATOS'!C4 -> AARON Y MARSHA EDWARDS | D5: ='BASE DATOS'!AA4 -> 205107.09 | E5: =I5+L5 -> 0 | F5: =Tabla5[[#This Row],[PENDIENTE GISA]]+Tabla5[[#This Row],[PENDIENTE MULTIBANK]]+Tabla5[[#This Row],[PENDIENTE GASTOS LEGALES]]+Tabla5[[#This Row],[FONDO ADM PENDIENTE]]+Tabla5[[#This Row],[MEDIDOR PENDIENTE]]+Tabla5[[#This Row],[PENALIZACIÓN PENDIENTE]] -> 0 | G5: ='BASE DATOS'!AE4 -> 61532.13 | H5: =SUMIFS(Tabla35[Abonos],Tabla35[Lote],B5,Tabla35[Cliente],C5,Tabla35[Concepto],"ABONO") -> 61532.13 | I5: =G5-H5 -> 0 | J5: ='BASE DATOS'!AF4 -> 143574.96 | K5: =SUMIFS(Tabla35[Abonos],Tabla35[Lote],B5,Tabla35[Cliente],C5,Tabla35[Concepto],"MULTIBANK") -> 143574.96 | L5: =J5-K5 -> 0 | M5: ='BASE DATOS'!AV4 -> 5858.13 | N5: =SUMIFS(Tabla35[Abonos],Tabla35[Lote],B5,Tabla35[Cliente],C5,Tabla35[Concepto],"GASTOS LEGALES") -> 5858.13 | O5: =M5-N5 -> 0 | P5: 500 | Q5: =SUMIFS(Tabla35[Abonos],Tabla35[Lote],B5,Tabla35[Cliente],C5,Tabla35[Concepto],"FONDO ADM") -> 500 | R5: =P5-Q5 -> 0 | S5: 300 | T5: =SUMIFS(Tabla35[Abonos],Tabla35[Lote],B5,Tabla35[Cliente],C5,Tabla35[Concepto],"MEDIDOR") -> 300 | U5: =S5-T5 -> 0 | W5: =SUMIFS(Tabla35[Abonos],Tabla35[Lote],B5,Tabla35[Cliente],C5,Tabla35[Concepto],"PENALIZACIÓN") -> 0 | X5: =V5-W5 -> 0
B6: L-504 | C6: ='BASE DATOS'!C5 -> GEORGE WALES Y MAUZIE-LISA WALES | D6: ='BASE DATOS'!AA5 -> 204500 | E6: =I6+L6 -> -0.5 | F6: =Tabla5[[#This Row],[PENDIENTE GISA]]+Tabla5[[#This Row],[PENDIENTE MULTIBANK]]+Tabla5[[#This Row],[PENDIENTE GASTOS LEGALES]]+Tabla5[[#This Row],[FONDO ADM PENDIENTE]]+Tabla5[[#This Row],[MEDIDOR PENDIENTE]]+Tabla5[[#This Row],[PENALIZACIÓN PENDIENTE]] -> -0.5 | G6: ='BASE DATOS'!AE5 -> 204500 | H6: =SUMIFS(Tabla35[Abonos],Tabla35[Lote],B6,Tabla35[Cliente],C6,Tabla35[Concepto],"ABONO") -> 204500.5 | I6: =G6-H6 -> -0.5 | J6: ='BASE DATOS'!AF5 -> 0 | K6: =SUMIFS(Tabla35[Abonos],Tabla35[Lote],B6,Tabla35[Cliente],C6,Tabla35[Concepto],"MULTIBANK") -> 0 | L6: =J6-K6 -> 0 | M6: ='BASE DATOS'!AV5 -> 2070 | N6: =SUMIFS(Tabla35[Abonos],Tabla35[Lote],B6,Tabla35[Cliente],C6,Tabla35[Concepto],"GASTOS LEGALES") -> 2070 | O6: =M6-N6 -> 0 | P6: 500 | Q6: =SUMIFS(Tabla35[Abonos],Tabla35[Lote],B6,Tabla35[Cliente],C6,Tabla35[Concepto],"FONDO ADM") -> 500 | R6: =P6-Q6 -> 0 | S6: 300 | T6: =SUMIFS(Tabla35[Abonos],Tabla35[Lote],B6,Tabla35[Cliente],C6,Tabla35[Concepto],"MEDIDOR") -> 300 | U6: =S6-T6 -> 0 | W6: =SUMIFS(Tabla35[Abonos],Tabla35[Lote],B6,Tabla35[Cliente],C6,Tabla35[Concepto],"PENALIZACIÓN") -> 0 | X6: =V6-W6 -> 0
B7: L-505 | C7: ='BASE DATOS'!C6 -> ALCIBIADES SOLIS | D7: ='BASE DATOS'!AA6 -> 186379.5 | E7: =I7+L7 -> 0 | F7: =Tabla5[[#This Row],[PENDIENTE GISA]]+Tabla5[[#This Row],[PENDIENTE MULTIBANK]]+Tabla5[[#This Row],[PENDIENTE GASTOS LEGALES]]+Tabla5[[#This Row],[FONDO ADM PENDIENTE]]+Tabla5[[#This Row],[MEDIDOR PENDIENTE]]+Tabla5[[#This Row],[PENALIZACIÓN PENDIENTE]] -> 0 | G7: ='BASE DATOS'!AE6 -> 55913.85 | H7: =SUMIFS(Tabla35[Abonos],Tabla35[Lote],B7,Tabla35[Cliente],C7,Tabla35[Concepto],"ABONO") -> 55913.85 | I7: =G7-H7 -> 0 | J7: ='BASE DATOS'!AF6 -> 130465.65 | K7: =SUMIFS(Tabla35[Abonos],Tabla35[Lote],B7,Tabla35[Cliente],C7,Tabla35[Concepto],"MULTIBANK") -> 130465.65 | L7: =J7-K7 -> 0 | M7: ='BASE DATOS'!AV6 -> 1400 | N7: =SUMIFS(Tabla35[Abonos],Tabla35[Lote],B7,Tabla35[Cliente],C7,Tabla35[Concepto],"GASTOS LEGALES") -> 1400 | O7: =M7-N7 -> 0 | P7: 500 | Q7: =SUMIFS(Tabla35[Abonos],Tabla35[Lote],B7,Tabla35[Cliente],C7,Tabla35[Concepto],"FONDO ADM") -> 500 | R7: =P7-Q7 -> 0 | S7: 300 | T7: =SUMIFS(Tabla35[Abonos],Tabla35[Lote],B7,Tabla35[Cliente],C7,Tabla35[Concepto],"MEDIDOR") -> 300 | U7: =S7-T7 -> 0 | W7: =SUMIFS(Tabla35[Abonos],Tabla35[Lote],B7,Tabla35[Cliente],C7,Tabla35[Concepto],"PENALIZACIÓN") -> 0 | X7: =V7-W7 -> 0
B8: L-506 | C8: ='BASE DATOS'!C7 -> ERIC WHITAKER | D8: ='BASE DATOS'!AA7 -> 209100 | E8: =I8+L8 -> 0 | F8: =Tabla5[[#This Row],[PENDIENTE GISA]]+Tabla5[[#This Row],[PENDIENTE MULTIBANK]]+Tabla5[[#This Row],[PENDIENTE GASTOS LEGALES]]+Tabla5[[#This Row],[FONDO ADM PENDIENTE]]+Tabla5[[#This Row],[MEDIDOR PENDIENTE]]+Tabla5[[#This Row],[PENALIZACIÓN PENDIENTE]] -> 300 | G8: ='BASE DATOS'!AE7 -> 209100 | H8: =SUMIFS(Tabla35[Abonos],Tabla35[Lote],B8,Tabla35[Cliente],C8,Tabla35[Concepto],"ABONO") -> 209100 | I8: =G8-H8 -> 0 | J8: ='BASE DATOS'!AF7 -> 0 | K8: =SUMIFS(Tabla35[Abonos],Tabla35[Lote],B8,Tabla35[Cliente],C8,Tabla35[Concepto],"MULTIBANK") -> 0 | L8: =J8-K8 -> 0 | M8: ='BASE DATOS'!AV7 -> 3427.6 | N8: =SUMIFS(Tabla35[Abonos],Tabla35[Lote],B8,Tabla35[Cliente],C8,Tabla35[Concepto],"GASTOS LEGALES") -> 3427.6 | O8: =M8-N8 -> 0 | P8: 500 | Q8: =SUMIFS(Tabla35[Abonos],Tabla35[Lote],B8,Tabla35[Cliente],C8,Tabla35[Concepto],"FONDO ADM") -> 500 | R8: =P8-Q8 -> 0 | S8: 300 | T8: =SUMIFS(Tabla35[Abonos],Tabla35[Lote],B8,Tabla35[Cliente],C8,Tabla35[Concepto],"MEDIDOR") -> 0 | U8: =S8-T8 -> 300 | W8: =SUMIFS(Tabla35[Abonos],Tabla35[Lote],B8,Tabla35[Cliente],C8,Tabla35[Concepto],"PENALIZACIÓN") -> 0 | X8: =V8-W8 -> 0
B9: L-507 | C9: ='BASE DATOS'!C8 -> BRUNO LA GROTTA | D9: ='BASE DATOS'!AA8 -> 270000 | E9: =I9+L9 -> 0 | F9: =Tabla5[[#This Row],[PENDIENTE GISA]]+Tabla5[[#This Row],[PENDIENTE MULTIBANK]]+Tabla5[[#This Row],[PENDIENTE GASTOS LEGALES]]+Tabla5[[#This Row],[FONDO ADM PENDIENTE]]+Tabla5[[#This Row],[MEDIDOR PENDIENTE]]+Tabla5[[#This Row],[PENALIZACIÓN PENDIENTE]] -> 0 | G9: ='BASE DATOS'!AE8 -> 116000 | H9: =SUMIFS(Tabla35[Abonos],Tabla35[Lote],B9,Tabla35[Cliente],C9,Tabla35[Concepto],"ABONO") -> 116000 | I9: =G9-H9 -> 0 | J9: ='BASE DATOS'!AF8 -> 154000 | K9: =SUMIFS(Tabla35[Abonos],Tabla35[Lote],B9,Tabla35[Cliente],C9,Tabla35[Concepto],"MULTIBANK") -> 154000 | L9: =J9-K9 -> 0 | M9: ='BASE DATOS'!AV8 -> 1950 | N9: =SUMIFS(Tabla35[Abonos],Tabla35[Lote],B9,Tabla35[Cliente],C9,Tabla35[Concepto],"GASTOS LEGALES") -> 1950 | O9: =M9-N9 -> 0 | P9: 500 | Q9: =SUMIFS(Tabla35[Abonos],Tabla35[Lote],B9,Tabla35[Cliente],C9,Tabla35[Concepto],"FONDO ADM") -> 500 | R9: =P9-Q9 -> 0 | S9: 300 | T9: =SUMIFS(Tabla35[Abonos],Tabla35[Lote],B9,Tabla35[Cliente],C9,Tabla35[Concepto],"MEDIDOR") -> 300 | U9: =S9-T9 -> 0 | W9: =SUMIFS(Tabla35[Abonos],Tabla35[Lote],B9,Tabla35[Cliente],C9,Tabla35[Concepto],"PENALIZACIÓN") -> 0 | X9: =V9-W9 -> 0
B10: L-508 | C10: ='BASE DATOS'!C9 -> PAUL Y RENATE MIANO | D10: ='BASE DATOS'!AA9 -> 278683.5 | E10: =I10+L10 -> 0 | F10: =Tabla5[[#This Row],[PENDIENTE GISA]]+Tabla5[[#This Row],[PENDIENTE MULTIBANK]]+Tabla5[[#This Row],[PENDIENTE GASTOS LEGALES]]+Tabla5[[#This Row],[FONDO ADM PENDIENTE]]+Tabla5[[#This Row],[MEDIDOR PENDIENTE]]+Tabla5[[#This Row],[PENALIZACIÓN PENDIENTE]] -> 0 | G10: ='BASE DATOS'!AE9 -> 83592 | H10: =SUMIFS(Tabla35[Abonos],Tabla35[Lote],B10,Tabla35[Cliente],C10,Tabla35[Concepto],"ABONO") -> 83592 | I10: =G10-H10 -> 0 | J10: ='BASE DATOS'!AF9 -> 195091.5 | K10: =SUMIFS(Tabla35[Abonos],Tabla35[Lote],B10,Tabla35[Cliente],C10,Tabla35[Concepto],"MULTIBANK") -> 195091.5 | L10: =J10-K10 -> 0 | M10: ='BASE DATOS'!AV9 -> 1950 | N10: =SUMIFS(Tabla35[Abonos],Tabla35[Lote],B10,Tabla35[Cliente],C10,Tabla35[Concepto],"GASTOS LEGALES") -> 1950 | O10: =M10-N10 -> 0 | P10: 500 | Q10: =SUMIFS(Tabla35[Abonos],Tabla35[Lote],B10,Tabla35[Cliente],C10,Tabla35[Concepto],"FONDO ADM") -> 500 | R10: =P10-Q10 -> 0 | S10: 300 | T10: =SUMIFS(Tabla35[Abonos],Tabla35[Lote],B10,Tabla35[Cliente],C10,Tabla35[Concepto],"MEDIDOR") -> 300 | U10: =S10-T10 -> 0 | W10: =SUMIFS(Tabla35[Abonos],Tabla35[Lote],B10,Tabla35[Cliente],C10,Tabla35[Concepto],"PENALIZACIÓN") -> 0 | X10: =V10-W10 -> 0
B11: L-509 | C11: ='BASE DATOS'!C10 -> DAYANARA RÍOS | D11: ='BASE DATOS'!AA10 -> 186379.5 | E11: =I11+L11 -> 0 | F11: =Tabla5[[#This Row],[PENDIENTE GISA]]+Tabla5[[#This Row],[PENDIENTE MULTIBANK]]+Tabla5[[#This Row],[PENDIENTE GASTOS LEGALES]]+Tabla5[[#This Row],[FONDO ADM PENDIENTE]]+Tabla5[[#This Row],[MEDIDOR PENDIENTE]]+Tabla5[[#This Row],[PENALIZACIÓN PENDIENTE]] -> 0 | G11: ='BASE DATOS'!AE10 -> 37275.9 | H11: =SUMIFS(Tabla35[Abonos],Tabla35[Lote],B11,Tabla35[Cliente],C11,Tabla35[Concepto],"ABONO") -> 37275.9 | I11: =G11-H11 -> 0 | J11: ='BASE DATOS'!AF10 -> 149103.6 | K11: =SUMIFS(Tabla35[Abonos],Tabla35[Lote],B11,Tabla35[Cliente],C11,Tabla35[Concepto],"MULTIBANK") -> 149103.6 | L11: =J11-K11 -> 0 | M11: 0 | N11: =SUMIFS(Tabla35[Abonos],Tabla35[Lote],B11,Tabla35[Cliente],C11,Tabla35[Concepto],"GASTOS LEGALES") -> 0 | O11: =M11-N11 -> 0 | P11: 500 | Q11: =SUMIFS(Tabla35[Abonos],Tabla35[Lote],B11,Tabla35[Cliente],C11,Tabla35[Concepto],"FONDO ADM") -> 500 | R11: =P11-Q11 -> 0 | S11: 300 | T11: =SUMIFS(Tabla35[Abonos],Tabla35[Lote],B11,Tabla35[Cliente],C11,Tabla35[Concepto],"MEDIDOR") -> 300 | U11: =S11-T11 -> 0 | W11: =SUMIFS(Tabla35[Abonos],Tabla35[Lote],B11,Tabla35[Cliente],C11,Tabla35[Concepto],"PENALIZACIÓN") -> 0 | X11: =V11-W11 -> 0
B12: L-510 | C12: ='BASE DATOS'!C11 -> NICHOLAS CHILLEMI | D12: ='BASE DATOS'!AA11 -> 150000 | E12: =I12+L12 -> 0 | F12: =Tabla5[[#This Row],[PENDIENTE GISA]]+Tabla5[[#This Row],[PENDIENTE MULTIBANK]]+Tabla5[[#This Row],[PENDIENTE GASTOS LEGALES]]+Tabla5[[#This Row],[FONDO ADM PENDIENTE]]+Tabla5[[#This Row],[MEDIDOR PENDIENTE]]+Tabla5[[#This Row],[PENALIZACIÓN PENDIENTE]] -> 0 | G12: ='BASE DATOS'!AE11 -> 45000 | H12: =SUMIFS(Tabla35[Abonos],Tabla35[Lote],B12,Tabla35[Cliente],C12,Tabla35[Concepto],"ABONO") -> 45000 | I12: =G12-H12 -> 0 | J12: ='BASE DATOS'!AF11 -> 105000 | K12: =SUMIFS(Tabla35[Abonos],Tabla35[Lote],B12,Tabla35[Cliente],C12,Tabla35[Concepto],"MULTIBANK") -> 105000 | L12: =J12-K12 -> 0 | M12: ='BASE DATOS'!AV11 -> 1525 | N12: =SUMIFS(Tabla35[Abonos],Tabla35[Lote],B12,Tabla35[Cliente],C12,Tabla35[Concepto],"GASTOS LEGALES") -> 1525 | O12: =M12-N12 -> 0 | P12: 500 | Q12: =SUMIFS(Tabla35[Abonos],Tabla35[Lote],B12,Tabla35[Cliente],C12,Tabla35[Concepto],"FONDO ADM") -> 500 | R12: =P12-Q12 -> 0 | S12: 300 | T12: =SUMIFS(Tabla35[Abonos],Tabla35[Lote],B12,Tabla35[Cliente],C12,Tabla35[Concepto],"MEDIDOR") -> 300 | U12: =S12-T12 -> 0 | W12: =SUMIFS(Tabla35[Abonos],Tabla35[Lote],B12,Tabla35[Cliente],C12,Tabla35[Concepto],"PENALIZACIÓN") -> 0 | X12: =V12-W12 -> 0
B13: L-511 | C13: ='BASE DATOS'!C12 -> JEANETTE MUNROE | D13: ='BASE DATOS'!AA12 -> 168121.5 | E13: =I13+L13 -> 0 | F13: =Tabla5[[#This Row],[PENDIENTE GISA]]+Tabla5[[#This Row],[PENDIENTE MULTIBANK]]+Tabla5[[#This Row],[PENDIENTE GASTOS LEGALES]]+Tabla5[[#This Row],[FONDO ADM PENDIENTE]]+Tabla5[[#This Row],[MEDIDOR PENDIENTE]]+Tabla5[[#This Row],[PENALIZACIÓN PENDIENTE]] -> 0 | G13: ='BASE DATOS'!AE12 -> 58842.525 | H13: =SUMIFS(Tabla35[Abonos],Tabla35[Lote],B13,Tabla35[Cliente],C13,Tabla35[Concepto],"ABONO") -> 58842.525 | I13: =G13-H13 -> 0 | J13: ='BASE DATOS'!AF12 -> 109278.98 | K13: =SUMIFS(Tabla35[Abonos],Tabla35[Lote],B13,Tabla35[Cliente],C13,Tabla35[Concepto],"MULTIBANK") -> 109278.98 | L13: =J13-K13 -> 0 | M13: ='BASE DATOS'!AV12 -> 1600 | N13: =SUMIFS(Tabla35[Abonos],Tabla35[Lote],B13,Tabla35[Cliente],C13,Tabla35[Concepto],"GASTOS LEGALES") -> 1600 | O13: =M13-N13 -> 0 | P13: 500 | Q13: =SUMIFS(Tabla35[Abonos],Tabla35[Lote],B13,Tabla35[Cliente],C13,Tabla35[Concepto],"FONDO ADM") -> 500 | R13: =P13-Q13 -> 0 | S13: 300 | T13: =SUMIFS(Tabla35[Abonos],Tabla35[Lote],B13,Tabla35[Cliente],C13,Tabla35[Concepto],"MEDIDOR") -> 300 | U13: =S13-T13 -> 0 | W13: =SUMIFS(Tabla35[Abonos],Tabla35[Lote],B13,Tabla35[Cliente],C13,Tabla35[Concepto],"PENALIZACIÓN") -> 0 | X13: =V13-W13 -> 0
B14: L-401 | C14: ='BASE DATOS'!C13 -> ROBERT RODRIGUEZ | D14: ='BASE DATOS'!AA13 -> 160000 | E14: =I14+L14 -> 0 | F14: =Tabla5[[#This Row],[PENDIENTE GISA]]+Tabla5[[#This Row],[PENDIENTE MULTIBANK]]+Tabla5[[#This Row],[PENDIENTE GASTOS LEGALES]]+Tabla5[[#This Row],[FONDO ADM PENDIENTE]]+Tabla5[[#This Row],[MEDIDOR PENDIENTE]]+Tabla5[[#This Row],[PENALIZACIÓN PENDIENTE]] -> 300 | G14: ='BASE DATOS'!AE13 -> 56000 | H14: =SUMIFS(Tabla35[Abonos],Tabla35[Lote],B14,Tabla35[Cliente],C14,Tabla35[Concepto],"ABONO") -> 56000 | I14: =G14-H14 -> 0 | J14: ='BASE DATOS'!AF13 -> 104000 | K14: =SUMIFS(Tabla35[Abonos],Tabla35[Lote],B14,Tabla35[Cliente],C14,Tabla35[Concepto],"MULTIBANK") -> 104000 | L14: =J14-K14 -> 0 | M14: 0 | N14: =SUMIFS(Tabla35[Abonos],Tabla35[Lote],B14,Tabla35[Cliente],C14,Tabla35[Concepto],"GASTOS LEGALES") -> 0 | O14: =M14-N14 -> 0 | P14: 500 | Q14: =SUMIFS(Tabla35[Abonos],Tabla35[Lote],B14,Tabla35[Cliente],C14,Tabla35[Concepto],"FONDO ADM") -> 500 | R14: =P14-Q14 -> 0 | S14: 300 | T14: =SUMIFS(Tabla35[Abonos],Tabla35[Lote],B14,Tabla35[Cliente],C14,Tabla35[Concepto],"MEDIDOR") -> 0 | U14: =S14-T14 -> 300 | W14: =SUMIFS(Tabla35[Abonos],Tabla35[Lote],B14,Tabla35[Cliente],C14,Tabla35[Concepto],"PENALIZACIÓN") -> 0 | X14: =V14-W14 -> 0
B15: L-402 | C15: ='BASE DATOS'!C14 -> EDGAR UREÑA | D15: ='BASE DATOS'!AA14 -> 152500 | E15: =I15+L15 -> 0 | F15: =Tabla5[[#This Row],[PENDIENTE GISA]]+Tabla5[[#This Row],[PENDIENTE MULTIBANK]]+Tabla5[[#This Row],[PENDIENTE GASTOS LEGALES]]+Tabla5[[#This Row],[FONDO ADM PENDIENTE]]+Tabla5[[#This Row],[MEDIDOR PENDIENTE]]+Tabla5[[#This Row],[PENALIZACIÓN PENDIENTE]] -> 0 | G15: ='BASE DATOS'!AE14 -> 30500 | H15: =SUMIFS(Tabla35[Abonos],Tabla35[Lote],B15,Tabla35[Cliente],C15,Tabla35[Concepto],"ABONO") -> 30500 | I15: =G15-H15 -> 0 | J15: ='BASE DATOS'!AF14 -> 122000 | K15: =SUMIFS(Tabla35[Abonos],Tabla35[Lote],B15,Tabla35[Cliente],C15,Tabla35[Concepto],"MULTIBANK") -> 122000 | L15: =J15-K15 -> 0 | M15: 0 | N15: =SUMIFS(Tabla35[Abonos],Tabla35[Lote],B15,Tabla35[Cliente],C15,Tabla35[Concepto],"GASTOS LEGALES") -> 0 | O15: =M15-N15 -> 0 | P15: 500 | Q15: =SUMIFS(Tabla35[Abonos],Tabla35[Lote],B15,Tabla35[Cliente],C15,Tabla35[Concepto],"FONDO ADM") -> 500 | R15: =P15-Q15 -> 0 | S15: 300 | T15: =SUMIFS(Tabla35[Abonos],Tabla35[Lote],B15,Tabla35[Cliente],C15,Tabla35[Concepto],"MEDIDOR") -> 300 | U15: =S15-T15 -> 0 | W15: =SUMIFS(Tabla35[Abonos],Tabla35[Lote],B15,Tabla35[Cliente],C15,Tabla35[Concepto],"PENALIZACIÓN") -> 0 | X15: =V15-W15 -> 0
B16: L-403 | C16: ='BASE DATOS'!C15 -> CARLOS ARAGON / MILAINE DOMINGUEZ | D16: ='BASE DATOS'!AA15 -> 185270 | E16: =I16+L16 -> 123214.08 | F16: =Tabla5[[#This Row],[PENDIENTE GISA]]+Tabla5[[#This Row],[PENDIENTE MULTIBANK]]+Tabla5[[#This Row],[PENDIENTE GASTOS LEGALES]]+Tabla5[[#This Row],[FONDO ADM PENDIENTE]]+Tabla5[[#This Row],[MEDIDOR PENDIENTE]]+Tabla5[[#This Row],[PENALIZACIÓN PENDIENTE]] -> 128214.08 | G16: ='BASE DATOS'!AE15 -> 185270 | H16: =SUMIFS(Tabla35[Abonos],Tabla35[Lote],B16,Tabla35[Cliente],C16,Tabla35[Concepto],"ABONO") -> 62055.92 | I16: =G16-H16 -> 123214.08 | J16: ='BASE DATOS'!AF15 -> 0 | K16: =SUMIFS(Tabla35[Abonos],Tabla35[Lote],B16,Tabla35[Cliente],C16,Tabla35[Concepto],"MULTIBANK") -> 0 | L16: =J16-K16 -> 0 | M16: ='BASE DATOS'!AV15 -> 0 | N16: =SUMIFS(Tabla35[Abonos],Tabla35[Lote],B16,Tabla35[Cliente],C16,Tabla35[Concepto],"GASTOS LEGALES") -> 0 | O16: =M16-N16 -> 0 | P16: 500 | Q16: =SUMIFS(Tabla35[Abonos],Tabla35[Lote],B16,Tabla35[Cliente],C16,Tabla35[Concepto],"FONDO ADM") -> 500 | R16: =P16-Q16 -> 0 | S16: 300 | T16: =SUMIFS(Tabla35[Abonos],Tabla35[Lote],B16,Tabla35[Cliente],C16,Tabla35[Concepto],"MEDIDOR") -> 300 | U16: =S16-T16 -> 0 | V16: 5000 | W16: =SUMIFS(Tabla35[Abonos],Tabla35[Lote],B16,Tabla35[Cliente],C16,Tabla35[Concepto],"PENALIZACIÓN") -> 0 | X16: =V16-W16 -> 5000
B17: L-404 | C17: ='BASE DATOS'!C16 -> VERA ANN MATTHEWS / RUDOLF MATTHEWS | D17: ='BASE DATOS'!AA16 -> 191892.6 | E17: =I17+L17 -> 0 | F17: =Tabla5[[#This Row],[PENDIENTE GISA]]+Tabla5[[#This Row],[PENDIENTE MULTIBANK]]+Tabla5[[#This Row],[PENDIENTE GASTOS LEGALES]]+Tabla5[[#This Row],[FONDO ADM PENDIENTE]]+Tabla5[[#This Row],[MEDIDOR PENDIENTE]]+Tabla5[[#This Row],[PENALIZACIÓN PENDIENTE]] -> 300 | G17: ='BASE DATOS'!AE16 -> 63751.65 | H17: =SUMIFS(Tabla35[Abonos],Tabla35[Lote],B17,Tabla35[Cliente],C17,Tabla35[Concepto],"ABONO") -> 63751.65 | I17: =G17-H17 -> 0 | J17: ='BASE DATOS'!AF16 -> 128140.95 | K17: =SUMIFS(Tabla35[Abonos],Tabla35[Lote],B17,Tabla35[Cliente],C17,Tabla35[Concepto],"MULTIBANK") -> 128140.95 | L17: =J17-K17 -> 0 | M17: 0 | N17: =SUMIFS(Tabla35[Abonos],Tabla35[Lote],B17,Tabla35[Cliente],C17,Tabla35[Concepto],"GASTOS LEGALES") -> 0 | O17: =M17-N17 -> 0 | P17: 500 | Q17: =SUMIFS(Tabla35[Abonos],Tabla35[Lote],B17,Tabla35[Cliente],C17,Tabla35[Concepto],"FONDO ADM") -> 500 | R17: =P17-Q17 -> 0 | S17: 300 | T17: =SUMIFS(Tabla35[Abonos],Tabla35[Lote],B17,Tabla35[Cliente],C17,Tabla35[Concepto],"MEDIDOR") -> 0 | U17: =S17-T17 -> 300 | W17: =SUMIFS(Tabla35[Abonos],Tabla35[Lote],B17,Tabla35[Cliente],C17,Tabla35[Concepto],"PENALIZACIÓN") -> 0 | X17: =V17-W17 -> 0
B18: L-405 | C18: ='BASE DATOS'!C17 -> GABRIEL DIAZ / NURIA CASTILLO | D18: ='BASE DATOS'!AA17 -> 180000 | E18: =I18+L18 -> 0 | F18: =Tabla5[[#This Row],[PENDIENTE GISA]]+Tabla5[[#This Row],[PENDIENTE MULTIBANK]]+Tabla5[[#This Row],[PENDIENTE GASTOS LEGALES]]+Tabla5[[#This Row],[FONDO ADM PENDIENTE]]+Tabla5[[#This Row],[MEDIDOR PENDIENTE]]+Tabla5[[#This Row],[PENALIZACIÓN PENDIENTE]] -> 0 | G18: ='BASE DATOS'!AE17 -> 50000 | H18: =SUMIFS(Tabla35[Abonos],Tabla35[Lote],B18,Tabla35[Cliente],C18,Tabla35[Concepto],"ABONO") -> 50000 | I18: =G18-H18 -> 0 | J18: ='BASE DATOS'!AF17 -> 130000 | K18: =SUMIFS(Tabla35[Abonos],Tabla35[Lote],B18,Tabla35[Cliente],C18,Tabla35[Concepto],"MULTIBANK") -> 130000 | L18: =J18-K18 -> 0 | M18: 0 | N18: =SUMIFS(Tabla35[Abonos],Tabla35[Lote],B18,Tabla35[Cliente],C18,Tabla35[Concepto],"GASTOS LEGALES") -> 0 | O18: =M18-N18 -> 0 | P18: 500 | Q18: =SUMIFS(Tabla35[Abonos],Tabla35[Lote],B18,Tabla35[Cliente],C18,Tabla35[Concepto],"FONDO ADM") -> 500 | R18: =P18-Q18 -> 0 | S18: 300 | T18: =SUMIFS(Tabla35[Abonos],Tabla35[Lote],B18,Tabla35[Cliente],C18,Tabla35[Concepto],"MEDIDOR") -> 300 | U18: =S18-T18 -> 0 | W18: =SUMIFS(Tabla35[Abonos],Tabla35[Lote],B18,Tabla35[Cliente],C18,Tabla35[Concepto],"PENALIZACIÓN") -> 0 | X18: =V18-W18 -> 0
B19: L-406 | C19: ='BASE DATOS'!C18 -> JOHN ESTRELLA / MARIA ESTRELLA | D19: ='BASE DATOS'!AA18 -> 205422.3 | E19: =I19+L19 -> 0 | F19: =Tabla5[[#This Row],[PENDIENTE GISA]]+Tabla5[[#This Row],[PENDIENTE MULTIBANK]]+Tabla5[[#This Row],[PENDIENTE GASTOS LEGALES]]+Tabla5[[#This Row],[FONDO ADM PENDIENTE]]+Tabla5[[#This Row],[MEDIDOR PENDIENTE]]+Tabla5[[#This Row],[PENALIZACIÓN PENDIENTE]] -> 0 | G19: ='BASE DATOS'!AE18 -> 61626.69 | H19: =SUMIFS(Tabla35[Abonos],Tabla35[Lote],B19,Tabla35[Cliente],C19,Tabla35[Concepto],"ABONO") -> 61626.69 | I19: =G19-H19 -> 0 | J19: ='BASE DATOS'!AF18 -> 143795.61 | K19: =SUMIFS(Tabla35[Abonos],Tabla35[Lote],B19,Tabla35[Cliente],C19,Tabla35[Concepto],"MULTIBANK") -> 143795.61 | L19: =J19-K19 -> 0 | M19: ='BASE DATOS'!AV18 -> 1805 | N19: =SUMIFS(Tabla35[Abonos],Tabla35[Lote],B19,Tabla35[Cliente],C19,Tabla35[Concepto],"GASTOS LEGALES") -> 1805 | O19: =M19-N19 -> 0 | P19: 500 | Q19: =SUMIFS(Tabla35[Abonos],Tabla35[Lote],B19,Tabla35[Cliente],C19,Tabla35[Concepto],"FONDO ADM") -> 500 | R19: =P19-Q19 -> 0 | S19: 300 | T19: =SUMIFS(Tabla35[Abonos],Tabla35[Lote],B19,Tabla35[Cliente],C19,Tabla35[Concepto],"MEDIDOR") -> 300 | U19: =S19-T19 -> 0 | W19: =SUMIFS(Tabla35[Abonos],Tabla35[Lote],B19,Tabla35[Cliente],C19,Tabla35[Concepto],"PENALIZACIÓN") -> 0 | X19: =V19-W19 -> 0
B20: L-407 | C20: ='BASE DATOS'!C19 -> LEO MC DONOUGH / JODI ELLIOT | D20: ='BASE DATOS'!AA19 -> 299000 | E20: =I20+L20 -> 0 | F20: =Tabla5[[#This Row],[PENDIENTE GISA]]+Tabla5[[#This Row],[PENDIENTE MULTIBANK]]+Tabla5[[#This Row],[PENDIENTE GASTOS LEGALES]]+Tabla5[[#This Row],[FONDO ADM PENDIENTE]]+Tabla5[[#This Row],[MEDIDOR PENDIENTE]]+Tabla5[[#This Row],[PENALIZACIÓN PENDIENTE]] -> 0 | G20: ='BASE DATOS'!AE19 -> 89700 | H20: =SUMIFS(Tabla35[Abonos],Tabla35[Lote],B20,Tabla35[Cliente],C20,Tabla35[Concepto],"ABONO") -> 89700 | I20: =G20-H20 -> 0 | J20: ='BASE DATOS'!AF19 -> 209300 | K20: =SUMIFS(Tabla35[Abonos],Tabla35[Lote],B20,Tabla35[Cliente],C20,Tabla35[Concepto],"MULTIBANK") -> 209300 | L20: =J20-K20 -> 0 | M20: ='BASE DATOS'!AV19 -> 1967 | N20: =SUMIFS(Tabla35[Abonos],Tabla35[Lote],B20,Tabla35[Cliente],C20,Tabla35[Concepto],"GASTOS LEGALES") -> 1967 | O20: =M20-N20 -> 0 | P20: 500 | Q20: =SUMIFS(Tabla35[Abonos],Tabla35[Lote],B20,Tabla35[Cliente],C20,Tabla35[Concepto],"FONDO ADM") -> 500 | R20: =P20-Q20 -> 0 | S20: 300 | T20: =SUMIFS(Tabla35[Abonos],Tabla35[Lote],B20,Tabla35[Cliente],C20,Tabla35[Concepto],"MEDIDOR") -> 300 | U20: =S20-T20 -> 0 | W20: =SUMIFS(Tabla35[Abonos],Tabla35[Lote],B20,Tabla35[Cliente],C20,Tabla35[Concepto],"PENALIZACIÓN") -> 0 | X20: =V20-W20 -> 0
B21: L-408 | C21: ='BASE DATOS'!C20 -> CONSTRUA INTERNATIONAL | D21: ='BASE DATOS'!AA20 -> 250000 | E21: =I21+L21 -> 0 | F21: =Tabla5[[#This Row],[PENDIENTE GISA]]+Tabla5[[#This Row],[PENDIENTE MULTIBANK]]+Tabla5[[#This Row],[PENDIENTE GASTOS LEGALES]]+Tabla5[[#This Row],[FONDO ADM PENDIENTE]]+Tabla5[[#This Row],[MEDIDOR PENDIENTE]]+Tabla5[[#This Row],[PENALIZACIÓN PENDIENTE]] -> 800 | G21: ='BASE DATOS'!AE20 -> 250000 | H21: =SUMIFS(Tabla35[Abonos],Tabla35[Lote],B21,Tabla35[Cliente],C21,Tabla35[Concepto],"ABONO") -> 250000 | I21: =G21-H21 -> 0 | J21: ='BASE DATOS'!AF20 -> 0 | K21: =SUMIFS(Tabla35[Abonos],Tabla35[Lote],B21,Tabla35[Cliente],C21,Tabla35[Concepto],"MULTIBANK") -> 0 | L21: =J21-K21 -> 0 | M21: ='BASE DATOS'!AV20 -> 2078 | N21: =SUMIFS(Tabla35[Abonos],Tabla35[Lote],B21,Tabla35[Cliente],C21,Tabla35[Concepto],"GASTOS LEGALES") -> 2078 | O21: =M21-N21 -> 0 | P21: 500 | Q21: =SUMIFS(Tabla35[Abonos],Tabla35[Lote],B21,Tabla35[Cliente],C21,Tabla35[Concepto],"FONDO ADM") -> 0 | R21: =P21-Q21 -> 500 | S21: 300 | T21: =SUMIFS(Tabla35[Abonos],Tabla35[Lote],B21,Tabla35[Cliente],C21,Tabla35[Concepto],"MEDIDOR") -> 0 | U21: =S21-T21 -> 300 | W21: =SUMIFS(Tabla35[Abonos],Tabla35[Lote],B21,Tabla35[Cliente],C21,Tabla35[Concepto],"PENALIZACIÓN") -> 0 | X21: =V21-W21 -> 0
B22: L-409 | C22: ='BASE DATOS'!C21 -> BOJAN MALISEVIC / ZORAN MALISEVIC | D22: ='BASE DATOS'!AA21 -> 205000 | E22: =I22+L22 -> 0 | F22: =Tabla5[[#This Row],[PENDIENTE GISA]]+Tabla5[[#This Row],[PENDIENTE MULTIBANK]]+Tabla5[[#This Row],[PENDIENTE GASTOS LEGALES]]+Tabla5[[#This Row],[FONDO ADM PENDIENTE]]+Tabla5[[#This Row],[MEDIDOR PENDIENTE]]+Tabla5[[#This Row],[PENALIZACIÓN PENDIENTE]] -> 0 | G22: ='BASE DATOS'!AE21 -> 155000 | H22: =SUMIFS(Tabla35[Abonos],Tabla35[Lote],B22,Tabla35[Cliente],C22,Tabla35[Concepto],"ABONO") -> 155000 | I22: =G22-H22 -> 0 | J22: ='BASE DATOS'!AF21 -> 50000 | K22: =SUMIFS(Tabla35[Abonos],Tabla35[Lote],B22,Tabla35[Cliente],C22,Tabla35[Concepto],"MULTIBANK") -> 50000 | L22: =J22-K22 -> 0 | M22: ='BASE DATOS'!AV21 -> 1900 | N22: =SUMIFS(Tabla35[Abonos],Tabla35[Lote],B22,Tabla35[Cliente],C22,Tabla35[Concepto],"GASTOS LEGALES") -> 1900 | O22: =M22-N22 -> 0 | P22: 500 | Q22: =SUMIFS(Tabla35[Abonos],Tabla35[Lote],B22,Tabla35[Cliente],C22,Tabla35[Concepto],"FONDO ADM") -> 500 | R22: =P22-Q22 -> 0 | S22: 300 | T22: =SUMIFS(Tabla35[Abonos],Tabla35[Lote],B22,Tabla35[Cliente],C22,Tabla35[Concepto],"MEDIDOR") -> 300 | U22: =S22-T22 -> 0 | W22: =SUMIFS(Tabla35[Abonos],Tabla35[Lote],B22,Tabla35[Cliente],C22,Tabla35[Concepto],"PENALIZACIÓN") -> 0 | X22: =V22-W22 -> 0
B23: L-410 | C23: ='BASE DATOS'!C22 -> MICHAEL BELANGER | D23: ='BASE DATOS'!AA22 -> 146853 | E23: =I23+L23 -> 0 | F23: =Tabla5[[#This Row],[PENDIENTE GISA]]+Tabla5[[#This Row],[PENDIENTE MULTIBANK]]+Tabla5[[#This Row],[PENDIENTE GASTOS LEGALES]]+Tabla5[[#This Row],[FONDO ADM PENDIENTE]]+Tabla5[[#This Row],[MEDIDOR PENDIENTE]]+Tabla5[[#This Row],[PENALIZACIÓN PENDIENTE]] -> 0 | G23: ='BASE DATOS'!AE22 -> 44055.9 | H23: =SUMIFS(Tabla35[Abonos],Tabla35[Lote],B23,Tabla35[Cliente],C23,Tabla35[Concepto],"ABONO") -> 44055.9 | I23: =G23-H23 -> 0 | J23: ='BASE DATOS'!AF22 -> 102797.1 | K23: =SUMIFS(Tabla35[Abonos],Tabla35[Lote],B23,Tabla35[Cliente],C23,Tabla35[Concepto],"MULTIBANK") -> 102797.1 | L23: =J23-K23 -> 0 | M23: ='BASE DATOS'!AV22 -> 450 | N23: =SUMIFS(Tabla35[Abonos],Tabla35[Lote],B23,Tabla35[Cliente],C23,Tabla35[Concepto],"GASTOS LEGALES") -> 450 | O23: =M23-N23 -> 0 | P23: 500 | Q23: =SUMIFS(Tabla35[Abonos],Tabla35[Lote],B23,Tabla35[Cliente],C23,Tabla35[Concepto],"FONDO ADM") -> 500 | R23: =P23-Q23 -> 0 | S23: 300 | T23: =SUMIFS(Tabla35[Abonos],Tabla35[Lote],B23,Tabla35[Cliente],C23,Tabla35[Concepto],"MEDIDOR") -> 300 | U23: =S23-T23 -> 0 | W23: =SUMIFS(Tabla35[Abonos],Tabla35[Lote],B23,Tabla35[Cliente],C23,Tabla35[Concepto],"PENALIZACIÓN") -> 0 | X23: =V23-W23 -> 0
B24: L-411 | C24: ='BASE DATOS'!C23 -> KOYNE LOISELLE | D24: ='BASE DATOS'!AA23 -> 161528.5 | E24: =I24+L24 -> 0 | F24: =Tabla5[[#This Row],[PENDIENTE GISA]]+Tabla5[[#This Row],[PENDIENTE MULTIBANK]]+Tabla5[[#This Row],[PENDIENTE GASTOS LEGALES]]+Tabla5[[#This Row],[FONDO ADM PENDIENTE]]+Tabla5[[#This Row],[MEDIDOR PENDIENTE]]+Tabla5[[#This Row],[PENALIZACIÓN PENDIENTE]] -> 377.1 | G24: ='BASE DATOS'!AE23 -> 48458.55 | H24: =SUMIFS(Tabla35[Abonos],Tabla35[Lote],B24,Tabla35[Cliente],C24,Tabla35[Concepto],"ABONO") -> 48458.55 | I24: =G24-H24 -> 0 | J24: ='BASE DATOS'!AF23 -> 113069.95 | K24: =SUMIFS(Tabla35[Abonos],Tabla35[Lote],B24,Tabla35[Cliente],C24,Tabla35[Concepto],"MULTIBANK") -> 113069.95 | L24: =J24-K24 -> 0 | M24: ='BASE DATOS'!AV23 -> 1550 | N24: =SUMIFS(Tabla35[Abonos],Tabla35[Lote],B24,Tabla35[Cliente],C24,Tabla35[Concepto],"GASTOS LEGALES") -> 1472.9 | O24: =M24-N24 -> 77.1 | P24: 500 | Q24: =SUMIFS(Tabla35[Abonos],Tabla35[Lote],B24,Tabla35[Cliente],C24,Tabla35[Concepto],"FONDO ADM") -> 500 | R24: =P24-Q24 -> 0 | S24: 300 | T24: =SUMIFS(Tabla35[Abonos],Tabla35[Lote],B24,Tabla35[Cliente],C24,Tabla35[Concepto],"MEDIDOR") -> 0 | U24: =S24-T24 -> 300 | W24: =SUMIFS(Tabla35[Abonos],Tabla35[Lote],B24,Tabla35[Cliente],C24,Tabla35[Concepto],"PENALIZACIÓN") -> 0 | X24: =V24-W24 -> 0
B25: L-301 | C25: ='BASE DATOS'!C24 -> SCOTT WAYNE / THI LE NETTIE | D25: ='BASE DATOS'!AA24 -> 202000 | E25: =I25+L25 -> 0 | F25: =Tabla5[[#This Row],[PENDIENTE GISA]]+Tabla5[[#This Row],[PENDIENTE MULTIBANK]]+Tabla5[[#This Row],[PENDIENTE GASTOS LEGALES]]+Tabla5[[#This Row],[FONDO ADM PENDIENTE]]+Tabla5[[#This Row],[MEDIDOR PENDIENTE]]+Tabla5[[#This Row],[PENALIZACIÓN PENDIENTE]] -> 300 | G25: ='BASE DATOS'!AE24 -> 70700 | H25: =SUMIFS(Tabla35[Abonos],Tabla35[Lote],B25,Tabla35[Cliente],C25,Tabla35[Concepto],"ABONO") -> 70700 | I25: =G25-H25 -> 0 | J25: ='BASE DATOS'!AF24 -> 131300 | K25: =SUMIFS(Tabla35[Abonos],Tabla35[Lote],B25,Tabla35[Cliente],C25,Tabla35[Concepto],"MULTIBANK") -> 131300 | L25: =J25-K25 -> 0 | M25: ='BASE DATOS'!AV24 -> 1870 | N25: =SUMIFS(Tabla35[Abonos],Tabla35[Lote],B25,Tabla35[Cliente],C25,Tabla35[Concepto],"GASTOS LEGALES") -> 1870 | O25: =M25-N25 -> 0 | P25: 500 | Q25: =SUMIFS(Tabla35[Abonos],Tabla35[Lote],B25,Tabla35[Cliente],C25,Tabla35[Concepto],"FONDO ADM") -> 500 | R25: =P25-Q25 -> 0 | S25: 300 | T25: =SUMIFS(Tabla35[Abonos],Tabla35[Lote],B25,Tabla35[Cliente],C25,Tabla35[Concepto],"MEDIDOR") -> 0 | U25: =S25-T25 -> 300 | W25: =SUMIFS(Tabla35[Abonos],Tabla35[Lote],B25,Tabla35[Cliente],C25,Tabla35[Concepto],"PENALIZACIÓN") -> 0 | X25: =V25-W25 -> 0
B26: L-302 | C26: ='BASE DATOS'!C25 -> CARLOS ARAGON | D26: ='BASE DATOS'!AA25 -> 145000 | E26: =I26+L26 -> 57.1 | F26: =Tabla5[[#This Row],[PENDIENTE GISA]]+Tabla5[[#This Row],[PENDIENTE MULTIBANK]]+Tabla5[[#This Row],[PENDIENTE GASTOS LEGALES]]+Tabla5[[#This Row],[FONDO ADM PENDIENTE]]+Tabla5[[#This Row],[MEDIDOR PENDIENTE]]+Tabla5[[#This Row],[PENALIZACIÓN PENDIENTE]] -> 57.1 | G26: ='BASE DATOS'!AE25 -> 145000 | H26: =SUMIFS(Tabla35[Abonos],Tabla35[Lote],B26,Tabla35[Cliente],C26,Tabla35[Concepto],"ABONO") -> 144942.9 | I26: =G26-H26 -> 57.1 | J26: ='BASE DATOS'!AF25 -> 0 | K26: =SUMIFS(Tabla35[Abonos],Tabla35[Lote],B26,Tabla35[Cliente],C26,Tabla35[Concepto],"MULTIBANK") -> 0 | L26: =J26-K26 -> 0 | M26: ='BASE DATOS'!AV25 -> 1593 | N26: =SUMIFS(Tabla35[Abonos],Tabla35[Lote],B26,Tabla35[Cliente],C26,Tabla35[Concepto],"GASTOS LEGALES") -> 1593 | O26: =M26-N26 -> 0 | P26: 500 | Q26: =SUMIFS(Tabla35[Abonos],Tabla35[Lote],B26,Tabla35[Cliente],C26,Tabla35[Concepto],"FONDO ADM") -> 500 | R26: =P26-Q26 -> 0 | S26: 300 | T26: =SUMIFS(Tabla35[Abonos],Tabla35[Lote],B26,Tabla35[Cliente],C26,Tabla35[Concepto],"MEDIDOR") -> 300 | U26: =S26-T26 -> 0 | W26: =SUMIFS(Tabla35[Abonos],Tabla35[Lote],B26,Tabla35[Cliente],C26,Tabla35[Concepto],"PENALIZACIÓN") -> 0 | X26: =V26-W26 -> 0
B27: L-303 | C27: ='BASE DATOS'!C26 -> INDIRA GARCIA | D27: ='BASE DATOS'!AA26 -> 187000 | E27: =I27+L27 -> 0 | F27: =Tabla5[[#This Row],[PENDIENTE GISA]]+Tabla5[[#This Row],[PENDIENTE MULTIBANK]]+Tabla5[[#This Row],[PENDIENTE GASTOS LEGALES]]+Tabla5[[#This Row],[FONDO ADM PENDIENTE]]+Tabla5[[#This Row],[MEDIDOR PENDIENTE]]+Tabla5[[#This Row],[PENALIZACIÓN PENDIENTE]] -> 0 | G27: ='BASE DATOS'!AE26 -> 17692.69 | H27: =SUMIFS(Tabla35[Abonos],Tabla35[Lote],B27,Tabla35[Cliente],C27,Tabla35[Concepto],"ABONO") -> 17692.69 | I27: =G27-H27 -> 0 | J27: ='BASE DATOS'!AF26 -> 169307.31 | K27: =SUMIFS(Tabla35[Abonos],Tabla35[Lote],B27,Tabla35[Cliente],C27,Tabla35[Concepto],"MULTIBANK") -> 169307.31 | L27: =J27-K27 -> 0 | M27: 0 | N27: =SUMIFS(Tabla35[Abonos],Tabla35[Lote],B27,Tabla35[Cliente],C27,Tabla35[Concepto],"GASTOS LEGALES") -> 0 | O27: =M27-N27 -> 0 | P27: 500 | Q27: =SUMIFS(Tabla35[Abonos],Tabla35[Lote],B27,Tabla35[Cliente],C27,Tabla35[Concepto],"FONDO ADM") -> 500 | R27: =P27-Q27 -> 0 | S27: 300 | T27: =SUMIFS(Tabla35[Abonos],Tabla35[Lote],B27,Tabla35[Cliente],C27,Tabla35[Concepto],"MEDIDOR") -> 300 | U27: =S27-T27 -> 0 | W27: =SUMIFS(Tabla35[Abonos],Tabla35[Lote],B27,Tabla35[Cliente],C27,Tabla35[Concepto],"PENALIZACIÓN") -> 0 | X27: =V27-W27 -> 0
B28: L-304 | C28: ='BASE DATOS'!C27 -> JAMES STORK Y RUTH URIETA | D28: ='BASE DATOS'!AA27 -> 183000 | E28: =I28+L28 -> 0 | F28: =Tabla5[[#This Row],[PENDIENTE GISA]]+Tabla5[[#This Row],[PENDIENTE MULTIBANK]]+Tabla5[[#This Row],[PENDIENTE GASTOS LEGALES]]+Tabla5[[#This Row],[FONDO ADM PENDIENTE]]+Tabla5[[#This Row],[MEDIDOR PENDIENTE]]+Tabla5[[#This Row],[PENALIZACIÓN PENDIENTE]] -> 0 | G28: ='BASE DATOS'!AE27 -> 54900 | H28: =SUMIFS(Tabla35[Abonos],Tabla35[Lote],B28,Tabla35[Cliente],C28,Tabla35[Concepto],"ABONO") -> 54900 | I28: =G28-H28 -> 0 | J28: ='BASE DATOS'!AF27 -> 128100 | K28: =SUMIFS(Tabla35[Abonos],Tabla35[Lote],B28,Tabla35[Cliente],C28,Tabla35[Concepto],"MULTIBANK") -> 128100 | L28: =J28-K28 -> 0 | M28: ='BASE DATOS'!AV27 -> 1619 | N28: =SUMIFS(Tabla35[Abonos],Tabla35[Lote],B28,Tabla35[Cliente],C28,Tabla35[Concepto],"GASTOS LEGALES") -> 1619 | O28: =M28-N28 -> 0 | P28: 500 | Q28: =SUMIFS(Tabla35[Abonos],Tabla35[Lote],B28,Tabla35[Cliente],C28,Tabla35[Concepto],"FONDO ADM") -> 500 | R28: =P28-Q28 -> 0 | S28: 300 | T28: =SUMIFS(Tabla35[Abonos],Tabla35[Lote],B28,Tabla35[Cliente],C28,Tabla35[Concepto],"MEDIDOR") -> 300 | U28: =S28-T28 -> 0 | W28: =SUMIFS(Tabla35[Abonos],Tabla35[Lote],B28,Tabla35[Cliente],C28,Tabla35[Concepto],"PENALIZACIÓN") -> 0 | X28: =V28-W28 -> 0
B29: L-305 | C29: ='BASE DATOS'!C28 -> GRUPO DICOS | D29: ='BASE DATOS'!AA28 -> 187976.82 | E29: =I29+L29 -> 94976.82 | F29: =Tabla5[[#This Row],[PENDIENTE GISA]]+Tabla5[[#This Row],[PENDIENTE MULTIBANK]]+Tabla5[[#This Row],[PENDIENTE GASTOS LEGALES]]+Tabla5[[#This Row],[FONDO ADM PENDIENTE]]+Tabla5[[#This Row],[MEDIDOR PENDIENTE]]+Tabla5[[#This Row],[PENALIZACIÓN PENDIENTE]] -> 94976.82 | G29: ='BASE DATOS'!AE28 -> 187976.82 | H29: =SUMIFS(Tabla35[Abonos],Tabla35[Lote],B29,Tabla35[Cliente],C29,Tabla35[Concepto],"ABONO") -> 93000 | I29: =G29-H29 -> 94976.82 | J29: ='BASE DATOS'!AF28 -> 0 | K29: =SUMIFS(Tabla35[Abonos],Tabla35[Lote],B29,Tabla35[Cliente],C29,Tabla35[Concepto],"MULTIBANK") -> 0 | L29: =J29-K29 -> 0 | M29: ='BASE DATOS'!AV28 -> 0 | N29: =SUMIFS(Tabla35[Abonos],Tabla35[Lote],B29,Tabla35[Cliente],C29,Tabla35[Concepto],"GASTOS LEGALES") -> 0 | O29: =M29-N29 -> 0 | P29: 500 | Q29: =SUMIFS(Tabla35[Abonos],Tabla35[Lote],B29,Tabla35[Cliente],C29,Tabla35[Concepto],"FONDO ADM") -> 500 | R29: =P29-Q29 -> 0 | S29: 300 | T29: =SUMIFS(Tabla35[Abonos],Tabla35[Lote],B29,Tabla35[Cliente],C29,Tabla35[Concepto],"MEDIDOR") -> 300 | U29: =S29-T29 -> 0 | W29: =SUMIFS(Tabla35[Abonos],Tabla35[Lote],B29,Tabla35[Cliente],C29,Tabla35[Concepto],"PENALIZACIÓN") -> 0 | X29: =V29-W29 -> 0
B30: L-306 | C30: ='BASE DATOS'!C29 -> 0 | D30: ='BASE DATOS'!AA29 -> 198850 | E30: =I30+L30 -> 198850 | F30: =Tabla5[[#This Row],[PENDIENTE GISA]]+Tabla5[[#This Row],[PENDIENTE MULTIBANK]]+Tabla5[[#This Row],[PENDIENTE GASTOS LEGALES]]+Tabla5[[#This Row],[FONDO ADM PENDIENTE]]+Tabla5[[#This Row],[MEDIDOR PENDIENTE]]+Tabla5[[#This Row],[PENALIZACIÓN PENDIENTE]] -> 199650 | G30: ='BASE DATOS'!AE29 -> 198850 | H30: =SUMIFS(Tabla35[Abonos],Tabla35[Lote],B30,Tabla35[Cliente],C30,Tabla35[Concepto],"ABONO") -> 0 | I30: =G30-H30 -> 198850 | J30: ='BASE DATOS'!AF29 -> 0 | K30: =SUMIFS(Tabla35[Abonos],Tabla35[Lote],B30,Tabla35[Cliente],C30,Tabla35[Concepto],"MULTIBANK") -> 0 | L30: =J30-K30 -> 0 | M30: ='BASE DATOS'!AV29 -> 0 | N30: =SUMIFS(Tabla35[Abonos],Tabla35[Lote],B30,Tabla35[Cliente],C30,Tabla35[Concepto],"GASTOS LEGALES") -> 0 | O30: =M30-N30 -> 0 | P30: 500 | Q30: =SUMIFS(Tabla35[Abonos],Tabla35[Lote],B30,Tabla35[Cliente],C30,Tabla35[Concepto],"FONDO ADM") -> 0 | R30: =P30-Q30 -> 500 | S30: 300 | T30: =SUMIFS(Tabla35[Abonos],Tabla35[Lote],B30,Tabla35[Cliente],C30,Tabla35[Concepto],"MEDIDOR") -> 0 | U30: =S30-T30 -> 300 | W30: =SUMIFS(Tabla35[Abonos],Tabla35[Lote],B30,Tabla35[Cliente],C30,Tabla35[Concepto],"PENALIZACIÓN") -> 0 | X30: =V30-W30 -> 0
B31: L-307 | C31: ='BASE DATOS'!C30 -> YANIRED GONZALEZ ALVARADO DE ADAMS | D31: ='BASE DATOS'!AA30 -> 187000 | E31: =I31+L31 -> 0 | F31: =Tabla5[[#This Row],[PENDIENTE GISA]]+Tabla5[[#This Row],[PENDIENTE MULTIBANK]]+Tabla5[[#This Row],[PENDIENTE GASTOS LEGALES]]+Tabla5[[#This Row],[FONDO ADM PENDIENTE]]+Tabla5[[#This Row],[MEDIDOR PENDIENTE]]+Tabla5[[#This Row],[PENALIZACIÓN PENDIENTE]] -> 0 | G31: ='BASE DATOS'!AE30 -> 56100 | H31: =SUMIFS(Tabla35[Abonos],Tabla35[Lote],B31,Tabla35[Cliente],C31,Tabla35[Concepto],"ABONO") -> 56100 | I31: =G31-H31 -> 0 | J31: ='BASE DATOS'!AF30 -> 130900 | K31: =SUMIFS(Tabla35[Abonos],Tabla35[Lote],B31,Tabla35[Cliente],C31,Tabla35[Concepto],"MULTIBANK") -> 130900 | L31: =J31-K31 -> 0 | M31: ='BASE DATOS'!AV30 -> 1330 | N31: =SUMIFS(Tabla35[Abonos],Tabla35[Lote],B31,Tabla35[Cliente],C31,Tabla35[Concepto],"GASTOS LEGALES") -> 1330 | O31: =M31-N31 -> 0 | P31: 500 | Q31: =SUMIFS(Tabla35[Abonos],Tabla35[Lote],B31,Tabla35[Cliente],C31,Tabla35[Concepto],"FONDO ADM") -> 500 | R31: =P31-Q31 -> 0 | S31: 300 | T31: =SUMIFS(Tabla35[Abonos],Tabla35[Lote],B31,Tabla35[Cliente],C31,Tabla35[Concepto],"MEDIDOR") -> 300 | U31: =S31-T31 -> 0 | W31: =SUMIFS(Tabla35[Abonos],Tabla35[Lote],B31,Tabla35[Cliente],C31,Tabla35[Concepto],"PENALIZACIÓN") -> 0 | X31: =V31-W31 -> 0
B32: L-308 | C32: ='BASE DATOS'!C31 -> NORA MORENO | D32: ='BASE DATOS'!AA31 -> 185000 | E32: =I32+L32 -> 5503.63 | F32: =Tabla5[[#This Row],[PENDIENTE GISA]]+Tabla5[[#This Row],[PENDIENTE MULTIBANK]]+Tabla5[[#This Row],[PENDIENTE GASTOS LEGALES]]+Tabla5[[#This Row],[FONDO ADM PENDIENTE]]+Tabla5[[#This Row],[MEDIDOR PENDIENTE]]+Tabla5[[#This Row],[PENALIZACIÓN PENDIENTE]] -> 5503.63 | G32: ='BASE DATOS'!AE31 -> 31000 | H32: =SUMIFS(Tabla35[Abonos],Tabla35[Lote],B32,Tabla35[Cliente],C32,Tabla35[Concepto],"ABONO") -> 25496.37 | I32: =G32-H32 -> 5503.63 | J32: ='BASE DATOS'!AF31 -> 154000 | K32: =SUMIFS(Tabla35[Abonos],Tabla35[Lote],B32,Tabla35[Cliente],C32,Tabla35[Concepto],"MULTIBANK") -> 154000 | L32: =J32-K32 -> 0 | M32: 0 | N32: =SUMIFS(Tabla35[Abonos],Tabla35[Lote],B32,Tabla35[Cliente],C32,Tabla35[Concepto],"GASTOS LEGALES") -> 0 | O32: =M32-N32 -> 0 | P32: 500 | Q32: =SUMIFS(Tabla35[Abonos],Tabla35[Lote],B32,Tabla35[Cliente],C32,Tabla35[Concepto],"FONDO ADM") -> 500 | R32: =P32-Q32 -> 0 | S32: 300 | T32: =SUMIFS(Tabla35[Abonos],Tabla35[Lote],B32,Tabla35[Cliente],C32,Tabla35[Concepto],"MEDIDOR") -> 300 | U32: =S32-T32 -> 0 | W32: =SUMIFS(Tabla35[Abonos],Tabla35[Lote],B32,Tabla35[Cliente],C32,Tabla35[Concepto],"PENALIZACIÓN") -> 0 | X32: =V32-W32 -> 0
B33: L-309 | C33: ='BASE DATOS'!C32 -> SHAROMAY OSMA | D33: ='BASE DATOS'!AA32 -> 180000 | E33: =I33+L33 -> 0 | F33: =Tabla5[[#This Row],[PENDIENTE GISA]]+Tabla5[[#This Row],[PENDIENTE MULTIBANK]]+Tabla5[[#This Row],[PENDIENTE GASTOS LEGALES]]+Tabla5[[#This Row],[FONDO ADM PENDIENTE]]+Tabla5[[#This Row],[MEDIDOR PENDIENTE]]+Tabla5[[#This Row],[PENALIZACIÓN PENDIENTE]] -> 0 | G33: ='BASE DATOS'!AE32 -> 27000 | H33: =SUMIFS(Tabla35[Abonos],Tabla35[Lote],B33,Tabla35[Cliente],C33,Tabla35[Concepto],"ABONO") -> 27000 | I33: =G33-H33 -> 0 | J33: ='BASE DATOS'!AF32 -> 153000 | K33: =SUMIFS(Tabla35[Abonos],Tabla35[Lote],B33,Tabla35[Cliente],C33,Tabla35[Concepto],"MULTIBANK") -> 153000 | L33: =J33-K33 -> 0 | M33: 0 | N33: =SUMIFS(Tabla35[Abonos],Tabla35[Lote],B33,Tabla35[Cliente],C33,Tabla35[Concepto],"GASTOS LEGALES") -> 0 | O33: =M33-N33 -> 0 | P33: 500 | Q33: =SUMIFS(Tabla35[Abonos],Tabla35[Lote],B33,Tabla35[Cliente],C33,Tabla35[Concepto],"FONDO ADM") -> 500 | R33: =P33-Q33 -> 0 | S33: 300 | T33: =SUMIFS(Tabla35[Abonos],Tabla35[Lote],B33,Tabla35[Cliente],C33,Tabla35[Concepto],"MEDIDOR") -> 300 | U33: =S33-T33 -> 0 | W33: =SUMIFS(Tabla35[Abonos],Tabla35[Lote],B33,Tabla35[Cliente],C33,Tabla35[Concepto],"PENALIZACIÓN") -> 0 | X33: =V33-W33 -> 0
B34: L-310 | C34: ='BASE DATOS'!C33 -> GERMAN SANCHEZ | D34: ='BASE DATOS'!AA33 -> 185000 | E34: =I34+L34 -> 0 | F34: =Tabla5[[#This Row],[PENDIENTE GISA]]+Tabla5[[#This Row],[PENDIENTE MULTIBANK]]+Tabla5[[#This Row],[PENDIENTE GASTOS LEGALES]]+Tabla5[[#This Row],[FONDO ADM PENDIENTE]]+Tabla5[[#This Row],[MEDIDOR PENDIENTE]]+Tabla5[[#This Row],[PENALIZACIÓN PENDIENTE]] -> 0 | G34: ='BASE DATOS'!AE33 -> 31000 | H34: =SUMIFS(Tabla35[Abonos],Tabla35[Lote],B34,Tabla35[Cliente],C34,Tabla35[Concepto],"ABONO") -> 31000 | I34: =G34-H34 -> 0 | J34: ='BASE DATOS'!AF33 -> 154000 | K34: =SUMIFS(Tabla35[Abonos],Tabla35[Lote],B34,Tabla35[Cliente],C34,Tabla35[Concepto],"MULTIBANK") -> 154000 | L34: =J34-K34 -> 0 | M34: 0 | N34: =SUMIFS(Tabla35[Abonos],Tabla35[Lote],B34,Tabla35[Cliente],C34,Tabla35[Concepto],"GASTOS LEGALES") -> 0 | O34: =M34-N34 -> 0 | P34: 500 | Q34: =SUMIFS(Tabla35[Abonos],Tabla35[Lote],B34,Tabla35[Cliente],C34,Tabla35[Concepto],"FONDO ADM") -> 500 | R34: =P34-Q34 -> 0 | S34: 300 | T34: =SUMIFS(Tabla35[Abonos],Tabla35[Lote],B34,Tabla35[Cliente],C34,Tabla35[Concepto],"MEDIDOR") -> 300 | U34: =S34-T34 -> 0 | W34: =SUMIFS(Tabla35[Abonos],Tabla35[Lote],B34,Tabla35[Cliente],C34,Tabla35[Concepto],"PENALIZACIÓN") -> 0 | X34: =V34-W34 -> 0
B35: L-311 | C35: ='BASE DATOS'!C34 -> MELINDA MOORE | D35: ='BASE DATOS'!AA34 -> 150000 | E35: =I35+L35 -> 0 | F35: =Tabla5[[#This Row],[PENDIENTE GISA]]+Tabla5[[#This Row],[PENDIENTE MULTIBANK]]+Tabla5[[#This Row],[PENDIENTE GASTOS LEGALES]]+Tabla5[[#This Row],[FONDO ADM PENDIENTE]]+Tabla5[[#This Row],[MEDIDOR PENDIENTE]]+Tabla5[[#This Row],[PENALIZACIÓN PENDIENTE]] -> 10 | G35: ='BASE DATOS'!AE34 -> 45000 | H35: =SUMIFS(Tabla35[Abonos],Tabla35[Lote],B35,Tabla35[Cliente],C35,Tabla35[Concepto],"ABONO") -> 45000 | I35: =G35-H35 -> 0 | J35: ='BASE DATOS'!AF34 -> 105000 | K35: =SUMIFS(Tabla35[Abonos],Tabla35[Lote],B35,Tabla35[Cliente],C35,Tabla35[Concepto],"MULTIBANK") -> 105000 | L35: =J35-K35 -> 0 | M35: ='BASE DATOS'!AV34 -> 950 | N35: =SUMIFS(Tabla35[Abonos],Tabla35[Lote],B35,Tabla35[Cliente],C35,Tabla35[Concepto],"GASTOS LEGALES") -> 950 | O35: =M35-N35 -> 0 | P35: 500 | Q35: =SUMIFS(Tabla35[Abonos],Tabla35[Lote],B35,Tabla35[Cliente],C35,Tabla35[Concepto],"FONDO ADM") -> 490 | R35: =P35-Q35 -> 10 | S35: 300 | T35: =SUMIFS(Tabla35[Abonos],Tabla35[Lote],B35,Tabla35[Cliente],C35,Tabla35[Concepto],"MEDIDOR") -> 300 | U35: =S35-T35 -> 0 | W35: =SUMIFS(Tabla35[Abonos],Tabla35[Lote],B35,Tabla35[Cliente],C35,Tabla35[Concepto],"PENALIZACIÓN") -> 0 | X35: =V35-W35 -> 0
B36: L-312 | C36: ='BASE DATOS'!C35 -> ALVARO MORENO | D36: ='BASE DATOS'!AA35 -> 172500 | E36: =I36+L36 -> 0 | F36: =Tabla5[[#This Row],[PENDIENTE GISA]]+Tabla5[[#This Row],[PENDIENTE MULTIBANK]]+Tabla5[[#This Row],[PENDIENTE GASTOS LEGALES]]+Tabla5[[#This Row],[FONDO ADM PENDIENTE]]+Tabla5[[#This Row],[MEDIDOR PENDIENTE]]+Tabla5[[#This Row],[PENALIZACIÓN PENDIENTE]] -> 0 | G36: ='BASE DATOS'!AE35 -> 40000 | H36: =SUMIFS(Tabla35[Abonos],Tabla35[Lote],B36,Tabla35[Cliente],C36,Tabla35[Concepto],"ABONO") -> 40000 | I36: =G36-H36 -> 0 | J36: ='BASE DATOS'!AF35 -> 132500 | K36: =SUMIFS(Tabla35[Abonos],Tabla35[Lote],B36,Tabla35[Cliente],C36,Tabla35[Concepto],"MULTIBANK") -> 132500 | L36: =J36-K36 -> 0 | M36: 0 | N36: =SUMIFS(Tabla35[Abonos],Tabla35[Lote],B36,Tabla35[Cliente],C36,Tabla35[Concepto],"GASTOS LEGALES") -> 0 | O36: =M36-N36 -> 0 | P36: 500 | Q36: =SUMIFS(Tabla35[Abonos],Tabla35[Lote],B36,Tabla35[Cliente],C36,Tabla35[Concepto],"FONDO ADM") -> 500 | R36: =P36-Q36 -> 0 | S36: 300 | T36: =SUMIFS(Tabla35[Abonos],Tabla35[Lote],B36,Tabla35[Cliente],C36,Tabla35[Concepto],"MEDIDOR") -> 300 | U36: =S36-T36 -> 0 | W36: =SUMIFS(Tabla35[Abonos],Tabla35[Lote],B36,Tabla35[Cliente],C36,Tabla35[Concepto],"PENALIZACIÓN") -> 0 | X36: =V36-W36 -> 0
B37: L-201 | C37: ='BASE DATOS'!C36 -> SIMON LEWIS CHAPELLE | D37: ='BASE DATOS'!AA36 -> 202000 | E37: =I37+L37 -> 0 | F37: =Tabla5[[#This Row],[PENDIENTE GISA]]+Tabla5[[#This Row],[PENDIENTE MULTIBANK]]+Tabla5[[#This Row],[PENDIENTE GASTOS LEGALES]]+Tabla5[[#This Row],[FONDO ADM PENDIENTE]]+Tabla5[[#This Row],[MEDIDOR PENDIENTE]]+Tabla5[[#This Row],[PENALIZACIÓN PENDIENTE]] -> 0 | G37: ='BASE DATOS'!AE36 -> 60000 | H37: =SUMIFS(Tabla35[Abonos],Tabla35[Lote],B37,Tabla35[Cliente],C37,Tabla35[Concepto],"ABONO") -> 60000 | I37: =G37-H37 -> 0 | J37: ='BASE DATOS'!AF36 -> 142000 | K37: =SUMIFS(Tabla35[Abonos],Tabla35[Lote],B37,Tabla35[Cliente],C37,Tabla35[Concepto],"MULTIBANK") -> 142000 | L37: =J37-K37 -> 0 | M37: ='BASE DATOS'!AV36 -> 2070 | N37: =SUMIFS(Tabla35[Abonos],Tabla35[Lote],B37,Tabla35[Cliente],C37,Tabla35[Concepto],"GASTOS LEGALES") -> 2070 | O37: =M37-N37 -> 0 | P37: 500 | Q37: =SUMIFS(Tabla35[Abonos],Tabla35[Lote],B37,Tabla35[Cliente],C37,Tabla35[Concepto],"FONDO ADM") -> 500 | R37: =P37-Q37 -> 0 | S37: 300 | T37: =SUMIFS(Tabla35[Abonos],Tabla35[Lote],B37,Tabla35[Cliente],C37,Tabla35[Concepto],"MEDIDOR") -> 300 | U37: =S37-T37 -> 0 | W37: =SUMIFS(Tabla35[Abonos],Tabla35[Lote],B37,Tabla35[Cliente],C37,Tabla35[Concepto],"PENALIZACIÓN") -> 0 | X37: =V37-W37 -> 0
B38: L-202 | C38: ='BASE DATOS'!C37 -> RUTH WINSLOW | D38: ='BASE DATOS'!AA37 -> 137862 | E38: =I38+L38 -> 25 | F38: =Tabla5[[#This Row],[PENDIENTE GISA]]+Tabla5[[#This Row],[PENDIENTE MULTIBANK]]+Tabla5[[#This Row],[PENDIENTE GASTOS LEGALES]]+Tabla5[[#This Row],[FONDO ADM PENDIENTE]]+Tabla5[[#This Row],[MEDIDOR PENDIENTE]]+Tabla5[[#This Row],[PENALIZACIÓN PENDIENTE]] -> 45 | G38: ='BASE DATOS'!AE37 -> 41358.6 | H38: =SUMIFS(Tabla35[Abonos],Tabla35[Lote],B38,Tabla35[Cliente],C38,Tabla35[Concepto],"ABONO") -> 41333.6 | I38: =G38-H38 -> 25 | J38: ='BASE DATOS'!AF37 -> 96503.4 | K38: =SUMIFS(Tabla35[Abonos],Tabla35[Lote],B38,Tabla35[Cliente],C38,Tabla35[Concepto],"MULTIBANK") -> 96503.4 | L38: =J38-K38 -> 0 | M38: ='BASE DATOS'!AV37 -> 1725 | N38: =SUMIFS(Tabla35[Abonos],Tabla35[Lote],B38,Tabla35[Cliente],C38,Tabla35[Concepto],"GASTOS LEGALES") -> 1705 | O38: =M38-N38 -> 20 | P38: 500 | Q38: =SUMIFS(Tabla35[Abonos],Tabla35[Lote],B38,Tabla35[Cliente],C38,Tabla35[Concepto],"FONDO ADM") -> 500 | R38: =P38-Q38 -> 0 | S38: 300 | T38: =SUMIFS(Tabla35[Abonos],Tabla35[Lote],B38,Tabla35[Cliente],C38,Tabla35[Concepto],"MEDIDOR") -> 300 | U38: =S38-T38 -> 0 | W38: =SUMIFS(Tabla35[Abonos],Tabla35[Lote],B38,Tabla35[Cliente],C38,Tabla35[Concepto],"PENALIZACIÓN") -> 0 | X38: =V38-W38 -> 0
B39: L-203 | C39: ='BASE DATOS'!C38 -> JOSE ALEJANDRO DE LEON | D39: ='BASE DATOS'!AA38 -> 179900 | E39: =I39+L39 -> 0 | F39: =Tabla5[[#This Row],[PENDIENTE GISA]]+Tabla5[[#This Row],[PENDIENTE MULTIBANK]]+Tabla5[[#This Row],[PENDIENTE GASTOS LEGALES]]+Tabla5[[#This Row],[FONDO ADM PENDIENTE]]+Tabla5[[#This Row],[MEDIDOR PENDIENTE]]+Tabla5[[#This Row],[PENALIZACIÓN PENDIENTE]] -> 300 | G39: ='BASE DATOS'!AE38 -> 179900 | H39: =SUMIFS(Tabla35[Abonos],Tabla35[Lote],B39,Tabla35[Cliente],C39,Tabla35[Concepto],"ABONO") -> 179900 | I39: =G39-H39 -> 0 | J39: ='BASE DATOS'!AF38 -> 0 | K39: =SUMIFS(Tabla35[Abonos],Tabla35[Lote],B39,Tabla35[Cliente],C39,Tabla35[Concepto],"MULTIBANK") -> 0 | L39: =J39-K39 -> 0 | M39: ='BASE DATOS'!AV38 -> 1750 | N39: =SUMIFS(Tabla35[Abonos],Tabla35[Lote],B39,Tabla35[Cliente],C39,Tabla35[Concepto],"GASTOS LEGALES") -> 1750 | O39: =M39-N39 -> 0 | P39: 500 | Q39: =SUMIFS(Tabla35[Abonos],Tabla35[Lote],B39,Tabla35[Cliente],C39,Tabla35[Concepto],"FONDO ADM") -> 500 | R39: =P39-Q39 -> 0 | S39: 300 | T39: =SUMIFS(Tabla35[Abonos],Tabla35[Lote],B39,Tabla35[Cliente],C39,Tabla35[Concepto],"MEDIDOR") -> 0 | U39: =S39-T39 -> 300 | W39: =SUMIFS(Tabla35[Abonos],Tabla35[Lote],B39,Tabla35[Cliente],C39,Tabla35[Concepto],"PENALIZACIÓN") -> 0 | X39: =V39-W39 -> 0
B40: L-204 | C40: ='BASE DATOS'!C39 -> MELVA BELTRAN | D40: ='BASE DATOS'!AA39 -> 184000 | E40: =I40+L40 -> 171000 | F40: =Tabla5[[#This Row],[PENDIENTE GISA]]+Tabla5[[#This Row],[PENDIENTE MULTIBANK]]+Tabla5[[#This Row],[PENDIENTE GASTOS LEGALES]]+Tabla5[[#This Row],[FONDO ADM PENDIENTE]]+Tabla5[[#This Row],[MEDIDOR PENDIENTE]]+Tabla5[[#This Row],[PENALIZACIÓN PENDIENTE]] -> #VALUE! | G40: ='BASE DATOS'!AE39 -> 184000 | H40: =SUMIFS(Tabla35[Abonos],Tabla35[Lote],B40,Tabla35[Cliente],C40,Tabla35[Concepto],"ABONO") -> 13000 | I40: =G40-H40 -> 171000 | J40: ='BASE DATOS'!AF39 -> 0 | K40: =SUMIFS(Tabla35[Abonos],Tabla35[Lote],B40,Tabla35[Cliente],C40,Tabla35[Concepto],"MULTIBANK") -> 0 | L40: =J40-K40 -> 0 | M40: ='BASE DATOS'!AV39 -> BANCO | N40: =SUMIFS(Tabla35[Abonos],Tabla35[Lote],B40,Tabla35[Cliente],C40,Tabla35[Concepto],"GASTOS LEGALES") -> 0 | O40: =M40-N40 -> #VALUE! | P40: 500 | Q40: =SUMIFS(Tabla35[Abonos],Tabla35[Lote],B40,Tabla35[Cliente],C40,Tabla35[Concepto],"FONDO ADM") -> 500 | R40: =P40-Q40 -> 0 | S40: 300 | T40: =SUMIFS(Tabla35[Abonos],Tabla35[Lote],B40,Tabla35[Cliente],C40,Tabla35[Concepto],"MEDIDOR") -> 300 | U40: =S40-T40 -> 0 | W40: =SUMIFS(Tabla35[Abonos],Tabla35[Lote],B40,Tabla35[Cliente],C40,Tabla35[Concepto],"PENALIZACIÓN") -> 0 | X40: =V40-W40 -> 0
B41: L-205 | C41: ='BASE DATOS'!C40 -> ISABELLE BELANGER/DANIEL CARON | D41: ='BASE DATOS'!AA40 -> 194000 | E41: =I41+L41 -> 121932.1 | F41: =Tabla5[[#This Row],[PENDIENTE GISA]]+Tabla5[[#This Row],[PENDIENTE MULTIBANK]]+Tabla5[[#This Row],[PENDIENTE GASTOS LEGALES]]+Tabla5[[#This Row],[FONDO ADM PENDIENTE]]+Tabla5[[#This Row],[MEDIDOR PENDIENTE]]+Tabla5[[#This Row],[PENALIZACIÓN PENDIENTE]] -> 125688.65 | G41: ='BASE DATOS'!AE40 -> 194000 | H41: =SUMIFS(Tabla35[Abonos],Tabla35[Lote],B41,Tabla35[Cliente],C41,Tabla35[Concepto],"ABONO") -> 72067.9 | I41: =G41-H41 -> 121932.1 | J41: ='BASE DATOS'!AF40 -> 0 | K41: =SUMIFS(Tabla35[Abonos],Tabla35[Lote],B41,Tabla35[Cliente],C41,Tabla35[Concepto],"MULTIBANK") -> 0 | L41: =J41-K41 -> 0 | M41: ='BASE DATOS'!AV40 -> 2956.55 | N41: =SUMIFS(Tabla35[Abonos],Tabla35[Lote],B41,Tabla35[Cliente],C41,Tabla35[Concepto],"GASTOS LEGALES") -> 0 | O41: =M41-N41 -> 2956.55 | P41: 500 | Q41: =SUMIFS(Tabla35[Abonos],Tabla35[Lote],B41,Tabla35[Cliente],C41,Tabla35[Concepto],"FONDO ADM") -> 0 | R41: =P41-Q41 -> 500 | S41: 300 | T41: =SUMIFS(Tabla35[Abonos],Tabla35[Lote],B41,Tabla35[Cliente],C41,Tabla35[Concepto],"MEDIDOR") -> 0 | U41: =S41-T41 -> 300 | W41: =SUMIFS(Tabla35[Abonos],Tabla35[Lote],B41,Tabla35[Cliente],C41,Tabla35[Concepto],"PENALIZACIÓN") -> 0 | X41: =V41-W41 -> 0
B42: L-206 | C42: ='BASE DATOS'!C41 -> DARKO VASIC Y DANIEL KRAUSKOPF | D42: ='BASE DATOS'!AA41 -> 204000 | E42: =I42+L42 -> 132610 | F42: =Tabla5[[#This Row],[PENDIENTE GISA]]+Tabla5[[#This Row],[PENDIENTE MULTIBANK]]+Tabla5[[#This Row],[PENDIENTE GASTOS LEGALES]]+Tabla5[[#This Row],[FONDO ADM PENDIENTE]]+Tabla5[[#This Row],[MEDIDOR PENDIENTE]]+Tabla5[[#This Row],[PENALIZACIÓN PENDIENTE]] -> 132960.33 | G42: ='BASE DATOS'!AE41 -> 204000 | H42: =SUMIFS(Tabla35[Abonos],Tabla35[Lote],B42,Tabla35[Cliente],C42,Tabla35[Concepto],"ABONO") -> 71390 | I42: =G42-H42 -> 132610 | J42: ='BASE DATOS'!AF41 -> 0 | K42: =SUMIFS(Tabla35[Abonos],Tabla35[Lote],B42,Tabla35[Cliente],C42,Tabla35[Concepto],"MULTIBANK") -> 0 | L42: =J42-K42 -> 0 | M42: ='BASE DATOS'!AV41 -> 2966 | N42: =SUMIFS(Tabla35[Abonos],Tabla35[Lote],B42,Tabla35[Cliente],C42,Tabla35[Concepto],"GASTOS LEGALES") -> 2923.55 | O42: =M42-N42 -> 42.45 | P42: 500 | Q42: =SUMIFS(Tabla35[Abonos],Tabla35[Lote],B42,Tabla35[Cliente],C42,Tabla35[Concepto],"FONDO ADM") -> 492.12 | R42: =P42-Q42 -> 7.88 | S42: 300 | T42: =SUMIFS(Tabla35[Abonos],Tabla35[Lote],B42,Tabla35[Cliente],C42,Tabla35[Concepto],"MEDIDOR") -> 0 | U42: =S42-T42 -> 300 | W42: =SUMIFS(Tabla35[Abonos],Tabla35[Lote],B42,Tabla35[Cliente],C42,Tabla35[Concepto],"PENALIZACIÓN") -> 0 | X42: =V42-W42 -> 0
B43: L-207 | C43: ='BASE DATOS'!C42 -> 0 | D43: ='BASE DATOS'!AA42 -> 201000 | E43: =I43+L43 -> 201000 | F43: =Tabla5[[#This Row],[PENDIENTE GISA]]+Tabla5[[#This Row],[PENDIENTE MULTIBANK]]+Tabla5[[#This Row],[PENDIENTE GASTOS LEGALES]]+Tabla5[[#This Row],[FONDO ADM PENDIENTE]]+Tabla5[[#This Row],[MEDIDOR PENDIENTE]]+Tabla5[[#This Row],[PENALIZACIÓN PENDIENTE]] -> 201800 | G43: ='BASE DATOS'!AE42 -> 201000 | H43: =SUMIFS(Tabla35[Abonos],Tabla35[Lote],B43,Tabla35[Cliente],C43,Tabla35[Concepto],"ABONO") -> 0 | I43: =G43-H43 -> 201000 | J43: ='BASE DATOS'!AF42 -> 0 | K43: =SUMIFS(Tabla35[Abonos],Tabla35[Lote],B43,Tabla35[Cliente],C43,Tabla35[Concepto],"MULTIBANK") -> 0 | L43: =J43-K43 -> 0 | M43: ='BASE DATOS'!AV42 -> 0 | N43: =SUMIFS(Tabla35[Abonos],Tabla35[Lote],B43,Tabla35[Cliente],C43,Tabla35[Concepto],"GASTOS LEGALES") -> 0 | O43: =M43-N43 -> 0 | P43: 500 | Q43: =SUMIFS(Tabla35[Abonos],Tabla35[Lote],B43,Tabla35[Cliente],C43,Tabla35[Concepto],"FONDO ADM") -> 0 | R43: =P43-Q43 -> 500 | S43: 300 | T43: =SUMIFS(Tabla35[Abonos],Tabla35[Lote],B43,Tabla35[Cliente],C43,Tabla35[Concepto],"MEDIDOR") -> 0 | U43: =S43-T43 -> 300 | W43: =SUMIFS(Tabla35[Abonos],Tabla35[Lote],B43,Tabla35[Cliente],C43,Tabla35[Concepto],"PENALIZACIÓN") -> 0 | X43: =V43-W43 -> 0
B44: L-208 | C44: ='BASE DATOS'!C43 -> SANDRA KAVANAUGH/SHARON BOMFALK | D44: ='BASE DATOS'!AA43 -> 201000 | E44: =I44+L44 -> 0 | F44: =Tabla5[[#This Row],[PENDIENTE GISA]]+Tabla5[[#This Row],[PENDIENTE MULTIBANK]]+Tabla5[[#This Row],[PENDIENTE GASTOS LEGALES]]+Tabla5[[#This Row],[FONDO ADM PENDIENTE]]+Tabla5[[#This Row],[MEDIDOR PENDIENTE]]+Tabla5[[#This Row],[PENALIZACIÓN PENDIENTE]] -> 0 | G44: ='BASE DATOS'!AE43 -> 201000 | H44: =SUMIFS(Tabla35[Abonos],Tabla35[Lote],B44,Tabla35[Cliente],C44,Tabla35[Concepto],"ABONO") -> 201000 | I44: =G44-H44 -> 0 | J44: ='BASE DATOS'!AF43 -> 0 | K44: =SUMIFS(Tabla35[Abonos],Tabla35[Lote],B44,Tabla35[Cliente],C44,Tabla35[Concepto],"MULTIBANK") -> 0 | L44: =J44-K44 -> 0 | M44: ='BASE DATOS'!AV43 -> 1830 | N44: =SUMIFS(Tabla35[Abonos],Tabla35[Lote],B44,Tabla35[Cliente],C44,Tabla35[Concepto],"GASTOS LEGALES") -> 1830 | O44: =M44-N44 -> 0 | P44: 500 | Q44: =SUMIFS(Tabla35[Abonos],Tabla35[Lote],B44,Tabla35[Cliente],C44,Tabla35[Concepto],"FONDO ADM") -> 500 | R44: =P44-Q44 -> 0 | S44: 300 | T44: =SUMIFS(Tabla35[Abonos],Tabla35[Lote],B44,Tabla35[Cliente],C44,Tabla35[Concepto],"MEDIDOR") -> 300 | U44: =S44-T44 -> 0 | W44: =SUMIFS(Tabla35[Abonos],Tabla35[Lote],B44,Tabla35[Cliente],C44,Tabla35[Concepto],"PENALIZACIÓN") -> 0 | X44: =V44-W44 -> 0
B45: L-209 | C45: ='BASE DATOS'!C44 -> CONSTRUA INTERNATIONAL | D45: ='BASE DATOS'!AA44 -> 130000 | E45: =I45+L45 -> 0 | F45: =Tabla5[[#This Row],[PENDIENTE GISA]]+Tabla5[[#This Row],[PENDIENTE MULTIBANK]]+Tabla5[[#This Row],[PENDIENTE GASTOS LEGALES]]+Tabla5[[#This Row],[FONDO ADM PENDIENTE]]+Tabla5[[#This Row],[MEDIDOR PENDIENTE]]+Tabla5[[#This Row],[PENALIZACIÓN PENDIENTE]] -> 800 | G45: ='BASE DATOS'!AE44 -> 130000 | H45: =SUMIFS(Tabla35[Abonos],Tabla35[Lote],B45,Tabla35[Cliente],C45,Tabla35[Concepto],"ABONO") -> 130000 | I45: =G45-H45 -> 0 | J45: ='BASE DATOS'!AF44 -> 0 | K45: =SUMIFS(Tabla35[Abonos],Tabla35[Lote],B45,Tabla35[Cliente],C45,Tabla35[Concepto],"MULTIBANK") -> 0 | L45: =J45-K45 -> 0 | M45: ='BASE DATOS'!AV44 -> 1726 | N45: =SUMIFS(Tabla35[Abonos],Tabla35[Lote],B45,Tabla35[Cliente],C45,Tabla35[Concepto],"GASTOS LEGALES") -> 1726 | O45: =M45-N45 -> 0 | P45: 500 | Q45: =SUMIFS(Tabla35[Abonos],Tabla35[Lote],B45,Tabla35[Cliente],C45,Tabla35[Concepto],"FONDO ADM") -> 0 | R45: =P45-Q45 -> 500 | S45: 300 | T45: =SUMIFS(Tabla35[Abonos],Tabla35[Lote],B45,Tabla35[Cliente],C45,Tabla35[Concepto],"MEDIDOR") -> 0 | U45: =S45-T45 -> 300 | W45: =SUMIFS(Tabla35[Abonos],Tabla35[Lote],B45,Tabla35[Cliente],C45,Tabla35[Concepto],"PENALIZACIÓN") -> 0 | X45: =V45-W45 -> 0
B46: L-210 | C46: ='BASE DATOS'!C45 -> NADIA RODRIGUEZ | D46: ='BASE DATOS'!AA45 -> 180000 | E46: =I46+L46 -> 100000 | F46: =Tabla5[[#This Row],[PENDIENTE GISA]]+Tabla5[[#This Row],[PENDIENTE MULTIBANK]]+Tabla5[[#This Row],[PENDIENTE GASTOS LEGALES]]+Tabla5[[#This Row],[FONDO ADM PENDIENTE]]+Tabla5[[#This Row],[MEDIDOR PENDIENTE]]+Tabla5[[#This Row],[PENALIZACIÓN PENDIENTE]] -> #VALUE! | G46: ='BASE DATOS'!AE45 -> 180000 | H46: =SUMIFS(Tabla35[Abonos],Tabla35[Lote],B46,Tabla35[Cliente],C46,Tabla35[Concepto],"ABONO") -> 80000 | I46: =G46-H46 -> 100000 | J46: ='BASE DATOS'!AF45 -> 0 | K46: =SUMIFS(Tabla35[Abonos],Tabla35[Lote],B46,Tabla35[Cliente],C46,Tabla35[Concepto],"MULTIBANK") -> 0 | L46: =J46-K46 -> 0 | M46: ='BASE DATOS'!AV45 -> BANCO | N46: =SUMIFS(Tabla35[Abonos],Tabla35[Lote],B46,Tabla35[Cliente],C46,Tabla35[Concepto],"GASTOS LEGALES") -> 0 | O46: =M46-N46 -> #VALUE! | P46: 500 | Q46: =SUMIFS(Tabla35[Abonos],Tabla35[Lote],B46,Tabla35[Cliente],C46,Tabla35[Concepto],"FONDO ADM") -> 0 | R46: =P46-Q46 -> 500 | S46: 300 | T46: =SUMIFS(Tabla35[Abonos],Tabla35[Lote],B46,Tabla35[Cliente],C46,Tabla35[Concepto],"MEDIDOR") -> 0 | U46: =S46-T46 -> 300 | W46: =SUMIFS(Tabla35[Abonos],Tabla35[Lote],B46,Tabla35[Cliente],C46,Tabla35[Concepto],"PENALIZACIÓN") -> 0 | X46: =V46-W46 -> 0
B47: L-211 | C47: ='BASE DATOS'!C46 -> MICHAEL RIVAS | D47: ='BASE DATOS'!AA46 -> 143389.44 | E47: =I47+L47 -> 0 | F47: =Tabla5[[#This Row],[PENDIENTE GISA]]+Tabla5[[#This Row],[PENDIENTE MULTIBANK]]+Tabla5[[#This Row],[PENDIENTE GASTOS LEGALES]]+Tabla5[[#This Row],[FONDO ADM PENDIENTE]]+Tabla5[[#This Row],[MEDIDOR PENDIENTE]]+Tabla5[[#This Row],[PENALIZACIÓN PENDIENTE]] -> 3300 | G47: ='BASE DATOS'!AE46 -> 17000 | H47: =SUMIFS(Tabla35[Abonos],Tabla35[Lote],B47,Tabla35[Cliente],C47,Tabla35[Concepto],"ABONO") -> 17000 | I47: =G47-H47 -> 0 | J47: ='BASE DATOS'!AF46 -> 126389.44 | K47: =SUMIFS(Tabla35[Abonos],Tabla35[Lote],B47,Tabla35[Cliente],C47,Tabla35[Concepto],"MULTIBANK") -> 126389.44 | L47: =J47-K47 -> 0 | M47: 0 | N47: =SUMIFS(Tabla35[Abonos],Tabla35[Lote],B47,Tabla35[Cliente],C47,Tabla35[Concepto],"GASTOS LEGALES") -> 0 | O47: =M47-N47 -> 0 | P47: 500 | Q47: =SUMIFS(Tabla35[Abonos],Tabla35[Lote],B47,Tabla35[Cliente],C47,Tabla35[Concepto],"FONDO ADM") -> 500 | R47: =P47-Q47 -> 0 | S47: 300 | T47: =SUMIFS(Tabla35[Abonos],Tabla35[Lote],B47,Tabla35[Cliente],C47,Tabla35[Concepto],"MEDIDOR") -> 300 | U47: =S47-T47 -> 0 | V47: 5000 | W47: =SUMIFS(Tabla35[Abonos],Tabla35[Lote],B47,Tabla35[Cliente],C47,Tabla35[Concepto],"PENALIZACIÓN") -> 1700 | X47: =V47-W47 -> 3300
B48: L-212 | C48: ='BASE DATOS'!C47 -> ALESSANDRO GANCI CERRUD | D48: ='BASE DATOS'!AA47 -> 185000 | E48: =I48+L48 -> 0 | F48: =Tabla5[[#This Row],[PENDIENTE GISA]]+Tabla5[[#This Row],[PENDIENTE MULTIBANK]]+Tabla5[[#This Row],[PENDIENTE GASTOS LEGALES]]+Tabla5[[#This Row],[FONDO ADM PENDIENTE]]+Tabla5[[#This Row],[MEDIDOR PENDIENTE]]+Tabla5[[#This Row],[PENALIZACIÓN PENDIENTE]] -> 0 | G48: ='BASE DATOS'!AE47 -> 14801 | H48: =SUMIFS(Tabla35[Abonos],Tabla35[Lote],B48,Tabla35[Cliente],C48,Tabla35[Concepto],"ABONO") -> 14801 | I48: =G48-H48 -> 0 | J48: ='BASE DATOS'!AF47 -> 170199 | K48: =SUMIFS(Tabla35[Abonos],Tabla35[Lote],B48,Tabla35[Cliente],C48,Tabla35[Concepto],"MULTIBANK") -> 170199 | L48: =J48-K48 -> 0 | M48: 0 | N48: =SUMIFS(Tabla35[Abonos],Tabla35[Lote],B48,Tabla35[Cliente],C48,Tabla35[Concepto],"GASTOS LEGALES") -> 0 | O48: =M48-N48 -> 0 | P48: 500 | Q48: =SUMIFS(Tabla35[Abonos],Tabla35[Lote],B48,Tabla35[Cliente],C48,Tabla35[Concepto],"FONDO ADM") -> 500 | R48: =P48-Q48 -> 0 | S48: 300 | T48: =SUMIFS(Tabla35[Abonos],Tabla35[Lote],B48,Tabla35[Cliente],C48,Tabla35[Concepto],"MEDIDOR") -> 300 | U48: =S48-T48 -> 0 | W48: =SUMIFS(Tabla35[Abonos],Tabla35[Lote],B48,Tabla35[Cliente],C48,Tabla35[Concepto],"PENALIZACIÓN") -> 0 | X48: =V48-W48 -> 0
B49: L-101 | C49: ='BASE DATOS'!C48 -> 0 | D49: ='BASE DATOS'!AA48 -> 220862.25 | E49: =I49+L49 -> 0 | F49: =Tabla5[[#This Row],[PENDIENTE GISA]]+Tabla5[[#This Row],[PENDIENTE MULTIBANK]]+Tabla5[[#This Row],[PENDIENTE GASTOS LEGALES]]+Tabla5[[#This Row],[FONDO ADM PENDIENTE]]+Tabla5[[#This Row],[MEDIDOR PENDIENTE]]+Tabla5[[#This Row],[PENALIZACIÓN PENDIENTE]] -> 800 | G49: ='BASE DATOS'!AE48 -> 0 | H49: =SUMIFS(Tabla35[Abonos],Tabla35[Lote],B49,Tabla35[Cliente],C49,Tabla35[Concepto],"ABONO") -> 0 | I49: =G49-H49 -> 0 | J49: ='BASE DATOS'!AF48 -> 0 | K49: =SUMIFS(Tabla35[Abonos],Tabla35[Lote],B49,Tabla35[Cliente],C49,Tabla35[Concepto],"MULTIBANK") -> 0 | L49: =J49-K49 -> 0 | M49: ='BASE DATOS'!AV48 -> 0 | N49: =SUMIFS(Tabla35[Abonos],Tabla35[Lote],B49,Tabla35[Cliente],C49,Tabla35[Concepto],"GASTOS LEGALES") -> 0 | O49: =M49-N49 -> 0 | P49: 500 | Q49: =SUMIFS(Tabla35[Abonos],Tabla35[Lote],B49,Tabla35[Cliente],C49,Tabla35[Concepto],"FONDO ADM") -> 0 | R49: =P49-Q49 -> 500 | S49: 300 | T49: =SUMIFS(Tabla35[Abonos],Tabla35[Lote],B49,Tabla35[Cliente],C49,Tabla35[Concepto],"MEDIDOR") -> 0 | U49: =S49-T49 -> 300 | W49: =SUMIFS(Tabla35[Abonos],Tabla35[Lote],B49,Tabla35[Cliente],C49,Tabla35[Concepto],"PENALIZACIÓN") -> 0 | X49: =V49-W49 -> 0
B50: L-102 | C50: ='BASE DATOS'!C49 -> PAUL HINSHAW | D50: ='BASE DATOS'!AA49 -> 182000 | E50: =I50+L50 -> 0 | F50: =Tabla5[[#This Row],[PENDIENTE GISA]]+Tabla5[[#This Row],[PENDIENTE MULTIBANK]]+Tabla5[[#This Row],[PENDIENTE GASTOS LEGALES]]+Tabla5[[#This Row],[FONDO ADM PENDIENTE]]+Tabla5[[#This Row],[MEDIDOR PENDIENTE]]+Tabla5[[#This Row],[PENALIZACIÓN PENDIENTE]] -> 0 | G50: ='BASE DATOS'!AE49 -> 182000 | H50: =SUMIFS(Tabla35[Abonos],Tabla35[Lote],B50,Tabla35[Cliente],C50,Tabla35[Concepto],"ABONO") -> 182000 | I50: =G50-H50 -> 0 | J50: ='BASE DATOS'!AF49 -> 0 | K50: =SUMIFS(Tabla35[Abonos],Tabla35[Lote],B50,Tabla35[Cliente],C50,Tabla35[Concepto],"MULTIBANK") -> 0 | L50: =J50-K50 -> 0 | M50: ='BASE DATOS'!AV49 -> 1704 | N50: =SUMIFS(Tabla35[Abonos],Tabla35[Lote],B50,Tabla35[Cliente],C50,Tabla35[Concepto],"GASTOS LEGALES") -> 1704 | O50: =M50-N50 -> 0 | P50: 500 | Q50: =SUMIFS(Tabla35[Abonos],Tabla35[Lote],B50,Tabla35[Cliente],C50,Tabla35[Concepto],"FONDO ADM") -> 500 | R50: =P50-Q50 -> 0 | S50: 300 | T50: =SUMIFS(Tabla35[Abonos],Tabla35[Lote],B50,Tabla35[Cliente],C50,Tabla35[Concepto],"MEDIDOR") -> 300 | U50: =S50-T50 -> 0 | W50: =SUMIFS(Tabla35[Abonos],Tabla35[Lote],B50,Tabla35[Cliente],C50,Tabla35[Concepto],"PENALIZACIÓN") -> 0 | X50: =V50-W50 -> 0
B51: L-103 | C51: ='BASE DATOS'!C50 -> ALLISON SMITH HARRIS | D51: ='BASE DATOS'!AA50 -> 236000 | E51: =I51+L51 -> 0 | F51: =Tabla5[[#This Row],[PENDIENTE GISA]]+Tabla5[[#This Row],[PENDIENTE MULTIBANK]]+Tabla5[[#This Row],[PENDIENTE GASTOS LEGALES]]+Tabla5[[#This Row],[FONDO ADM PENDIENTE]]+Tabla5[[#This Row],[MEDIDOR PENDIENTE]]+Tabla5[[#This Row],[PENALIZACIÓN PENDIENTE]] -> 0 | G51: ='BASE DATOS'!AE50 -> 68700 | H51: =SUMIFS(Tabla35[Abonos],Tabla35[Lote],B51,Tabla35[Cliente],C51,Tabla35[Concepto],"ABONO") -> 68700 | I51: =G51-H51 -> 0 | J51: ='BASE DATOS'!AF50 -> 167300 | K51: =SUMIFS(Tabla35[Abonos],Tabla35[Lote],B51,Tabla35[Cliente],C51,Tabla35[Concepto],"MULTIBANK") -> 167300 | L51: =J51-K51 -> 0 | M51: 0 | N51: =SUMIFS(Tabla35[Abonos],Tabla35[Lote],B51,Tabla35[Cliente],C51,Tabla35[Concepto],"GASTOS LEGALES") -> 0 | O51: =M51-N51 -> 0 | P51: 500 | Q51: =SUMIFS(Tabla35[Abonos],Tabla35[Lote],B51,Tabla35[Cliente],C51,Tabla35[Concepto],"FONDO ADM") -> 500 | R51: =P51-Q51 -> 0 | S51: 300 | T51: =SUMIFS(Tabla35[Abonos],Tabla35[Lote],B51,Tabla35[Cliente],C51,Tabla35[Concepto],"MEDIDOR") -> 300 | U51: =S51-T51 -> 0 | W51: =SUMIFS(Tabla35[Abonos],Tabla35[Lote],B51,Tabla35[Cliente],C51,Tabla35[Concepto],"PENALIZACIÓN") -> 0 | X51: =V51-W51 -> 0
B52: L-104 | C52: ='BASE DATOS'!C51 -> PEDRO GALVEZ | D52: ='BASE DATOS'!AA51 -> 212650 | E52: =I52+L52 -> 0 | F52: =Tabla5[[#This Row],[PENDIENTE GISA]]+Tabla5[[#This Row],[PENDIENTE MULTIBANK]]+Tabla5[[#This Row],[PENDIENTE GASTOS LEGALES]]+Tabla5[[#This Row],[FONDO ADM PENDIENTE]]+Tabla5[[#This Row],[MEDIDOR PENDIENTE]]+Tabla5[[#This Row],[PENALIZACIÓN PENDIENTE]] -> 0 | G52: ='BASE DATOS'!AE51 -> 74427.5 | H52: =SUMIFS(Tabla35[Abonos],Tabla35[Lote],B52,Tabla35[Cliente],C52,Tabla35[Concepto],"ABONO") -> 74427.5 | I52: =G52-H52 -> 0 | J52: ='BASE DATOS'!AF51 -> 138222.5 | K52: =SUMIFS(Tabla35[Abonos],Tabla35[Lote],B52,Tabla35[Cliente],C52,Tabla35[Concepto],"MULTIBANK") -> 138222.5 | L52: =J52-K52 -> 0 | M52: 0 | N52: =SUMIFS(Tabla35[Abonos],Tabla35[Lote],B52,Tabla35[Cliente],C52,Tabla35[Concepto],"GASTOS LEGALES") -> 0 | O52: =M52-N52 -> 0 | P52: 500 | Q52: =SUMIFS(Tabla35[Abonos],Tabla35[Lote],B52,Tabla35[Cliente],C52,Tabla35[Concepto],"FONDO ADM") -> 500 | R52: =P52-Q52 -> 0 | S52: 300 | T52: =SUMIFS(Tabla35[Abonos],Tabla35[Lote],B52,Tabla35[Cliente],C52,Tabla35[Concepto],"MEDIDOR") -> 300 | U52: =S52-T52 -> 0 | W52: =SUMIFS(Tabla35[Abonos],Tabla35[Lote],B52,Tabla35[Cliente],C52,Tabla35[Concepto],"PENALIZACIÓN") -> 0 | X52: =V52-W52 -> 0
B53: L-105 | C53: ='BASE DATOS'!C52 -> 0 | D53: ='BASE DATOS'!AA52 -> 250000 | E53: =I53+L53 -> 0 | F53: =Tabla5[[#This Row],[PENDIENTE GISA]]+Tabla5[[#This Row],[PENDIENTE MULTIBANK]]+Tabla5[[#This Row],[PENDIENTE GASTOS LEGALES]]+Tabla5[[#This Row],[FONDO ADM PENDIENTE]]+Tabla5[[#This Row],[MEDIDOR PENDIENTE]]+Tabla5[[#This Row],[PENALIZACIÓN PENDIENTE]] -> 800 | G53: ='BASE DATOS'!AE52 -> 0 | H53: =SUMIFS(Tabla35[Abonos],Tabla35[Lote],B53,Tabla35[Cliente],C53,Tabla35[Concepto],"ABONO") -> 0 | I53: =G53-H53 -> 0 | J53: ='BASE DATOS'!AF52 -> 0 | K53: =SUMIFS(Tabla35[Abonos],Tabla35[Lote],B53,Tabla35[Cliente],C53,Tabla35[Concepto],"MULTIBANK") -> 0 | L53: =J53-K53 -> 0 | M53: ='BASE DATOS'!AV52 -> 0 | N53: =SUMIFS(Tabla35[Abonos],Tabla35[Lote],B53,Tabla35[Cliente],C53,Tabla35[Concepto],"GASTOS LEGALES") -> 0 | O53: =M53-N53 -> 0 | P53: 500 | Q53: =SUMIFS(Tabla35[Abonos],Tabla35[Lote],B53,Tabla35[Cliente],C53,Tabla35[Concepto],"FONDO ADM") -> 0 | R53: =P53-Q53 -> 500 | S53: 300 | T53: =SUMIFS(Tabla35[Abonos],Tabla35[Lote],B53,Tabla35[Cliente],C53,Tabla35[Concepto],"MEDIDOR") -> 0 | U53: =S53-T53 -> 300 | W53: =SUMIFS(Tabla35[Abonos],Tabla35[Lote],B53,Tabla35[Cliente],C53,Tabla35[Concepto],"PENALIZACIÓN") -> 0 | X53: =V53-W53 -> 0
B54: L-106 | C54: ='BASE DATOS'!C53 -> SANDRA KAVANAUGH | D54: ='BASE DATOS'!AA53 -> 250000 | E54: =I54+L54 -> 0 | F54: =Tabla5[[#This Row],[PENDIENTE GISA]]+Tabla5[[#This Row],[PENDIENTE MULTIBANK]]+Tabla5[[#This Row],[PENDIENTE GASTOS LEGALES]]+Tabla5[[#This Row],[FONDO ADM PENDIENTE]]+Tabla5[[#This Row],[MEDIDOR PENDIENTE]]+Tabla5[[#This Row],[PENALIZACIÓN PENDIENTE]] -> 0 | G54: ='BASE DATOS'!AE53 -> 75000 | H54: =SUMIFS(Tabla35[Abonos],Tabla35[Lote],B54,Tabla35[Cliente],C54,Tabla35[Concepto],"ABONO") -> 75000 | I54: =G54-H54 -> 0 | J54: ='BASE DATOS'!AF53 -> 175000 | K54: =SUMIFS(Tabla35[Abonos],Tabla35[Lote],B54,Tabla35[Cliente],C54,Tabla35[Concepto],"MULTIBANK") -> 175000 | L54: =J54-K54 -> 0 | M54: ='BASE DATOS'!AV53 -> 2100 | N54: =SUMIFS(Tabla35[Abonos],Tabla35[Lote],B54,Tabla35[Cliente],C54,Tabla35[Concepto],"GASTOS LEGALES") -> 2100 | O54: =M54-N54 -> 0 | P54: 500 | Q54: =SUMIFS(Tabla35[Abonos],Tabla35[Lote],B54,Tabla35[Cliente],C54,Tabla35[Concepto],"FONDO ADM") -> 500 | R54: =P54-Q54 -> 0 | S54: 300 | T54: =SUMIFS(Tabla35[Abonos],Tabla35[Lote],B54,Tabla35[Cliente],C54,Tabla35[Concepto],"MEDIDOR") -> 300 | U54: =S54-T54 -> 0 | W54: =SUMIFS(Tabla35[Abonos],Tabla35[Lote],B54,Tabla35[Cliente],C54,Tabla35[Concepto],"PENALIZACIÓN") -> 0 | X54: =V54-W54 -> 0
B55: L-107 | C55: ='BASE DATOS'!C54 -> ADELI ZAVALETA | D55: ='BASE DATOS'!AA54 -> 220000 | E55: =I55+L55 -> 110000 | F55: =Tabla5[[#This Row],[PENDIENTE GISA]]+Tabla5[[#This Row],[PENDIENTE MULTIBANK]]+Tabla5[[#This Row],[PENDIENTE GASTOS LEGALES]]+Tabla5[[#This Row],[FONDO ADM PENDIENTE]]+Tabla5[[#This Row],[MEDIDOR PENDIENTE]]+Tabla5[[#This Row],[PENALIZACIÓN PENDIENTE]] -> 110250 | G55: ='BASE DATOS'!AE54 -> 220000 | H55: =SUMIFS(Tabla35[Abonos],Tabla35[Lote],B55,Tabla35[Cliente],C55,Tabla35[Concepto],"ABONO") -> 110000 | I55: =G55-H55 -> 110000 | J55: ='BASE DATOS'!AF54 -> 0 | K55: =SUMIFS(Tabla35[Abonos],Tabla35[Lote],B55,Tabla35[Cliente],C55,Tabla35[Concepto],"MULTIBANK") -> 0 | L55: =J55-K55 -> 0 | M55: ='BASE DATOS'!AV54 -> 0 | N55: =SUMIFS(Tabla35[Abonos],Tabla35[Lote],B55,Tabla35[Cliente],C55,Tabla35[Concepto],"GASTOS LEGALES") -> 0 | O55: =M55-N55 -> 0 | P55: 500 | Q55: =SUMIFS(Tabla35[Abonos],Tabla35[Lote],B55,Tabla35[Cliente],C55,Tabla35[Concepto],"FONDO ADM") -> 250 | R55: =P55-Q55 -> 250 | S55: 300 | T55: =SUMIFS(Tabla35[Abonos],Tabla35[Lote],B55,Tabla35[Cliente],C55,Tabla35[Concepto],"MEDIDOR") -> 300 | U55: =S55-T55 -> 0 | W55: =SUMIFS(Tabla35[Abonos],Tabla35[Lote],B55,Tabla35[Cliente],C55,Tabla35[Concepto],"PENALIZACIÓN") -> 0 | X55: =V55-W55 -> 0
B56: L-108 | C56: ='BASE DATOS'!C55 -> ADELI ZAVALETA | D56: ='BASE DATOS'!AA55 -> 217000 | E56: =I56+L56 -> 214000 | F56: =Tabla5[[#This Row],[PENDIENTE GISA]]+Tabla5[[#This Row],[PENDIENTE MULTIBANK]]+Tabla5[[#This Row],[PENDIENTE GASTOS LEGALES]]+Tabla5[[#This Row],[FONDO ADM PENDIENTE]]+Tabla5[[#This Row],[MEDIDOR PENDIENTE]]+Tabla5[[#This Row],[PENALIZACIÓN PENDIENTE]] -> 214800 | G56: ='BASE DATOS'!AE55 -> 217000 | H56: =SUMIFS(Tabla35[Abonos],Tabla35[Lote],B56,Tabla35[Cliente],C56,Tabla35[Concepto],"ABONO") -> 3000 | I56: =G56-H56 -> 214000 | J56: ='BASE DATOS'!AF55 -> 0 | K56: =SUMIFS(Tabla35[Abonos],Tabla35[Lote],B56,Tabla35[Cliente],C56,Tabla35[Concepto],"MULTIBANK") -> 0 | L56: =J56-K56 -> 0 | M56: ='BASE DATOS'!AV55 -> 0 | N56: =SUMIFS(Tabla35[Abonos],Tabla35[Lote],B56,Tabla35[Cliente],C56,Tabla35[Concepto],"GASTOS LEGALES") -> 0 | O56: =M56-N56 -> 0 | P56: 500 | Q56: =SUMIFS(Tabla35[Abonos],Tabla35[Lote],B56,Tabla35[Cliente],C56,Tabla35[Concepto],"FONDO ADM") -> 0 | R56: =P56-Q56 -> 500 | S56: 300 | T56: =SUMIFS(Tabla35[Abonos],Tabla35[Lote],B56,Tabla35[Cliente],C56,Tabla35[Concepto],"MEDIDOR") -> 0 | U56: =S56-T56 -> 300 | W56: =SUMIFS(Tabla35[Abonos],Tabla35[Lote],B56,Tabla35[Cliente],C56,Tabla35[Concepto],"PENALIZACIÓN") -> 0 | X56: =V56-W56 -> 0
B57: L-109 | C57: ='BASE DATOS'!C56 -> CARMEN BERNASCONI | D57: ='BASE DATOS'!AA56 -> 221338.98 | E57: =I57+L57 -> 0 | F57: =Tabla5[[#This Row],[PENDIENTE GISA]]+Tabla5[[#This Row],[PENDIENTE MULTIBANK]]+Tabla5[[#This Row],[PENDIENTE GASTOS LEGALES]]+Tabla5[[#This Row],[FONDO ADM PENDIENTE]]+Tabla5[[#This Row],[MEDIDOR PENDIENTE]]+Tabla5[[#This Row],[PENALIZACIÓN PENDIENTE]] -> 57.1 | G57: ='BASE DATOS'!AE56 -> 221338.98 | H57: =SUMIFS(Tabla35[Abonos],Tabla35[Lote],B57,Tabla35[Cliente],C57,Tabla35[Concepto],"ABONO") -> 221338.98 | I57: =G57-H57 -> 0 | J57: ='BASE DATOS'!AF56 -> 0 | K57: =SUMIFS(Tabla35[Abonos],Tabla35[Lote],B57,Tabla35[Cliente],C57,Tabla35[Concepto],"MULTIBANK") -> 0 | L57: =J57-K57 -> 0 | M57: ='BASE DATOS'!AV56 -> 1824 | N57: =SUMIFS(Tabla35[Abonos],Tabla35[Lote],B57,Tabla35[Cliente],C57,Tabla35[Concepto],"GASTOS LEGALES") -> 1766.9 | O57: =M57-N57 -> 57.1 | P57: 500 | Q57: =SUMIFS(Tabla35[Abonos],Tabla35[Lote],B57,Tabla35[Cliente],C57,Tabla35[Concepto],"FONDO ADM") -> 500 | R57: =P57-Q57 -> 0 | S57: 300 | T57: =SUMIFS(Tabla35[Abonos],Tabla35[Lote],B57,Tabla35[Cliente],C57,Tabla35[Concepto],"MEDIDOR") -> 300 | U57: =S57-T57 -> 0 | W57: =SUMIFS(Tabla35[Abonos],Tabla35[Lote],B57,Tabla35[Cliente],C57,Tabla35[Concepto],"PENALIZACIÓN") -> 0 | X57: =V57-W57 -> 0
B58: L-110 | C58: ='BASE DATOS'!C57 -> 0 | D58: ='BASE DATOS'!AA57 -> 204000 | E58: =I58+L58 -> 0 | F58: =Tabla5[[#This Row],[PENDIENTE GISA]]+Tabla5[[#This Row],[PENDIENTE MULTIBANK]]+Tabla5[[#This Row],[PENDIENTE GASTOS LEGALES]]+Tabla5[[#This Row],[FONDO ADM PENDIENTE]]+Tabla5[[#This Row],[MEDIDOR PENDIENTE]]+Tabla5[[#This Row],[PENALIZACIÓN PENDIENTE]] -> 800 | G58: ='BASE DATOS'!AE57 -> 0 | H58: =SUMIFS(Tabla35[Abonos],Tabla35[Lote],B58,Tabla35[Cliente],C58,Tabla35[Concepto],"ABONO") -> 0 | I58: =G58-H58 -> 0 | J58: ='BASE DATOS'!AF57 -> 0 | K58: =SUMIFS(Tabla35[Abonos],Tabla35[Lote],B58,Tabla35[Cliente],C58,Tabla35[Concepto],"MULTIBANK") -> 0 | L58: =J58-K58 -> 0 | M58: ='BASE DATOS'!AV57 -> 0 | N58: =SUMIFS(Tabla35[Abonos],Tabla35[Lote],B58,Tabla35[Cliente],C58,Tabla35[Concepto],"GASTOS LEGALES") -> 0 | O58: =M58-N58 -> 0 | P58: 500 | Q58: =SUMIFS(Tabla35[Abonos],Tabla35[Lote],B58,Tabla35[Cliente],C58,Tabla35[Concepto],"FONDO ADM") -> 0 | R58: =P58-Q58 -> 500 | S58: 300 | T58: =SUMIFS(Tabla35[Abonos],Tabla35[Lote],B58,Tabla35[Cliente],C58,Tabla35[Concepto],"MEDIDOR") -> 0 | U58: =S58-T58 -> 300 | W58: =SUMIFS(Tabla35[Abonos],Tabla35[Lote],B58,Tabla35[Cliente],C58,Tabla35[Concepto],"PENALIZACIÓN") -> 0 | X58: =V58-W58 -> 0
